Workbook
Name a: #REF!
Name a: Demande_alea!$D1
Name b: #REF!
Name b: Demande_alea!$E1
Name d: #REF!
Name d: Demande_alea!$H1
Name f: #REF!
Name f: Demande_alea!$F1
Name k: #REF!
Name k: Demande_alea!$G1
Name s: #REF!
Name s: Demande_alea!$I1
Name t: #REF!
Name t: Demande_alea!A$2

Sheet Account
A1: <Nom> | B1: Account | Q1: /Fin/
Q2: /Fin/
A3: <Process> | B3: résultat courant | C3: cumulative result | D3: cumulative result | Q3: /Fin/
A4: emprunt 0,4% par semaine | B4: 1 | C4: -1 | D4: -0.204 | Q4: /Fin/
A5: <Periode_Debut> | B5: 0 | C5: 0 | D5: 1 | Q5: /Fin/
A6: <Periode_Prolongement> | B6: 0 | C6: 0 | D6: 4 | Q6: /Fin/
A7: <Source> | B7: Account | C7: Account | D7: Account | Q7: /Fin/
Q8: /Fin/
A9: <Etat des lieux> | B9: <Minimal> | C9: <Maximal> | D9: 0 | E9: 1 | F9: 2 | G9: 3 | H9: 4 | I9: 5 | J9: 6 | K9: 7 | L9: 8 | M9: 9 | N9: 10 | O9: 11 | P9: 12 | Q9: /Fin/
A10: cumulative result | B10: -1000000000000 | C10: =-B10 -> 1000000000000 | D10: 0 | E10: 11454.5 | F10: -55172 | G10: -90658 | H10: -94258 | I10: -94258 | J10: -94258 | K10: -94258 | L10: -94258 | M10: -94258 | N10: -94258 | O10: -94258 | P10: -94258 | Q10: /Fin/
A11: cumulative CO2 | B11: =B10 -> -1000000000000 | C11: =-B11 -> 1000000000000 | D11: 0 | E11: 340808.32 | F11: 722862.96 | Q11: /Fin/
Q12: /Fin/
A13: /Fin/ | B13: /Fin/ | C13: /Fin/ | D13: /Fin/ | E13: /Fin/ | F13: /Fin/ | G13: /Fin/ | H13: /Fin/ | I13: /Fin/ | J13: /Fin/ | K13: /Fin/ | L13: /Fin/ | M13: /Fin/ | N13: /Fin/ | O13: /Fin/ | P13: /Fin/ | Q13: /Fin/

Sheet Arnhem
A1: <Nom> | B1: Arnhem factory | E1: Période | F1: 1 | S1: /Fin/
S2: /Fin/
A3: <Process> | B3: nectar (pallet) | C3: nectar (vat) | D3: pack (batch) | E3: Time not used | F3: Time not used | G3: production cost (wages excluded) | H3: production cost (wages excluded) | I3: CO2 production | J3: CO2 production | K3: cost of nectar pallets storage | L3: cost of nectar vats storage | M3: pack storage cost | N3: cumulative result | O3: cumulative result | P3: cumulative result | Q3: cumulative CO2 | S3: /Fin/
A4: Nectar packaging | B4: 30 | C4: -1 | D4: -1 | E4: -20 | F4: =-E4 -> 20 | G4: 100 | H4: =-G4 -> -100 | I4: 500 | J4: =-I4 -> -500 | K4: =18000*0.02 -> 360 | L4: -330 | M4: =1000*0.02*D4 -> -20 | N4: =-G4 -> -100 | O4: =-K4 -> -360 | P4: =-(L4+M4) -> 350 | Q4: =I4 -> 500 | S4: /Fin/
A5: <Periode_Debut> | B5: 0 | C5: 0 | D5: 0 | E5: 0 | F5: 1 | G5: 0 | H5: 1 | I5: 0 | J5: 1 | K5: 1 | L5: 0 | M5: 0 | N5: 0 | O5: 1 | P5: 0 | Q5: 0 | S5: /Fin/
A6: <Periode_Prolongement> | B6: 0 | C6: 0 | D6: 0 | E6: 0 | F6: 0 | G6: 0 | H6: 0 | I6: 0 | J6: 0 | K6: 0 | L6: 0 | M6: 0 | N6: 0 | O6: 20 | P6: 20 | Q6: 0 | S6: /Fin/
A7: <Source> | B7: Arnhem factory | C7: Arnhem factory | D7: Arnhem factory | E7: Arnhem factory | F7: Arnhem factory | G7: Arnhem factory | H7: Arnhem factory | I7: Arnhem factory | J7: Arnhem factory | K7: Arnhem factory | L7: Arnhem factory | M7: Arnhem factory | N7: Account | O7: Account | P7: Account | Q7: Account | S7: /Fin/
S8: /Fin/
A9: <Process> | B9: nectar (vat) | C9: concentrate (bin) | D9: puree (bin) | E9: Time not used | F9: Time not used | G9: production cost (wages excluded) | H9: production cost (wages excluded) | I9: CO2 production | J9: CO2 production | K9: cost of nectar vats storage | L9: concentrate storage cost | M9: puree storage cost | N9: cumulative result | O9: cumulative result | P9: cumulative result | Q9: cumulative CO2 | S9: /Fin/
A10: Nectar production | B10: 1 | C10: -1 | D10: -5 | E10: -100 | F10: =-E10 -> 100 | G10: 300 | H10: =-G10 -> -300 | I10: 2000 | J10: =-I10 -> -2000 | K10: 330 | L10: =64*C10 -> -64 | M10: =2200*0.02*D10 -> -220 | N10: =-G10 -> -300 | O10: =-K10 -> -330 | P10: =-(L10+M10) -> 284 | Q10: =I10 -> 2000 | S10: /Fin/
A11: <Periode_Debut> | B11: 0 | C11: 0 | D11: 0 | E11: 0 | F11: 1 | G11: 0 | H11: 1 | I11: 0 | J11: 1 | K11: 1 | L11: 0 | M11: 0 | N11: 0 | O11: 1 | P11: 0 | Q11: 0 | S11: /Fin/
A12: <Periode_Prolongement> | B12: 0 | C12: 0 | D12: 0 | E12: 0 | F12: 0 | G12: 0 | H12: 0 | I12: 0 | J12: 0 | K12: 0 | L12: 0 | M12: 0 | N12: 0 | O12: 20 | P12: 20 | Q12: 0 | S12: /Fin/
A13: <Source> | B13: Arnhem factory | C13: Arnhem factory | D13: Arnhem factory | E13: Arnhem factory | F13: Arnhem factory | G13: Arnhem factory | H13: Arnhem factory | I13: Arnhem factory | J13: Arnhem factory | K13: Arnhem factory | L13: Arnhem factory | M13: Arnhem factory | N13: Account | O13: Account | P13: Account | Q13: Account | S13: /Fin/
S14: /Fin/
A15: <Process> | B15: staff | C15: Time not used | D15: Hiring cost | E15: Hiring cost | F15: wages cost | G15: cumulative result | H15: cumulative result | S15: /Fin/
A16: Hiring | B16: 1 | C16: 150 | D16: 2000 | E16: =-D16 -> -2000 | F16: 3000 | G16: =-D16 -> -2000 | H16: =-F16 -> -3000 | S16: /Fin/
A17: <Periode_Debut> | B17: 0 | C17: 1 | D17: 0 | E17: 1 | F17: 1 | G17: 0 | H17: 1 | S17: /Fin/
A18: <Periode_Prolongement> | B18: 0 | C18: 0 | D18: 0 | E18: 0 | F18: 0 | G18: 0 | H18: 20 | S18: /Fin/
A19: <Source> | B19: Arnhem factory | C19: Arnhem factory | D19: Arnhem factory | E19: Arnhem factory | F19: Arnhem factory | G19: Account | H19: Account | S19: /Fin/
S20: /Fin/
A21: <Process> | B21: staff | C21: Time not used | D21: Laying-off cost | E21: Laying-off cost | F21: wages cost | G21: cumulative result | H21: cumulative result | S21: /Fin/
A22: Laying-off | B22: -1 | C22: -150 | D22: 2000 | E22: =-D22 -> -2000 | F22: -3000 | G22: =-D22 -> -2000 | H22: =-F22 -> 3000 | S22: /Fin/
A23: <Periode_Debut> | B23: 0 | C23: 1 | D23: 0 | E23: 1 | F23: 1 | G23: 0 | H23: 1 | S23: /Fin/
A24: <Periode_Prolongement> | B24: 0 | C24: 0 | D24: 0 | E24: 0 | F24: 0 | G24: 0 | H24: 20 | S24: /Fin/
A25: <Source> | B25: Arnhem factory | C25: Arnhem factory | D25: Arnhem factory | E25: Arnhem factory | F25: Arnhem factory | G25: Account | H25: Account | S25: /Fin/
S26: /Fin/
A27: <Etat des lieux> | B27: <Minimal> | C27: <Maximal> | D27: 0 | E27: 1 | F27: 2 | G27: 3 | H27: 4 | I27: 5 | J27: 6 | K27: 7 | L27: 8 | M27: 9 | N27: 10 | O27: 11 | P27: 12 | S27: /Fin/
A28: nectar (pallet) | B28: 0 | C28: 750 | D28: 300 | E28: 472 | F28: 282 | S28: /Fin/
A29: nectar (vat) | B29: 0 | C29: 160 | D29: 10 | E29: 7 | F29: 7 | S29: /Fin/
A30: cordial (pallet) | B30: 0 | C30: 750 | E30: 0 | F30: 0 | S30: /Fin/
A31: concentrate (bin) | B31: 0 | C31: 90 | D31: 10 | E31: 13 | F31: 11 | G31: 5 | S31: /Fin/
A32: puree (bin) | B32: 0 | C32: 90 | D32: 50 | E32: 65 | F32: 90 | G32: 60 | S32: /Fin/
A33: pack (batch) | B33: 0 | C33: 90 | D33: 10 | E33: 20 | F33: 23 | S33: /Fin/
A34: staff | B34: 0 | C34: 20 | D34: 6 | E34: 6 | F34: 6 | S34: /Fin/
A35: Time not used | B35: 0 | C35: 1000000000 | D35: 900 | E35: 0 | F35: 60 | G35: 840 | S35: /Fin/
A36: production cost (wages excluded) | B36: -1000000000 | C36: 1000000000 | E36: 3100 | F36: 2800 | G36: -2800 | S36: /Fin/
A37: cost of nectar pallets storage | B37: -1000000000 | C37: 1000000000 | E37: 2064 | F37: 864 | G37: 2520 | S37: /Fin/
A38: cost of nectar vats storage | B38: -1000000000 | C38: 1000000000 | E38: 0 | F38: 0 | G38: 2310 | S38: /Fin/
A39: cost of cordial pallets storage | B39: -1000000000 | C39: 1000000000 | E39: 0 | F39: 0 | S39: /Fin/
A40: concentrate storage cost | B40: -1000000000 | C40: 1000000000 | E40: 192 | F40: 384 | G40: 320 | H40: 320 | S40: /Fin/
A41: puree storage cost | B41: -1000000000 | C41: 1000000000 | E41: 660 | F41: 1320 | G41: 2640 | H41: 2640 | S41: /Fin/
A42: pack storage cost | B42: -1000000000 | C42: 1000000000 | E42: 0 | F42: 260 | G42: 200 | S42: /Fin/
A43: Hiring cost | B43: -1000000000 | C43: 1000000000 | E43: 0 | F43: 0 | G43: 0 | S43: /Fin/
A44: Laying-off cost | B44: -1000000000 | C44: 1000000000 | E44: 0 | F44: 0 | G44: 0 | S44: /Fin/
A45: wages cost | B45: -1000000000 | C45: 1000000000 | E45: 18000 | F45: 18000 | G45: 0 | S45: /Fin/
A46: CO2 production | B46: -1000000000 | C46: 1000000000 | E46: 19000 | F46: 17500 | G46: -17500 | S46: /Fin/
S47: /Fin/
A48: /Fin/ | B48: /Fin/ | C48: /Fin/ | D48: /Fin/ | E48: /Fin/ | F48: /Fin/ | G48: /Fin/ | H48: /Fin/ | I48: /Fin/ | J48: /Fin/ | K48: /Fin/ | L48: /Fin/ | M48: /Fin/ | N48: /Fin/ | O48: /Fin/ | P48: /Fin/ | Q48: /Fin/ | R48: /Fin/ | S48: /Fin/

Sheet Vesoul
A1: <Nom> | B1: Vesoul factory | E1: Période | F1: 1 | S1: /Fin/
S2: /Fin/
A3: <Process> | B3: cordial (pallet) | C3: cordial (vat) | D3: bottle (batch) | E3: Time not used | F3: Time not used | G3: production cost (wages excluded) | H3: production cost (wages excluded) | I3: CO2 production | J3: CO2 production | K3: cost of cordial pallets storage | L3: cost of cordial vats storage | M3: bottles storage cost | N3: cumulative result | O3: cumulative result | P3: cumulative result | Q3: cumulative CO2 | S3: /Fin/
A4: Cordial packaging | B4: 20 | C4: -1 | D4: -1 | E4: -20 | F4: =-E4 -> 20 | G4: 100 | H4: =-G4 -> -100 | I4: 500 | J4: =-I4 -> -500 | K4: 380 | L4: -310 | M4: -60 | N4: =-G4 -> -100 | O4: =-K4 -> -380 | P4: =-(L4+M4) -> 370 | Q4: =I4 -> 500 | S4: /Fin/
A5: <Periode_Debut> | B5: 0 | C5: 0 | D5: 0 | E5: 0 | F5: 1 | G5: 0 | H5: 1 | I5: 0 | J5: 1 | K5: 1 | L5: 0 | M5: 0 | N5: 0 | O5: 1 | P5: 0 | Q5: 0 | S5: /Fin/
A6: <Periode_Prolongement> | B6: 0 | C6: 0 | D6: 0 | E6: 0 | F6: 0 | G6: 0 | H6: 0 | I6: 0 | J6: 0 | K6: 0 | L6: 0 | M6: 0 | N6: 0 | O6: 20 | P6: 20 | Q6: 0 | S6: /Fin/
A7: <Source> | B7: Vesoul factory | C7: Vesoul factory | D7: Vesoul factory | E7: Vesoul factory | F7: Vesoul factory | G7: Vesoul factory | H7: Vesoul factory | I7: Vesoul factory | J7: Vesoul factory | K7: Vesoul factory | L7: Vesoul factory | M7: Vesoul factory | N7: Account | O7: Account | P7: Account | Q7: Account | S7: /Fin/
S8: /Fin/
A9: <Process> | B9: cordial (vat) | C9: concentrate (bin) | D9: sugar (tonne) | E9: Time not used | F9: Time not used | G9: production cost (wages excluded) | H9: production cost (wages excluded) | I9: CO2 production | J9: CO2 production | K9: cost of cordial vats storage | L9: concentrate storage cost | M9: sugar storage cost | N9: cumulative result | O9: cumulative result | P9: cumulative result | Q9: cumulative CO2 | S9: /Fin/
A10: Cordial production | B10: 1 | C10: -4 | D10: -1 | E10: -100 | F10: =-E10 -> 100 | G10: 300 | H10: =-G10 -> -300 | I10: 2000 | J10: =-I10 -> -2000 | K10: 310 | L10: =64*C10 -> -256 | M10: =8*D10 -> -8 | N10: =-G10 -> -300 | O10: =-K10 -> -310 | P10: =-(L10+M10) -> 264 | Q10: =I10 -> 2000 | S10: /Fin/
A11: <Periode_Debut> | B11: 0 | C11: 0 | D11: 0 | E11: 0 | F11: 1 | G11: 0 | H11: 1 | I11: 0 | J11: 1 | K11: 1 | L11: 0 | M11: 0 | N11: 0 | O11: 1 | P11: 0 | Q11: 0 | S11: /Fin/
A12: <Periode_Prolongement> | B12: 0 | C12: 0 | D12: 0 | E12: 0 | F12: 0 | G12: 0 | H12: 0 | I12: 0 | J12: 0 | K12: 0 | L12: 0 | M12: 0 | N12: 0 | O12: 20 | P12: 20 | Q12: 0 | S12: /Fin/
A13: <Source> | B13: Vesoul factory | C13: Vesoul factory | D13: Vesoul factory | E13: Vesoul factory | F13: Vesoul factory | G13: Vesoul factory | H13: Vesoul factory | I13: Vesoul factory | J13: Vesoul factory | K13: Vesoul factory | L13: Vesoul factory | M13: Vesoul factory | N13: Account | O13: Account | P13: Account | Q13: Account | S13: /Fin/
S14: /Fin/
A15: <Process> | B15: staff | C15: Time not used | D15: Hiring cost | E15: Hiring cost | F15: wages cost | G15: cumulative result | H15: cumulative result | S15: /Fin/
A16: Hiring | B16: 1 | C16: 150 | D16: 2000 | E16: =-D16 -> -2000 | F16: 3000 | G16: =-D16 -> -2000 | H16: =-F16 -> -3000 | S16: /Fin/
A17: <Periode_Debut> | B17: 0 | C17: 1 | D17: 0 | E17: 1 | F17: 1 | G17: 0 | H17: 1 | S17: /Fin/
A18: <Periode_Prolongement> | B18: 0 | C18: 0 | D18: 0 | E18: 0 | F18: 0 | G18: 0 | H18: 20 | S18: /Fin/
A19: <Source> | B19: Vesoul factory | C19: Vesoul factory | D19: Vesoul factory | E19: Vesoul factory | F19: Vesoul factory | G19: Account | H19: Account | S19: /Fin/
S20: /Fin/
A21: <Process> | B21: staff | C21: Time not used | D21: Laying-off cost | E21: Laying-off cost | F21: wages cost | G21: cumulative result | H21: cumulative result | S21: /Fin/
A22: Laying-off | B22: -1 | C22: -150 | D22: 2000 | E22: =-D22 -> -2000 | F22: -3000 | G22: =-D22 -> -2000 | H22: =-F22 -> 3000 | S22: /Fin/
A23: <Periode_Debut> | B23: 0 | C23: 1 | D23: 0 | E23: 1 | F23: 1 | G23: 0 | H23: 1 | S23: /Fin/
A24: <Periode_Prolongement> | B24: 0 | C24: 0 | D24: 0 | E24: 0 | F24: 0 | G24: 0 | H24: 20 | S24: /Fin/
A25: <Source> | B25: Vesoul factory | C25: Vesoul factory | D25: Vesoul factory | E25: Vesoul factory | F25: Vesoul factory | G25: Account | H25: Account | S25: /Fin/
S26: /Fin/
A27: <Etat des lieux> | B27: <Minimal> | C27: <Maximal> | D27: 0 | E27: 1 | F27: 2 | G27: 3 | H27: 4 | I27: 5 | J27: 6 | K27: 7 | L27: 8 | M27: 9 | N27: 10 | O27: 11 | P27: 12 | S27: /Fin/
A28: cordial (pallet) | B28: 0 | C28: 750 | D28: 200 | E28: 304 | F28: 185 | S28: /Fin/
A29: cordial (vat) | B29: 0 | C29: 160 | D29: 10 | E29: 7 | F29: 7 | S29: /Fin/
A30: nectar (pallet) | B30: 0 | C30: 750 | E30: 0 | F30: 0 | S30: /Fin/
A31: concentrate (bin) | B31: 0 | C31: 90 | D31: 40 | E31: 52 | F31: 34 | G31: 10 | S31: /Fin/
A32: sugar (tonne) | B32: 0 | C32: 90 | D32: 10 | E32: 23 | F32: 26 | S32: /Fin/
A33: bottle (batch) | B33: 0 | C33: 90 | D33: 10 | E33: 20 | F33: 23 | S33: /Fin/
A34: staff | B34: 0 | C34: 20 | D34: 6 | E34: 6 | F34: 6 | S34: /Fin/
A35: Time not used | B35: 0 | C35: 1000000000 | D35: 900 | E35: 0 | F35: 60 | G35: 840 | S35: /Fin/
A36: production cost (wages excluded) | B36: -1000000000 | C36: 1000000000 | E36: 3100 | F36: 2800 | G36: -2800 | S36: /Fin/
A37: cost of cordial vats storage | B37: -1000000000 | C37: 1000000000 | E37: 0 | F37: 0 | G37: 2170 | S37: /Fin/
A38: cost of cordial pallets storage | B38: -1000000000 | C38: 1000000000 | E38: 1976 | F38: 855 | G38: 2660 | S38: /Fin/
A39: cost of nectar pallets storage | B39: -1000000000 | C39: 1000000000 | E39: 0 | F39: 0 | S39: /Fin/
A40: concentrate storage cost | B40: -1000000000 | C40: 1000000000 | E40: 768 | F40: 1536 | G40: 640 | H40: 640 | S40: /Fin/
A41: sugar storage cost | B41: -1000000000 | C41: 1000000000 | E41: 24 | F41: 128 | G41: 80 | S41: /Fin/
A42: bottles storage cost | B42: -1000000000 | C42: 1000000000 | E42: 0 | F42: 780 | G42: 600 | S42: /Fin/
A43: Hiring cost | B43: -1000000000 | C43: 1000000000 | E43: 0 | F43: 0 | G43: 0 | S43: /Fin/
A44: Laying-off cost | B44: -1000000000 | C44: 1000000000 | E44: 0 | F44: 0 | G44: 0 | S44: /Fin/
A45: wages cost | B45: -1000000000 | C45: 1000000000 | E45: 18000 | F45: 18000 | G45: 0 | S45: /Fin/
A46: CO2 production | B46: -1000000000 | C46: 1000000000 | E46: 19000 | F46: 17500 | G46: -17500 | S46: /Fin/
S47: /Fin/
A48: /Fin/ | B48: /Fin/ | C48: /Fin/ | D48: /Fin/ | E48: /Fin/ | F48: /Fin/ | G48: /Fin/ | H48: /Fin/ | I48: /Fin/ | J48: /Fin/ | K48: /Fin/ | L48: /Fin/ | M48: /Fin/ | N48: /Fin/ | O48: /Fin/ | P48: /Fin/ | Q48: /Fin/ | R48: /Fin/ | S48: /Fin/

Sheet Auckland
A1: <Nom> | B1: Auckland factory | E1: Période | F1: 1 | Q1: /Fin/
Q2: /Fin/
A3: <Process> | B3: concentrate (bin) | C3: puree (bin) | D3: Time not used | E3: Time not used | F3: production cost (wages excluded) | G3: production cost (wages excluded) | H3: CO2 production | I3: CO2 production | J3: concentrate storage cost | K3: puree storage cost | L3: cumulative result | M3: cumulative result | N3: cumulative CO2 | Q3: /Fin/
A4: Purchasing and pression of kiwis | B4: 1 | C4: 4 | D4: -50 | E4: =-D4 -> 50 | F4: 10000 | G4: =-F4 -> -10000 | H4: 10000 | I4: =-H4 -> -10000 | J4: =0.02*3000*B4 -> 60 | K4: =0.02*2000*C4 -> 160 | L4: =-F4 -> -10000 | M4: =-J4-K4 -> -220 | N4: =F4 -> 10000 | Q4: /Fin/
A5: <Periode_Debut> | B5: 0 | C5: 0 | D5: 0 | E5: 1 | F5: 0 | G5: 1 | H5: 0 | I5: 1 | J5: 1 | K5: 1 | L5: 0 | M5: 1 | N5: 0 | Q5: /Fin/
A6: <Periode_Prolongement> | B6: 0 | C6: 0 | D6: 0 | E6: 0 | F6: 0 | G6: 0 | H6: 0 | I6: 0 | J6: 0 | K6: 0 | L6: 0 | M6: 20 | N6: 0 | Q6: /Fin/
A7: <Source> | B7: Auckland factory | C7: Auckland factory | D7: Auckland factory | E7: Auckland factory | F7: Auckland factory | G7: Auckland factory | H7: Auckland factory | I7: Auckland factory | J7: Auckland factory | K7: Auckland factory | L7: Account | M7: Account | N7: Account | Q7: /Fin/
Q8: /Fin/
A9: <Process> | B9: puree (bin) | C9: Puree sale | D9: Puree sale | E9: puree storage cost | F9: cumulative result | G9: cumulative result | Q9: /Fin/
A10: Puree sale | B10: -1 | C10: 2000 | D10: =-C10 -> -2000 | E10: -40 | F10: =C10 -> 2000 | G10: =-E10 -> 40 | Q10: /Fin/
A11: <Periode_Debut> | B11: 0 | C11: 0 | D11: 1 | E11: 1 | F11: 0 | G11: 1 | Q11: /Fin/
A12: <Periode_Prolongement> | B12: 0 | C12: 0 | D12: 0 | E12: 0 | F12: 0 | G12: 20 | Q12: /Fin/
A13: <Source> | B13: Auckland factory | C13: Auckland factory | D13: Auckland factory | E13: Auckland factory | F13: Account | G13: Account | Q13: /Fin/
Q14: /Fin/
A15: <Process> | B15: concentrate (bin) | C15: Concentrate sale | D15: Concentrate sale | E15: concentrate storage cost | F15: cumulative result | G15: cumulative result | Q15: /Fin/
A16: Concentrate sale | B16: -1 | C16: 3000 | D16: =-C16 -> -3000 | E16: -60 | F16: =C16 -> 3000 | G16: =-E16 -> 60 | Q16: /Fin/
A17: <Periode_Debut> | B17: 0 | C17: 0 | D17: 1 | E17: 1 | F17: 0 | G17: 1 | Q17: /Fin/
A18: <Periode_Prolongement> | B18: 0 | C18: 0 | D18: 0 | E18: 0 | F18: 0 | G18: 20 | Q18: /Fin/
A19: <Source> | B19: Auckland factory | C19: Auckland factory | D19: Auckland factory | E19: Auckland factory | F19: Account | G19: Account | Q19: /Fin/
Q20: /Fin/
A21: <Process> | B21: staff | C21: Time not used | D21: Hiring cost | E21: Hiring cost | F21: wages cost | G21: cumulative result | H21: cumulative result | Q21: /Fin/
A22: Hiring | B22: 1 | C22: 150 | D22: 2000 | E22: =-D22 -> -2000 | F22: 3000 | G22: =-D22 -> -2000 | H22: =-F22 -> -3000 | Q22: /Fin/
A23: <Periode_Debut> | B23: 0 | C23: 1 | D23: 0 | E23: 1 | F23: 1 | G23: 0 | H23: 1 | Q23: /Fin/
A24: <Periode_Prolongement> | B24: 0 | C24: 0 | D24: 0 | E24: 0 | F24: 0 | G24: 0 | H24: 20 | Q24: /Fin/
A25: <Source> | B25: Auckland factory | C25: Auckland factory | D25: Auckland factory | E25: Auckland factory | F25: Auckland factory | G25: Account | H25: Account | Q25: /Fin/
Q26: /Fin/
A27: <Process> | B27: staff | C27: Time not used | D27: Laying-off cost | E27: Laying-off cost | F27: wages cost | G27: cumulative result | H27: cumulative result | Q27: /Fin/
A28: Laying-off | B28: -1 | C28: -150 | D28: 2000 | E28: =-D28 -> -2000 | F28: -3000 | G28: =-D28 -> -2000 | H28: =-F28 -> 3000 | Q28: /Fin/
A29: <Periode_Debut> | B29: 0 | C29: 1 | D29: 0 | E29: 1 | F29: 1 | G29: 0 | H29: 1 | Q29: /Fin/
A30: <Periode_Prolongement> | B30: 0 | C30: 0 | D30: 0 | E30: 0 | F30: 0 | G30: 0 | H30: 20 | Q30: /Fin/
A31: <Source> | B31: Auckland factory | C31: Auckland factory | D31: Auckland factory | E31: Auckland factory | F31: Auckland factory | G31: Account | H31: Account | Q31: /Fin/
Q32: /Fin/
Q33: /Fin/
Q34: /Fin/
Q35: /Fin/
A36: <Etat des lieux> | B36: <Minimal> | C36: <Maximal> | D36: 0 | E36: 1 | F36: 2 | G36: 3 | H36: 4 | I36: 5 | J36: 6 | K36: 7 | L36: 8 | M36: 9 | N36: 10 | O36: 11 | P36: 12 | Q36: /Fin/
A37: concentrate (bin) | B37: 0 | C37: 90 | D37: 15 | E37: 15 | F37: 24 | Q37: /Fin/
A38: puree (bin) | B38: 0 | C38: 90 | D38: 60 | E38: 60 | F38: 96 | Q38: /Fin/
A39: staff | B39: 0 | C39: 20 | D39: 5 | E39: 8 | F39: 8 | Q39: /Fin/
A40: Time not used | B40: 0 | C40: 1000000000 | D40: 750 | E40: 0 | F40: 0 | G40: 1200 | Q40: /Fin/
A41: Puree sale | B41: -1000000000 | C41: 1000000000 | E41: 0 | F41: 0 | G41: 0 | Q41: /Fin/
A42: Concentrate sale | B42: -1000000000 | C42: 1000000000 | E42: 0 | F42: 0 | G42: 0 | Q42: /Fin/
A43: production cost (wages excluded) | B43: -1000000000 | C43: 1000000000 | E43: 150000 | F43: 240000 | G43: -240000 | Q43: /Fin/
A44: concentrate storage cost | B44: -1000000000 | C44: 1000000000 | E44: 0 | F44: 0 | G44: 1440 | Q44: /Fin/
A45: puree storage cost | B45: -1000000000 | C45: 1000000000 | E45: 0 | F45: 0 | G45: 3840 | Q45: /Fin/
A46: Hiring cost | B46: -1000000000 | C46: 1000000000 | E46: 6000 | F46: 0 | G46: 0 | Q46: /Fin/
A47: Laying-off cost | B47: -1000000000 | C47: 1000000000 | E47: 0 | F47: 0 | G47: 0 | Q47: /Fin/
A48: wages cost | B48: -1000000000 | C48: 1000000000 | E48: 15000 | F48: 24000 | G48: 0 | Q48: /Fin/
A49: CO2 production | B49: -1000000000 | C49: 1000000000 | E49: 150000 | F49: 240000 | G49: -240000 | Q49: /Fin/
Q50: /Fin/
A51: /Fin/ | B51: /Fin/ | C51: /Fin/ | D51: /Fin/ | E51: /Fin/ | F51: /Fin/ | G51: /Fin/ | H51: /Fin/ | I51: /Fin/ | J51: /Fin/ | K51: /Fin/ | L51: /Fin/ | M51: /Fin/ | N51: /Fin/ | O51: /Fin/ | P51: /Fin/ | Q51: /Fin/

Sheet Lorry1
A1: <Nom> | B1: Lorry 1 | E1: Période | F1: 1 | Q1: /Fin/
Q2: /Fin/
A3: <Process> | B3: distance (km) | C3: distance (km) | D3: Time not used | E3: Time not used | F3: transport cost | G3: transport cost | H3: CO2 production | I3: CO2 production | J3: cumulative result | K3: cumulative CO2 | Q3: /Fin/
A4: driving | B4: 1 | C4: -1 | D4: =-B4/60 -> -0.016666667 | E4: =-D4 -> 0.016666667 | F4: 2.5 | G4: =-F4 -> -2.5 | H4: 0.92 | I4: =-H4 -> -0.92 | J4: =-F4 -> -2.5 | K4: =H4 -> 0.92 | Q4: /Fin/
A5: <Periode_Debut> | B5: 0 | C5: 1 | D5: 0 | E5: 1 | F5: 0 | G5: 1 | H5: 0 | I5: 1 | J5: 0 | K5: 0 | Q5: /Fin/
A6: <Periode_Prolongement> | B6: 0 | C6: 0 | D6: 0 | E6: 0 | F6: 0 | G6: 0 | H6: 0 | I6: 0 | J6: 0 | K6: 0 | Q6: /Fin/
A7: <Source> | B7: Lorry 1 | C7: Lorry 1 | D7: Lorry 1 | E7: Lorry 1 | F7: Lorry 1 | G7: Lorry 1 | H7: Lorry 1 | I7: Lorry 1 | J7: Account | K7: Account | Q7: /Fin/
Q8: /Fin/
A9: <Process> | B9: nectar (pallet) | C9: nectar (pallet) | D9: volume (pallet) | E9: weight (tonne) | F9: Time not used | G9: Time not used | H9: cost of nectar pallets storage | I9: cumulative result | Q9: /Fin/
A10: nectar loading | B10: 1 | C10: =-B10 -> -1 | D10: =B10 -> 1 | E10: =0.35*B10 -> 0.35 | F10: -0.03 | G10: =-F10 -> 0.03 | H10: =-12*B10 -> -12 | I10: =-H10 -> 12 | Q10: /Fin/
A11: <Periode_Debut> | B11: 0 | C11: 0 | D11: 0 | E11: 0 | F11: 0 | G11: 1 | H11: 0 | I11: 0 | Q11: /Fin/
A12: <Periode_Prolongement> | B12: 0 | C12: 0 | D12: 0 | E12: 0 | F12: 0 | G12: 0 | H12: 0 | I12: 20 | Q12: /Fin/
A13: <Source> | B13: Lorry 1 | C13: ? | D13: Lorry 1 | E13: Lorry 1 | F13: Lorry 1 | G13: Lorry 1 | H13: ? | I13: Account | Q13: /Fin/
Q14: /Fin/
A15: <Process> | B15: cordial (pallet) | C15: cordial (pallet) | D15: volume (pallet) | E15: weight (tonne) | F15: Time not used | G15: Time not used | H15: cost of cordial pallets storage | I15: cumulative result | Q15: /Fin/
A16: cordial loading | B16: 1 | C16: =-B16 -> -1 | D16: =B16 -> 1 | E16: 0.5 | F16: -0.03 | G16: =-F16 -> 0.03 | H16: =-19*B16 -> -19 | I16: =-H16 -> 19 | Q16: /Fin/
A17: <Periode_Debut> | B17: 0 | C17: 0 | D17: 0 | E17: 0 | F17: 0 | G17: 1 | H17: 0 | I17: 0 | Q17: /Fin/
A18: <Periode_Prolongement> | B18: 0 | C18: 0 | D18: 0 | E18: 0 | F18: 0 | G18: 0 | H18: 0 | I18: 20 | Q18: /Fin/
A19: <Source> | B19: Lorry 1 | C19: ? | D19: Lorry 1 | E19: Lorry 1 | F19: Lorry 1 | G19: Lorry 1 | H19: ? | I19: Account | Q19: /Fin/
Q20: /Fin/
A21: <Process> | B21: nectar (pallet) | C21: nectar (pallet) | D21: volume (pallet) | E21: weight (tonne) | F21: Time not used | G21: Time not used | H21: cost of nectar pallets storage | I21: cumulative result | Q21: /Fin/
A22: nectar unloading | B22: -1 | C22: =-B22 -> 1 | D22: =B22 -> -1 | E22: =0.35*B22 -> -0.35 | F22: -0.03 | G22: =-F22 -> 0.03 | H22: =-12*B22 -> 12 | I22: =-H22 -> -12 | Q22: /Fin/
A23: <Periode_Debut> | B23: 0 | C23: 0 | D23: 0 | E23: 0 | F23: 0 | G23: 1 | H23: 0 | I23: 0 | Q23: /Fin/
A24: <Periode_Prolongement> | B24: 0 | C24: 0 | D24: 0 | E24: 0 | F24: 0 | G24: 0 | H24: 0 | I24: 20 | Q24: /Fin/
A25: <Source> | B25: Lorry 1 | C25: ? | D25: Lorry 1 | E25: Lorry 1 | F25: Lorry 1 | G25: Lorry 1 | H25: ? | I25: Account | Q25: /Fin/
Q26: /Fin/
A27: <Process> | B27: cordial (pallet) | C27: cordial (pallet) | D27: volume (pallet) | E27: weight (tonne) | F27: Time not used | G27: Time not used | H27: cost of cordial pallets storage | I27: cumulative result | Q27: /Fin/
A28: cordial unloading | B28: -1 | C28: =-B28 -> 1 | D28: =B28 -> -1 | E28: -0.5 | F28: -0.03 | G28: =-F28 -> 0.03 | H28: =-19*B28 -> 19 | I28: =-H28 -> -19 | Q28: /Fin/
A29: <Periode_Debut> | B29: 0 | C29: 0 | D29: 0 | E29: 0 | F29: 0 | G29: 1 | H29: 0 | I29: 0 | Q29: /Fin/
A30: <Periode_Prolongement> | B30: 0 | C30: 0 | D30: 0 | E30: 0 | F30: 0 | G30: 0 | H30: 0 | I30: 20 | Q30: /Fin/
A31: <Source> | B31: Lorry 1 | C31: ? | D31: Lorry 1 | E31: Lorry 1 | F31: Lorry 1 | G31: Lorry 1 | H31: ? | I31: Account | Q31: /Fin/
Q32: /Fin/
Q33: /Fin/
A34: <Etat des lieux> | B34: <Minimal> | C34: <Maximal> | D34: 0 | E34: 1 | F34: 2 | G34: 3 | H34: 4 | I34: 5 | J34: 6 | K34: 7 | L34: 8 | M34: 9 | N34: 10 | O34: 11 | P34: 12 | Q34: /Fin/
A35: nectar (pallet) | B35: 0 | C35: 1000000000 | E35: 0 | F35: 0 | Q35: /Fin/
A36: cordial (pallet) | B36: 0 | C36: 1000000000 | E36: 0 | F36: 0 | Q36: /Fin/
A37: volume (pallet) | B37: 0 | C37: 66 | E37: 0 | F37: 0 | Q37: /Fin/
A38: weight (tonne) | B38: 0 | C38: 25 | E38: -3.5527137e-15 | F38: -3.5527137e-15 | Q38: /Fin/
A39: distance (km) | B39: -1000000000 | C39: 1000000000 | E39: 21967 | F39: 22676 | G39: -22676 | Q39: /Fin/
A40: Time not used | B40: 0 | C40: 500 | D40: 500 | E40: 124.88333 | F40: 99.266667 | G40: 400.73333 | Q40: /Fin/
A41: transport cost | B41: -1000000000 | C41: 1000000000 | E41: 54917.5 | F41: 56690 | G41: -56690 | Q41: /Fin/
A42: CO2 production | B42: -1000000000 | C42: 1000000000 | E42: 20209.64 | F42: 20861.92 | G42: -20861.92 | Q42: /Fin/
Q43: /Fin/
A44: /Fin/ | B44: /Fin/ | C44: /Fin/ | D44: /Fin/ | E44: /Fin/ | F44: /Fin/ | G44: /Fin/ | H44: /Fin/ | I44: /Fin/ | J44: /Fin/ | K44: /Fin/ | L44: /Fin/ | M44: /Fin/ | N44: /Fin/ | O44: /Fin/ | P44: /Fin/ | Q44: /Fin/

Sheet Lorry2
A1: <Nom> | B1: Lorry 2 | E1: Période | F1: 1 | Q1: /Fin/
Q2: /Fin/
A3: <Process> | B3: distance (km) | C3: distance (km) | D3: Time not used | E3: Time not used | F3: transport cost | G3: transport cost | H3: CO2 production | I3: CO2 production | J3: cumulative result | K3: cumulative CO2 | Q3: /Fin/
A4: driving | B4: 1 | C4: -1 | D4: =-B4/60 -> -0.016666667 | E4: =-D4 -> 0.016666667 | F4: 2 | G4: =-F4 -> -2 | H4: 0.92 | I4: =-H4 -> -0.92 | J4: =-F4 -> -2 | K4: =H4 -> 0.92 | Q4: /Fin/
A5: <Periode_Debut> | B5: 0 | C5: 1 | D5: 0 | E5: 1 | F5: 0 | G5: 1 | H5: 0 | I5: 1 | J5: 0 | K5: 0 | Q5: /Fin/
A6: <Periode_Prolongement> | B6: 0 | C6: 0 | D6: 0 | E6: 0 | F6: 0 | G6: 0 | H6: 0 | I6: 0 | J6: 0 | K6: 0 | Q6: /Fin/
A7: <Source> | B7: Lorry 2 | C7: Lorry 2 | D7: Lorry 2 | E7: Lorry 2 | F7: Lorry 2 | G7: Lorry 2 | H7: Lorry 2 | I7: Lorry 2 | J7: Account | K7: Account | Q7: /Fin/
Q8: /Fin/
A9: <Process> | B9: nectar (pallet) | C9: nectar (pallet) | D9: volume (pallet) | E9: weight (tonne) | F9: Time not used | G9: Time not used | H9: cost of nectar pallets storage | I9: cumulative result | Q9: /Fin/
A10: nectar loading | B10: 1 | C10: =-B10 -> -1 | D10: =B10 -> 1 | E10: =0.35*B10 -> 0.35 | F10: -0.03 | G10: =-F10 -> 0.03 | H10: =-12*B10 -> -12 | I10: =-H10 -> 12 | Q10: /Fin/
A11: <Periode_Debut> | B11: 0 | C11: 0 | D11: 0 | E11: 0 | F11: 0 | G11: 1 | H11: 0 | I11: 0 | Q11: /Fin/
A12: <Periode_Prolongement> | B12: 0 | C12: 0 | D12: 0 | E12: 0 | F12: 0 | G12: 0 | H12: 0 | I12: 20 | Q12: /Fin/
A13: <Source> | B13: Lorry 2 | C13: ? | D13: Lorry 2 | E13: Lorry 2 | F13: Lorry 2 | G13: Lorry 2 | H13: ? | I13: Account | Q13: /Fin/
Q14: /Fin/
A15: <Process> | B15: cordial (pallet) | C15: cordial (pallet) | D15: volume (pallet) | E15: weight (tonne) | F15: Time not used | G15: Time not used | H15: cost of cordial pallets storage | I15: cumulative result | Q15: /Fin/
A16: cordial loading | B16: 1 | C16: =-B16 -> -1 | D16: =B16 -> 1 | E16: 0.5 | F16: -0.03 | G16: =-F16 -> 0.03 | H16: =-19*B16 -> -19 | I16: =-H16 -> 19 | Q16: /Fin/
A17: <Periode_Debut> | B17: 0 | C17: 0 | D17: 0 | E17: 0 | F17: 0 | G17: 1 | H17: 0 | I17: 0 | Q17: /Fin/
A18: <Periode_Prolongement> | B18: 0 | C18: 0 | D18: 0 | E18: 0 | F18: 0 | G18: 0 | H18: 0 | I18: 20 | Q18: /Fin/
A19: <Source> | B19: Lorry 2 | C19: ? | D19: Lorry 2 | E19: Lorry 2 | F19: Lorry 2 | G19: Lorry 2 | H19: ? | I19: Account | Q19: /Fin/
Q20: /Fin/
A21: <Process> | B21: nectar (pallet) | C21: nectar (pallet) | D21: volume (pallet) | E21: weight (tonne) | F21: Time not used | G21: Time not used | H21: cost of nectar pallets storage | I21: cumulative result | Q21: /Fin/
A22: nectar unloading | B22: -1 | C22: =-B22 -> 1 | D22: =B22 -> -1 | E22: =0.35*B22 -> -0.35 | F22: -0.03 | G22: =-F22 -> 0.03 | H22: =-12*B22 -> 12 | I22: =-H22 -> -12 | Q22: /Fin/
A23: <Periode_Debut> | B23: 0 | C23: 0 | D23: 0 | E23: 0 | F23: 0 | G23: 1 | H23: 0 | I23: 0 | Q23: /Fin/
A24: <Periode_Prolongement> | B24: 0 | C24: 0 | D24: 0 | E24: 0 | F24: 0 | G24: 0 | H24: 0 | I24: 20 | Q24: /Fin/
A25: <Source> | B25: Lorry 2 | C25: ? | D25: Lorry 2 | E25: Lorry 2 | F25: Lorry 2 | G25: Lorry 2 | H25: ? | I25: Account | Q25: /Fin/
Q26: /Fin/
A27: <Process> | B27: cordial (pallet) | C27: cordial (pallet) | D27: volume (pallet) | E27: weight (tonne) | F27: Time not used | G27: Time not used | H27: cost of cordial pallets storage | I27: cumulative result | Q27: /Fin/
A28: cordial unloading | B28: -1 | C28: =-B28 -> 1 | D28: =B28 -> -1 | E28: -0.5 | F28: -0.03 | G28: =-F28 -> 0.03 | H28: =-19*B28 -> 19 | I28: =-H28 -> -19 | Q28: /Fin/
A29: <Periode_Debut> | B29: 0 | C29: 0 | D29: 0 | E29: 0 | F29: 0 | G29: 1 | H29: 0 | I29: 0 | Q29: /Fin/
A30: <Periode_Prolongement> | B30: 0 | C30: 0 | D30: 0 | E30: 0 | F30: 0 | G30: 0 | H30: 0 | I30: 20 | Q30: /Fin/
A31: <Source> | B31: Lorry 2 | C31: ? | D31: Lorry 2 | E31: Lorry 2 | F31: Lorry 2 | G31: Lorry 2 | H31: ? | I31: Account | Q31: /Fin/
Q32: /Fin/
Q33: /Fin/
A34: <Etat des lieux> | B34: <Minimal> | C34: <Maximal> | D34: 0 | E34: 1 | F34: 2 | G34: 3 | H34: 4 | I34: 5 | J34: 6 | K34: 7 | L34: 8 | M34: 9 | N34: 10 | O34: 11 | P34: 12 | Q34: /Fin/
A35: nectar (pallet) | B35: 0 | C35: 1000000000 | E35: 0 | F35: 0 | Q35: /Fin/
A36: cordial (pallet) | B36: 0 | C36: 1000000000 | E36: 2 | F36: 0 | Q36: /Fin/
A37: volume (pallet) | B37: 0 | C37: 66 | E37: 2 | F37: 0 | Q37: /Fin/
A38: weight (tonne) | B38: 0 | C38: 25 | E38: 1 | F38: 0 | Q38: /Fin/
A39: distance (km) | B39: -1000000000 | C39: 1000000000 | E39: 9539 | F39: 13476 | G39: -13476 | Q39: /Fin/
A40: Time not used | B40: 0 | C40: 250 | D40: 250 | E40: 88.076667 | F40: 11.78 | G40: 238.22 | Q40: /Fin/
A41: transport cost | B41: -1000000000 | C41: 1000000000 | E41: 19078 | F41: 26952 | G41: -26952 | Q41: /Fin/
A42: CO2 production | B42: -1000000000 | C42: 1000000000 | E42: 8775.88 | F42: 12397.92 | G42: -12397.92 | Q42: /Fin/
Q43: /Fin/
A44: /Fin/ | B44: /Fin/ | C44: /Fin/ | D44: /Fin/ | E44: /Fin/ | F44: /Fin/ | G44: /Fin/ | H44: /Fin/ | I44: /Fin/ | J44: /Fin/ | K44: /Fin/ | L44: /Fin/ | M44: /Fin/ | N44: /Fin/ | O44: /Fin/ | P44: /Fin/ | Q44: /Fin/

Sheet Lorry3
A1: <Nom> | B1: Lorry 3 | E1: Période | F1: 1 | Q1: /Fin/
Q2: /Fin/
A3: <Process> | B3: distance (km) | C3: distance (km) | D3: Time not used | E3: Time not used | F3: transport cost | G3: transport cost | H3: CO2 production | I3: CO2 production | J3: cumulative result | K3: cumulative CO2 | Q3: /Fin/
A4: driving | B4: 1 | C4: -1 | D4: =-B4/70 -> -0.014285714 | E4: =-D4 -> 0.014285714 | F4: 1.5 | G4: =-F4 -> -1.5 | H4: 0.8 | I4: =-H4 -> -0.8 | J4: =-F4 -> -1.5 | K4: =H4 -> 0.8 | Q4: /Fin/
A5: <Periode_Debut> | B5: 0 | C5: 1 | D5: 0 | E5: 1 | F5: 0 | G5: 1 | H5: 0 | I5: 1 | J5: 0 | K5: 0 | Q5: /Fin/
A6: <Periode_Prolongement> | B6: 0 | C6: 0 | D6: 0 | E6: 0 | F6: 0 | G6: 0 | H6: 0 | I6: 0 | J6: 0 | K6: 0 | Q6: /Fin/
A7: <Source> | B7: Lorry 3 | C7: Lorry 3 | D7: Lorry 3 | E7: Lorry 3 | F7: Lorry 3 | G7: Lorry 3 | H7: Lorry 3 | I7: Lorry 3 | J7: Account | K7: Account | Q7: /Fin/
Q8: /Fin/
A9: <Process> | B9: nectar (pallet) | C9: nectar (pallet) | D9: volume (pallet) | E9: weight (tonne) | F9: Time not used | G9: Time not used | H9: cost of nectar pallets storage | I9: cumulative result | Q9: /Fin/
A10: nectar loading | B10: 1 | C10: =-B10 -> -1 | D10: =B10 -> 1 | E10: =0.35*B10 -> 0.35 | F10: -0.03 | G10: =-F10 -> 0.03 | H10: =-12*B10 -> -12 | I10: =-H10 -> 12 | Q10: /Fin/
A11: <Periode_Debut> | B11: 0 | C11: 0 | D11: 0 | E11: 0 | F11: 0 | G11: 1 | H11: 0 | I11: 0 | Q11: /Fin/
A12: <Periode_Prolongement> | B12: 0 | C12: 0 | D12: 0 | E12: 0 | F12: 0 | G12: 0 | H12: 0 | I12: 20 | Q12: /Fin/
A13: <Source> | B13: Lorry 3 | C13: ? | D13: Lorry 3 | E13: Lorry 3 | F13: Lorry 3 | G13: Lorry 3 | H13: ? | I13: Account | Q13: /Fin/
Q14: /Fin/
A15: <Process> | B15: cordial (pallet) | C15: cordial (pallet) | D15: volume (pallet) | E15: weight (tonne) | F15: Time not used | G15: Time not used | H15: cost of cordial pallets storage | I15: cumulative result | Q15: /Fin/
A16: cordial loading | B16: 1 | C16: =-B16 -> -1 | D16: =B16 -> 1 | E16: 0.5 | F16: -0.03 | G16: =-F16 -> 0.03 | H16: =-19*B16 -> -19 | I16: =-H16 -> 19 | Q16: /Fin/
A17: <Periode_Debut> | B17: 0 | C17: 0 | D17: 0 | E17: 0 | F17: 0 | G17: 1 | H17: 0 | I17: 0 | Q17: /Fin/
A18: <Periode_Prolongement> | B18: 0 | C18: 0 | D18: 0 | E18: 0 | F18: 0 | G18: 0 | H18: 0 | I18: 20 | Q18: /Fin/
A19: <Source> | B19: Lorry 3 | C19: ? | D19: Lorry 3 | E19: Lorry 3 | F19: Lorry 3 | G19: Lorry 3 | H19: ? | I19: Account | Q19: /Fin/
Q20: /Fin/
A21: <Process> | B21: nectar (pallet) | C21: nectar (pallet) | D21: volume (pallet) | E21: weight (tonne) | F21: Time not used | G21: Time not used | H21: cost of nectar pallets storage | I21: cumulative result | Q21: /Fin/
A22: nectar unloading | B22: -1 | C22: =-B22 -> 1 | D22: =B22 -> -1 | E22: =0.35*B22 -> -0.35 | F22: -0.03 | G22: =-F22 -> 0.03 | H22: =-12*B22 -> 12 | I22: =-H22 -> -12 | Q22: /Fin/
A23: <Periode_Debut> | B23: 0 | C23: 0 | D23: 0 | E23: 0 | F23: 0 | G23: 1 | H23: 0 | I23: 0 | Q23: /Fin/
A24: <Periode_Prolongement> | B24: 0 | C24: 0 | D24: 0 | E24: 0 | F24: 0 | G24: 0 | H24: 0 | I24: 20 | Q24: /Fin/
A25: <Source> | B25: Lorry 3 | C25: ? | D25: Lorry 3 | E25: Lorry 3 | F25: Lorry 3 | G25: Lorry 3 | H25: ? | I25: Account | Q25: /Fin/
Q26: /Fin/
A27: <Process> | B27: cordial (pallet) | C27: cordial (pallet) | D27: volume (pallet) | E27: weight (tonne) | F27: Time not used | G27: Time not used | H27: cost of cordial pallets storage | I27: cumulative result | Q27: /Fin/
A28: cordial unloading | B28: -1 | C28: =-B28 -> 1 | D28: =B28 -> -1 | E28: -0.5 | F28: -0.03 | G28: =-F28 -> 0.03 | H28: =-19*B28 -> 19 | I28: =-H28 -> -19 | Q28: /Fin/
A29: <Periode_Debut> | B29: 0 | C29: 0 | D29: 0 | E29: 0 | F29: 0 | G29: 1 | H29: 0 | I29: 0 | Q29: /Fin/
A30: <Periode_Prolongement> | B30: 0 | C30: 0 | D30: 0 | E30: 0 | F30: 0 | G30: 0 | H30: 0 | I30: 20 | Q30: /Fin/
A31: <Source> | B31: Lorry 3 | C31: ? | D31: Lorry 3 | E31: Lorry 3 | F31: Lorry 3 | G31: Lorry 3 | H31: ? | I31: Account | Q31: /Fin/
Q32: /Fin/
Q33: /Fin/
A34: <Etat des lieux> | B34: <Minimal> | C34: <Maximal> | D34: 0 | E34: 1 | F34: 2 | G34: 3 | H34: 4 | I34: 5 | J34: 6 | K34: 7 | L34: 8 | M34: 9 | N34: 10 | O34: 11 | P34: 12 | Q34: /Fin/
A35: nectar (pallet) | B35: 0 | C35: 1000000000 | E35: 0 | F35: 0 | Q35: /Fin/
A36: cordial (pallet) | B36: 0 | C36: 1000000000 | E36: 0 | F36: 0 | Q36: /Fin/
A37: volume (pallet) | B37: 0 | C37: 24 | E37: 0 | F37: 0 | Q37: /Fin/
A38: weight (tonne) | B38: 0 | C38: 15 | E38: 0 | F38: 0 | Q38: /Fin/
A39: distance (km) | B39: -1000000000 | C39: 1000000000 | E39: 6966 | F39: 9431 | G39: -9431 | Q39: /Fin/
A40: Time not used | B40: 0 | C40: 150 | D40: 150 | E40: 49.045714 | F40: 9.5114286 | G40: 140.48857 | Q40: /Fin/
A41: transport cost | B41: -1000000000 | C41: 1000000000 | E41: 10449 | F41: 14146.5 | G41: -14146.5 | Q41: /Fin/
A42: CO2 production | B42: -1000000000 | C42: 1000000000 | E42: 5572.8 | F42: 7544.8 | G42: -7544.8 | Q42: /Fin/
Q43: /Fin/
A44: /Fin/ | B44: /Fin/ | C44: /Fin/ | D44: /Fin/ | E44: /Fin/ | F44: /Fin/ | G44: /Fin/ | H44: /Fin/ | I44: /Fin/ | J44: /Fin/ | K44: /Fin/ | L44: /Fin/ | M44: /Fin/ | N44: /Fin/ | O44: /Fin/ | P44: /Fin/ | Q44: /Fin/

Sheet Wharehouse1
A1: <Nom> | B1: Paris | E1: Période | F1: 1 | Q1: /Fin/
Q2: /Fin/
A3: <Process> | B3: nectar needs (pallet) | C3: nectar needs (pallet) | D3: nectar (pallet) | E3: nectar sales (pallet) | F3: nectar sales (pallet) | G3: nectar turnover | H3: nectar turnover | I3: cost of nectar pallets storage | J3: cumulative result | K3: cumulative result | Q3: /Fin/
A4: Demand of nectar | B4: 1 | C4: -1 | D4: -1 | E4: 1 | F4: -1 | G4: 1000 | H4: =-G4 -> -1000 | I4: -12 | J4: =G4 -> 1000 | K4: =-I4 -> 12 | Q4: /Fin/
A5: <Periode_Debut> | B5: 0 | C5: 1 | D5: 0 | E5: 0 | F5: 1 | G5: 0 | H5: 1 | I5: 0 | J5: 0 | K5: 0 | Q5: /Fin/
A6: <Periode_Prolongement> | B6: 0 | C6: 0 | D6: 0 | E6: 0 | F6: 0 | G6: 0 | H6: 0 | I6: 0 | J6: 0 | K6: 20 | Q6: /Fin/
A7: <Source> | B7: Paris | C7: Paris | D7: Paris | E7: Paris | F7: Paris | G7: Paris | H7: Paris | I7: Paris | J7: Account | K7: Account | Q7: /Fin/
Q8: /Fin/
A9: <Process> | B9: cordial needs (pallet) | C9: cordial needs (pallet) | D9: cordial (pallet) | E9: cordial sales (pallet) | F9: cordial sales (pallet) | G9: cordial turnover | H9: cordial turnover | I9: cost of cordial pallets storage | J9: cumulative result | K9: cumulative result | Q9: /Fin/
A10: Demand of cordial | B10: 1 | C10: -1 | D10: -1 | E10: 1 | F10: -1 | G10: 1600 | H10: =-G10 -> -1600 | I10: -19 | J10: =G10 -> 1600 | K10: =-I10 -> 19 | Q10: /Fin/
A11: <Periode_Debut> | B11: 0 | C11: 1 | D11: 0 | E11: 0 | F11: 1 | G11: 0 | H11: 1 | I11: 0 | J11: 0 | K11: 0 | Q11: /Fin/
A12: <Periode_Prolongement> | B12: 0 | C12: 0 | D12: 0 | E12: 0 | F12: 0 | G12: 0 | H12: 0 | I12: 0 | J12: 0 | K12: 20 | Q12: /Fin/
A13: <Source> | B13: Paris | C13: Paris | D13: Paris | E13: Paris | F13: Paris | G13: Paris | H13: Paris | I13: Paris | J13: Account | K13: Account | Q13: /Fin/
Q14: /Fin/
Q15: /Fin/
Q16: /Fin/
A17: <Etat des lieux> | B17: <Minimal> | C17: <Maximal> | D17: 0 | E17: 1 | F17: 2 | G17: 3 | H17: 4 | I17: 5 | J17: 6 | K17: 7 | L17: 8 | M17: 9 | N17: 10 | O17: 11 | P17: 12 | Q17: /Fin/
A18: nectar (pallet) | B18: 0 | C18: 750 | D18: 10 | E18: 0 | F18: 1 | Q18: /Fin/
A19: cordial (pallet) | B19: 0 | C19: 750 | D19: 10 | E19: 2 | F19: 41 | Q19: /Fin/
A20: nectar turnover | B20: -1000000000 | C20: 1000000000 | D20: 0 | E20: 20000 | F20: 22000 | G20: -22000 | Q20: /Fin/
A21: cordial turnover | B21: -1000000000 | C21: 1000000000 | D21: 0 | E21: 24000 | F21: 27200 | G21: -27200 | Q21: /Fin/
A22: cost of nectar pallets storage | B22: -1000000000 | C22: 1000000000 | E22: 0 | F22: 12 | Q22: /Fin/
A23: cost of cordial pallets storage | B23: -1000000000 | C23: 1000000000 | E23: 38 | F23: 779 | Q23: /Fin/
A24: nectar needs (pallet) | B24: -1000000000 | C24: 1000000000 | E24: 20 | F24: 22 | G24: -22 | Q24: /Fin/
A25: cordial needs (pallet) | B25: -1000000000 | C25: 1000000000 | E25: 15 | F25: 17 | G25: -17 | Q25: /Fin/
A26: nectar sales (pallet) | B26: -1000000000 | C26: 1000000000 | E26: 20 | F26: 22 | G26: -22 | Q26: /Fin/
A27: cordial sales (pallet) | B27: -1000000000 | C27: 1000000000 | E27: 15 | F27: 17 | G27: -17 | Q27: /Fin/
Q28: /Fin/
A29: /Fin/ | B29: /Fin/ | C29: /Fin/ | D29: /Fin/ | E29: /Fin/ | F29: /Fin/ | G29: /Fin/ | H29: /Fin/ | I29: /Fin/ | J29: /Fin/ | K29: /Fin/ | L29: /Fin/ | M29: /Fin/ | N29: /Fin/ | O29: /Fin/ | P29: /Fin/ | Q29: /Fin/

Sheet Wharehouse2
A1: <Nom> | B1: Rauma | E1: Période | F1: 1 | Q1: /Fin/
Q2: /Fin/
A3: <Process> | B3: nectar needs (pallet) | C3: nectar needs (pallet) | D3: nectar (pallet) | E3: nectar sales (pallet) | F3: nectar sales (pallet) | G3: nectar turnover | H3: nectar turnover | I3: cost of nectar pallets storage | J3: cumulative result | K3: cumulative result | Q3: /Fin/
A4: Demand of nectar | B4: 1 | C4: -1 | D4: -1 | E4: 1 | F4: -1 | G4: 700 | H4: =-G4 -> -700 | I4: -12 | J4: =G4 -> 700 | K4: =-I4 -> 12 | Q4: /Fin/
A5: <Periode_Debut> | B5: 0 | C5: 1 | D5: 0 | E5: 0 | F5: 1 | G5: 0 | H5: 1 | I5: 0 | J5: 0 | K5: 0 | Q5: /Fin/
A6: <Periode_Prolongement> | B6: 0 | C6: 0 | D6: 0 | E6: 0 | F6: 0 | G6: 0 | H6: 0 | I6: 0 | J6: 0 | K6: 20 | Q6: /Fin/
A7: <Source> | B7: Rauma | C7: Rauma | D7: Rauma | E7: Rauma | F7: Rauma | G7: Rauma | H7: Rauma | I7: Rauma | J7: Account | K7: Account | Q7: /Fin/
Q8: /Fin/
A9: <Process> | B9: cordial needs (pallet) | C9: cordial needs (pallet) | D9: cordial (pallet) | E9: cordial sales (pallet) | F9: cordial sales (pallet) | G9: cordial turnover | H9: cordial turnover | I9: cost of cordial pallets storage | J9: cumulative result | K9: cumulative result | Q9: /Fin/
A10: Demand of cordial | B10: 1 | C10: -1 | D10: -1 | E10: 1 | F10: -1 | G10: 1300 | H10: =-G10 -> -1300 | I10: -19 | J10: =G10 -> 1300 | K10: =-I10 -> 19 | Q10: /Fin/
A11: <Periode_Debut> | B11: 0 | C11: 1 | D11: 0 | E11: 0 | F11: 1 | G11: 0 | H11: 1 | I11: 0 | J11: 0 | K11: 0 | Q11: /Fin/
A12: <Periode_Prolongement> | B12: 0 | C12: 0 | D12: 0 | E12: 0 | F12: 0 | G12: 0 | H12: 0 | I12: 0 | J12: 0 | K12: 20 | Q12: /Fin/
A13: <Source> | B13: Rauma | C13: Rauma | D13: Rauma | E13: Rauma | F13: Rauma | G13: Rauma | H13: Rauma | I13: Rauma | J13: Account | K13: Account | Q13: /Fin/
Q14: /Fin/
Q15: /Fin/
Q16: /Fin/
A17: <Etat des lieux> | B17: <Minimal> | C17: <Maximal> | D17: 0 | E17: 1 | F17: 2 | G17: 3 | H17: 4 | I17: 5 | J17: 6 | K17: 7 | L17: 8 | M17: 9 | N17: 10 | O17: 11 | P17: 12 | Q17: /Fin/
A18: nectar (pallet) | B18: 0 | C18: 750 | D18: 10 | E18: 1 | F18: 69 | Q18: /Fin/
A19: cordial (pallet) | B19: 0 | C19: 750 | D19: 10 | E19: 2 | F19: 2 | Q19: /Fin/
A20: nectar turnover | B20: -1000000000 | C20: 1000000000 | D20: 0 | E20: 14000 | F20: 15400 | G20: -15400 | Q20: /Fin/
A21: cordial turnover | B21: -1000000000 | C21: 1000000000 | D21: 0 | E21: 18200 | F21: 22100 | G21: -22100 | Q21: /Fin/
A22: cost of nectar pallets storage | B22: -1000000000 | C22: 1000000000 | E22: 12 | F22: 828 | Q22: /Fin/
A23: cost of cordial pallets storage | B23: -1000000000 | C23: 1000000000 | E23: 38 | F23: 38 | Q23: /Fin/
A24: nectar needs (pallet) | B24: -1000000000 | C24: 1000000000 | E24: 20 | F24: 22 | G24: -22
A25: cordial needs (pallet) | B25: -1000000000 | C25: 1000000000 | E25: 14 | F25: 17 | G25: -17 | Q25: /Fin/
A26: nectar sales (pallet) | B26: -1000000000 | C26: 1000000000 | E26: 20 | F26: 22 | G26: -22
A27: cordial sales (pallet) | B27: -1000000000 | C27: 1000000000 | E27: 14 | F27: 17 | G27: -17
Q28: /Fin/
A29: /Fin/ | B29: /Fin/ | C29: /Fin/ | D29: /Fin/ | E29: /Fin/ | F29: /Fin/ | G29: /Fin/ | H29: /Fin/ | I29: /Fin/ | J29: /Fin/ | K29: /Fin/ | L29: /Fin/ | M29: /Fin/ | N29: /Fin/ | O29: /Fin/ | P29: /Fin/ | Q29: /Fin/

Sheet Wharehouse3
A1: <Nom> | B1: Madrid | E1: Période | F1: 1 | Q1: /Fin/
Q2: /Fin/
A3: <Process> | B3: nectar needs (pallet) | C3: nectar needs (pallet) | D3: nectar (pallet) | E3: nectar sales (pallet) | F3: nectar sales (pallet) | G3: nectar turnover | H3: nectar turnover | I3: cost of nectar pallets storage | J3: cumulative result | K3: cumulative result | Q3: /Fin/
A4: Demand of nectar | B4: 1 | C4: -1 | D4: -1 | E4: 1 | F4: -1 | G4: 900 | H4: =-G4 -> -900 | I4: -12 | J4: =G4 -> 900 | K4: =-I4 -> 12 | Q4: /Fin/
A5: <Periode_Debut> | B5: 0 | C5: 1 | D5: 0 | E5: 0 | F5: 1 | G5: 0 | H5: 1 | I5: 0 | J5: 0 | K5: 0 | Q5: /Fin/
A6: <Periode_Prolongement> | B6: 0 | C6: 0 | D6: 0 | E6: 0 | F6: 0 | G6: 0 | H6: 0 | I6: 0 | J6: 0 | K6: 20 | Q6: /Fin/
A7: <Source> | B7: Madrid | C7: Madrid | D7: Madrid | E7: Madrid | F7: Madrid | G7: Madrid | H7: Madrid | I7: Madrid | J7: Account | K7: Account | Q7: /Fin/
Q8: /Fin/
A9: <Process> | B9: cordial needs (pallet) | C9: cordial needs (pallet) | D9: cordial (pallet) | E9: cordial sales (pallet) | F9: cordial sales (pallet) | G9: cordial turnover | H9: cordial turnover | I9: cost of cordial pallets storage | J9: cumulative result | K9: cumulative result | Q9: /Fin/
A10: Demand of cordial | B10: 1 | C10: -1 | D10: -1 | E10: 1 | F10: -1 | G10: 1500 | H10: =-G10 -> -1500 | I10: -19 | J10: =G10 -> 1500 | K10: =-I10 -> 19 | Q10: /Fin/
A11: <Periode_Debut> | B11: 0 | C11: 1 | D11: 0 | E11: 0 | F11: 1 | G11: 0 | H11: 1 | I11: 0 | J11: 0 | K11: 0 | Q11: /Fin/
A12: <Periode_Prolongement> | B12: 0 | C12: 0 | D12: 0 | E12: 0 | F12: 0 | G12: 0 | H12: 0 | I12: 0 | J12: 0 | K12: 20 | Q12: /Fin/
A13: <Source> | B13: Madrid | C13: Madrid | D13: Madrid | E13: Madrid | F13: Madrid | G13: Madrid | H13: Madrid | I13: Madrid | J13: Account | K13: Account | Q13: /Fin/
Q14: /Fin/
Q15: /Fin/
Q16: /Fin/
A17: <Etat des lieux> | B17: <Minimal> | C17: <Maximal> | D17: 0 | E17: 1 | F17: 2 | G17: 3 | H17: 4 | I17: 5 | J17: 6 | K17: 7 | L17: 8 | M17: 9 | N17: 10 | O17: 11 | P17: 12 | Q17: /Fin/
A18: nectar (pallet) | B18: 0 | C18: 750 | D18: 10 | E18: 2 | F18: 55 | Q18: /Fin/
A19: cordial (pallet) | B19: 0 | C19: 750 | D19: 10 | E19: 0 | F19: 23 | Q19: /Fin/
A20: nectar turnover | B20: -1000000000 | C20: 1000000000 | D20: 0 | E20: 21600 | F20: 21600 | G20: -21600 | Q20: /Fin/
A21: cordial turnover | B21: -1000000000 | C21: 1000000000 | D21: 0 | E21: 21000 | F21: 19500 | G21: -19500 | Q21: /Fin/
A22: cost of nectar pallets storage | B22: -1000000000 | C22: 1000000000 | E22: 24 | F22: 660 | Q22: /Fin/
A23: cost of cordial pallets storage | B23: -1000000000 | C23: 1000000000 | E23: 0 | F23: 437 | Q23: /Fin/
A24: nectar needs (pallet) | B24: -1000000000 | C24: 1000000000 | E24: 24 | F24: 24 | G24: -24
A25: cordial needs (pallet) | B25: -1000000000 | C25: 1000000000 | E25: 14 | F25: 13 | G25: -13 | Q25: /Fin/
A26: nectar sales (pallet) | B26: -1000000000 | C26: 1000000000 | E26: 24 | F26: 24 | G26: -24
A27: cordial sales (pallet) | B27: -1000000000 | C27: 1000000000 | E27: 14 | F27: 13 | G27: -13
Q28: /Fin/
A29: /Fin/ | B29: /Fin/ | C29: /Fin/ | D29: /Fin/ | E29: /Fin/ | F29: /Fin/ | G29: /Fin/ | H29: /Fin/ | I29: /Fin/ | J29: /Fin/ | K29: /Fin/ | L29: /Fin/ | M29: /Fin/ | N29: /Fin/ | O29: /Fin/ | P29: /Fin/ | Q29: /Fin/

Sheet Wharehouse4
A1: <Nom> | B1: Milan | E1: Période | F1: 1 | Q1: /Fin/
Q2: /Fin/
A3: <Process> | B3: nectar needs (pallet) | C3: nectar needs (pallet) | D3: nectar (pallet) | E3: nectar sales (pallet) | F3: nectar sales (pallet) | G3: nectar turnover | H3: nectar turnover | I3: cost of nectar pallets storage | J3: cumulative result | K3: cumulative result | Q3: /Fin/
A4: Demand of nectar | B4: 1 | C4: -1 | D4: -1 | E4: 1 | F4: -1 | G4: 900 | H4: =-G4 -> -900 | I4: -12 | J4: =G4 -> 900 | K4: =-I4 -> 12 | Q4: /Fin/
A5: <Periode_Debut> | B5: 0 | C5: 1 | D5: 0 | E5: 0 | F5: 1 | G5: 0 | H5: 1 | I5: 0 | J5: 0 | K5: 0 | Q5: /Fin/
A6: <Periode_Prolongement> | B6: 0 | C6: 0 | D6: 0 | E6: 0 | F6: 0 | G6: 0 | H6: 0 | I6: 0 | J6: 0 | K6: 20 | Q6: /Fin/
A7: <Source> | B7: Milan | C7: Milan | D7: Milan | E7: Milan | F7: Milan | G7: Milan | H7: Milan | I7: Milan | J7: Account | K7: Account | Q7: /Fin/
Q8: /Fin/
A9: <Process> | B9: cordial needs (pallet) | C9: cordial needs (pallet) | D9: cordial (pallet) | E9: cordial sales (pallet) | F9: cordial sales (pallet) | G9: cordial turnover | H9: cordial turnover | I9: cost of cordial pallets storage | J9: cumulative result | K9: cumulative result | Q9: /Fin/
A10: Demand of cordial | B10: 1 | C10: -1 | D10: -1 | E10: 1 | F10: -1 | G10: 1500 | H10: =-G10 -> -1500 | I10: -19 | J10: =G10 -> 1500 | K10: =-I10 -> 19 | Q10: /Fin/
A11: <Periode_Debut> | B11: 0 | C11: 1 | D11: 0 | E11: 0 | F11: 1 | G11: 0 | H11: 1 | I11: 0 | J11: 0 | K11: 0 | Q11: /Fin/
A12: <Periode_Prolongement> | B12: 0 | C12: 0 | D12: 0 | E12: 0 | F12: 0 | G12: 0 | H12: 0 | I12: 0 | J12: 0 | K12: 20 | Q12: /Fin/
A13: <Source> | B13: Milan | C13: Milan | D13: Milan | E13: Milan | F13: Milan | G13: Milan | H13: Milan | I13: Milan | J13: Account | K13: Account | Q13: /Fin/
Q14: /Fin/
Q15: /Fin/
Q16: /Fin/
A17: <Etat des lieux> | B17: <Minimal> | C17: <Maximal> | D17: 0 | E17: 1 | F17: 2 | G17: 3 | H17: 4 | I17: 5 | J17: 6 | K17: 7 | L17: 8 | M17: 9 | N17: 10 | O17: 11 | P17: 12 | Q17: /Fin/
A18: nectar (pallet) | B18: 0 | C18: 750 | D18: 10 | E18: 11 | F18: 19 | Q18: /Fin/
A19: cordial (pallet) | B19: 0 | C19: 750 | D19: 10 | E19: 4 | F19: 12 | Q19: /Fin/
A20: nectar turnover | B20: -1000000000 | C20: 1000000000 | D20: 0 | E20: 19800 | F20: 19800 | G20: -19800 | Q20: /Fin/
A21: cordial turnover | B21: -1000000000 | C21: 1000000000 | D21: 0 | E21: 22500 | F21: 21000 | G21: -21000 | Q21: /Fin/
A22: cost of nectar pallets storage | B22: -1000000000 | C22: 1000000000 | E22: 132 | F22: 228 | Q22: /Fin/
A23: cost of cordial pallets storage | B23: -1000000000 | C23: 1000000000 | E23: 76 | F23: 228 | Q23: /Fin/
A24: nectar needs (pallet) | B24: -1000000000 | C24: 1000000000 | E24: 22 | F24: 22 | G24: -22
A25: cordial needs (pallet) | B25: -1000000000 | C25: 1000000000 | E25: 15 | F25: 14 | G25: -14 | Q25: /Fin/
A26: nectar sales (pallet) | B26: -1000000000 | C26: 1000000000 | E26: 22 | F26: 22 | G26: -22
A27: cordial sales (pallet) | B27: -1000000000 | C27: 1000000000 | E27: 15 | F27: 14 | G27: -14
Q28: /Fin/
A29: /Fin/ | B29: /Fin/ | C29: /Fin/ | D29: /Fin/ | E29: /Fin/ | F29: /Fin/ | G29: /Fin/ | H29: /Fin/ | I29: /Fin/ | J29: /Fin/ | K29: /Fin/ | L29: /Fin/ | M29: /Fin/ | N29: /Fin/ | O29: /Fin/ | P29: /Fin/ | Q29: /Fin/

Sheet Wharehouse5
A1: <Nom> | B1: Rome | E1: Période | F1: 1 | Q1: /Fin/
Q2: /Fin/
A3: <Process> | B3: nectar needs (pallet) | C3: nectar needs (pallet) | D3: nectar (pallet) | E3: nectar sales (pallet) | F3: nectar sales (pallet) | G3: nectar turnover | H3: nectar turnover | I3: cost of nectar pallets storage | J3: cumulative result | K3: cumulative result | Q3: /Fin/
A4: Demand of nectar | B4: 1 | C4: -1 | D4: -1 | E4: 1 | F4: -1 | G4: 1000 | H4: =-G4 -> -1000 | I4: -12 | J4: =G4 -> 1000 | K4: =-I4 -> 12 | Q4: /Fin/
A5: <Periode_Debut> | B5: 0 | C5: 1 | D5: 0 | E5: 0 | F5: 1 | G5: 0 | H5: 1 | I5: 0 | J5: 0 | K5: 0 | Q5: /Fin/
A6: <Periode_Prolongement> | B6: 0 | C6: 0 | D6: 0 | E6: 0 | F6: 0 | G6: 0 | H6: 0 | I6: 0 | J6: 0 | K6: 20 | Q6: /Fin/
A7: <Source> | B7: Rome | C7: Rome | D7: Rome | E7: Rome | F7: Rome | G7: Rome | H7: Rome | I7: Rome | J7: Account | K7: Account | Q7: /Fin/
Q8: /Fin/
A9: <Process> | B9: cordial needs (pallet) | C9: cordial needs (pallet) | D9: cordial (pallet) | E9: cordial sales (pallet) | F9: cordial sales (pallet) | G9: cordial turnover | H9: cordial turnover | I9: cost of cordial pallets storage | J9: cumulative result | K9: cumulative result | Q9: /Fin/
A10: Demand of cordial | B10: 1 | C10: -1 | D10: -1 | E10: 1 | F10: -1 | G10: 1600 | H10: =-G10 -> -1600 | I10: -19 | J10: =G10 -> 1600 | K10: =-I10 -> 19 | Q10: /Fin/
A11: <Periode_Debut> | B11: 0 | C11: 1 | D11: 0 | E11: 0 | F11: 1 | G11: 0 | H11: 1 | I11: 0 | J11: 0 | K11: 0 | Q11: /Fin/
A12: <Periode_Prolongement> | B12: 0 | C12: 0 | D12: 0 | E12: 0 | F12: 0 | G12: 0 | H12: 0 | I12: 0 | J12: 0 | K12: 20 | Q12: /Fin/
A13: <Source> | B13: Rome | C13: Rome | D13: Rome | E13: Rome | F13: Rome | G13: Rome | H13: Rome | I13: Rome | J13: Account | K13: Account | Q13: /Fin/
Q14: /Fin/
Q15: /Fin/
Q16: /Fin/
A17: <Etat des lieux> | B17: <Minimal> | C17: <Maximal> | D17: 0 | E17: 1 | F17: 2 | G17: 3 | H17: 4 | I17: 5 | J17: 6 | K17: 7 | L17: 8 | M17: 9 | N17: 10 | O17: 11 | P17: 12 | Q17: /Fin/
A18: nectar (pallet) | B18: 0 | C18: 750 | D18: 10 | E18: 0 | F18: 5 | Q18: /Fin/
A19: cordial (pallet) | B19: 0 | C19: 750 | D19: 10 | E19: 0 | F19: 8 | Q19: /Fin/
A20: nectar turnover | B20: -1000000000 | C20: 1000000000 | D20: 0 | E20: 27000 | F20: 26000 | G20: -26000 | Q20: /Fin/
A21: cordial turnover | B21: -1000000000 | C21: 1000000000 | D21: 0 | E21: 30400 | F21: 27200 | G21: -27200 | Q21: /Fin/
A22: cost of nectar pallets storage | B22: -1000000000 | C22: 1000000000 | E22: 0 | F22: 60 | Q22: /Fin/
A23: cost of cordial pallets storage | B23: -1000000000 | C23: 1000000000 | E23: 0 | F23: 152 | Q23: /Fin/
A24: nectar needs (pallet) | B24: -1000000000 | C24: 1000000000 | E24: 29 | F24: 26 | G24: -26
A25: cordial needs (pallet) | B25: -1000000000 | C25: 1000000000 | E25: 19 | F25: 17 | G25: -17 | Q25: /Fin/
A26: nectar sales (pallet) | B26: -1000000000 | C26: 1000000000 | E26: 27 | F26: 26 | G26: -26
A27: cordial sales (pallet) | B27: -1000000000 | C27: 1000000000 | E27: 19 | F27: 17 | G27: -17
Q28: /Fin/
A29: /Fin/ | B29: /Fin/ | C29: /Fin/ | D29: /Fin/ | E29: /Fin/ | F29: /Fin/ | G29: /Fin/ | H29: /Fin/ | I29: /Fin/ | J29: /Fin/ | K29: /Fin/ | L29: /Fin/ | M29: /Fin/ | N29: /Fin/ | O29: /Fin/ | P29: /Fin/ | Q29: /Fin/

Sheet Wharehouse6
A1: <Nom> | B1: Bucharest | E1: Période | F1: 1 | Q1: /Fin/
Q2: /Fin/
A3: <Process> | B3: nectar needs (pallet) | C3: nectar needs (pallet) | D3: nectar (pallet) | E3: nectar sales (pallet) | F3: nectar sales (pallet) | G3: nectar turnover | H3: nectar turnover | I3: cost of nectar pallets storage | J3: cumulative result | K3: cumulative result | Q3: /Fin/
A4: Demand of nectar | B4: 1 | C4: -1 | D4: -1 | E4: 1 | F4: -1 | G4: 600 | H4: =-G4 -> -600 | I4: -12 | J4: =G4 -> 600 | K4: =-I4 -> 12 | Q4: /Fin/
A5: <Periode_Debut> | B5: 0 | C5: 1 | D5: 0 | E5: 0 | F5: 1 | G5: 0 | H5: 1 | I5: 0 | J5: 0 | K5: 0 | Q5: /Fin/
A6: <Periode_Prolongement> | B6: 0 | C6: 0 | D6: 0 | E6: 0 | F6: 0 | G6: 0 | H6: 0 | I6: 0 | J6: 0 | K6: 20 | Q6: /Fin/
A7: <Source> | B7: Bucharest | C7: Bucharest | D7: Bucharest | E7: Bucharest | F7: Bucharest | G7: Bucharest | H7: Bucharest | I7: Bucharest | J7: Account | K7: Account | Q7: /Fin/
Q8: /Fin/
A9: <Process> | B9: cordial needs (pallet) | C9: cordial needs (pallet) | D9: cordial (pallet) | E9: cordial sales (pallet) | F9: cordial sales (pallet) | G9: cordial turnover | H9: cordial turnover | I9: cost of cordial pallets storage | J9: cumulative result | K9: cumulative result | Q9: /Fin/
A10: Demand of cordial | B10: 1 | C10: -1 | D10: -1 | E10: 1 | F10: -1 | G10: 1200 | H10: =-G10 -> -1200 | I10: -19 | J10: =G10 -> 1200 | K10: =-I10 -> 19 | Q10: /Fin/
A11: <Periode_Debut> | B11: 0 | C11: 1 | D11: 0 | E11: 0 | F11: 1 | G11: 0 | H11: 1 | I11: 0 | J11: 0 | K11: 0 | Q11: /Fin/
A12: <Periode_Prolongement> | B12: 0 | C12: 0 | D12: 0 | E12: 0 | F12: 0 | G12: 0 | H12: 0 | I12: 0 | J12: 0 | K12: 20 | Q12: /Fin/
A13: <Source> | B13: Bucharest | C13: Bucharest | D13: Bucharest | E13: Bucharest | F13: Bucharest | G13: Bucharest | H13: Bucharest | I13: Bucharest | J13: Account | K13: Account | Q13: /Fin/
Q14: /Fin/
Q15: /Fin/
Q16: /Fin/
A17: <Etat des lieux> | B17: <Minimal> | C17: <Maximal> | D17: 0 | E17: 1 | F17: 2 | G17: 3 | H17: 4 | I17: 5 | J17: 6 | K17: 7 | L17: 8 | M17: 9 | N17: 10 | O17: 11 | P17: 12 | Q17: /Fin/
A18: nectar (pallet) | B18: 0 | C18: 750 | D18: 10 | E18: 3 | F18: 1 | Q18: /Fin/
A19: cordial (pallet) | B19: 0 | C19: 750 | D19: 10 | E19: 0 | F19: 3 | Q19: /Fin/
A20: nectar turnover | B20: -1000000000 | C20: 1000000000 | D20: 0 | E20: 9600 | F20: 10800 | G20: -10800 | Q20: /Fin/
A21: cordial turnover | B21: -1000000000 | C21: 1000000000 | D21: 0 | E21: 16800 | F21: 16800 | G21: -16800 | Q21: /Fin/
A22: cost of nectar pallets storage | B22: -1000000000 | C22: 1000000000 | E22: 36 | F22: 12 | Q22: /Fin/
A23: cost of cordial pallets storage | B23: -1000000000 | C23: 1000000000 | E23: 0 | F23: 57 | Q23: /Fin/
A24: nectar needs (pallet) | B24: -1000000000 | C24: 1000000000 | E24: 16 | F24: 18 | G24: -18
A25: cordial needs (pallet) | B25: -1000000000 | C25: 1000000000 | E25: 14 | F25: 14 | G25: -14 | Q25: /Fin/
A26: nectar sales (pallet) | B26: -1000000000 | C26: 1000000000 | E26: 16 | F26: 18 | G26: -18
A27: cordial sales (pallet) | B27: -1000000000 | C27: 1000000000 | E27: 14 | F27: 14 | G27: -14
Q28: /Fin/
A29: /Fin/ | B29: /Fin/ | C29: /Fin/ | D29: /Fin/ | E29: /Fin/ | F29: /Fin/ | G29: /Fin/ | H29: /Fin/ | I29: /Fin/ | J29: /Fin/ | K29: /Fin/ | L29: /Fin/ | M29: /Fin/ | N29: /Fin/ | O29: /Fin/ | P29: /Fin/ | Q29: /Fin/

Sheet Wharehouse7
A1: <Nom> | B1: Budapest | E1: Période | F1: 1 | Q1: /Fin/
Q2: /Fin/
A3: <Process> | B3: nectar needs (pallet) | C3: nectar needs (pallet) | D3: nectar (pallet) | E3: nectar sales (pallet) | F3: nectar sales (pallet) | G3: nectar turnover | H3: nectar turnover | I3: cost of nectar pallets storage | J3: cumulative result | K3: cumulative result | Q3: /Fin/
A4: Demand of nectar | B4: 1 | C4: -1 | D4: -1 | E4: 1 | F4: -1 | G4: 1100 | H4: =-G4 -> -1100 | I4: -12 | J4: =G4 -> 1100 | K4: =-I4 -> 12 | Q4: /Fin/
A5: <Periode_Debut> | B5: 0 | C5: 1 | D5: 0 | E5: 0 | F5: 1 | G5: 0 | H5: 1 | I5: 0 | J5: 0 | K5: 0 | Q5: /Fin/
A6: <Periode_Prolongement> | B6: 0 | C6: 0 | D6: 0 | E6: 0 | F6: 0 | G6: 0 | H6: 0 | I6: 0 | J6: 0 | K6: 20 | Q6: /Fin/
A7: <Source> | B7: Budapest | C7: Budapest | D7: Budapest | E7: Budapest | F7: Budapest | G7: Budapest | H7: Budapest | I7: Budapest | J7: Account | K7: Account | Q7: /Fin/
Q8: /Fin/
A9: <Process> | B9: cordial needs (pallet) | C9: cordial needs (pallet) | D9: cordial (pallet) | E9: cordial sales (pallet) | F9: cordial sales (pallet) | G9: cordial turnover | H9: cordial turnover | I9: cost of cordial pallets storage | J9: cumulative result | K9: cumulative result | Q9: /Fin/
A10: Demand of cordial | B10: 1 | C10: -1 | D10: -1 | E10: 1 | F10: -1 | G10: 1300 | H10: =-G10 -> -1300 | I10: -19 | J10: =G10 -> 1300 | K10: =-I10 -> 19 | Q10: /Fin/
A11: <Periode_Debut> | B11: 0 | C11: 1 | D11: 0 | E11: 0 | F11: 1 | G11: 0 | H11: 1 | I11: 0 | J11: 0 | K11: 0 | Q11: /Fin/
A12: <Periode_Prolongement> | B12: 0 | C12: 0 | D12: 0 | E12: 0 | F12: 0 | G12: 0 | H12: 0 | I12: 0 | J12: 0 | K12: 20 | Q12: /Fin/
A13: <Source> | B13: Budapest | C13: Budapest | D13: Budapest | E13: Budapest | F13: Budapest | G13: Budapest | H13: Budapest | I13: Budapest | J13: Account | K13: Account | Q13: /Fin/
Q14: /Fin/
Q15: /Fin/
Q16: /Fin/
A17: <Etat des lieux> | B17: <Minimal> | C17: <Maximal> | D17: 0 | E17: 1 | F17: 2 | G17: 3 | H17: 4 | I17: 5 | J17: 6 | K17: 7 | L17: 8 | M17: 9 | N17: 10 | O17: 11 | P17: 12 | Q17: /Fin/
A18: nectar (pallet) | B18: 0 | C18: 750 | D18: 10 | E18: 2 | F18: 49 | Q18: /Fin/
A19: cordial (pallet) | B19: 0 | C19: 750 | D19: 10 | E19: 0 | F19: 3 | Q19: /Fin/
A20: nectar turnover | B20: -1000000000 | C20: 1000000000 | D20: 0 | E20: 20900 | F20: 20900 | G20: -20900 | Q20: /Fin/
A21: cordial turnover | B21: -1000000000 | C21: 1000000000 | D21: 0 | E21: 26000 | F21: 23400 | G21: -23400 | Q21: /Fin/
A22: cost of nectar pallets storage | B22: -1000000000 | C22: 1000000000 | E22: 24 | F22: 588 | Q22: /Fin/
A23: cost of cordial pallets storage | B23: -1000000000 | C23: 1000000000 | E23: 0 | F23: 57 | Q23: /Fin/
A24: nectar needs (pallet) | B24: -1000000000 | C24: 1000000000 | E24: 19 | F24: 19 | G24: -19
A25: cordial needs (pallet) | B25: -1000000000 | C25: 1000000000 | E25: 20 | F25: 18 | G25: -18 | Q25: /Fin/
A26: nectar sales (pallet) | B26: -1000000000 | C26: 1000000000 | E26: 19 | F26: 19 | G26: -19
A27: cordial sales (pallet) | B27: -1000000000 | C27: 1000000000 | E27: 20 | F27: 18 | G27: -18
Q28: /Fin/
A29: /Fin/ | B29: /Fin/ | C29: /Fin/ | D29: /Fin/ | E29: /Fin/ | F29: /Fin/ | G29: /Fin/ | H29: /Fin/ | I29: /Fin/ | J29: /Fin/ | K29: /Fin/ | L29: /Fin/ | M29: /Fin/ | N29: /Fin/ | O29: /Fin/ | P29: /Fin/ | Q29: /Fin/

Sheet Wharehouse8
A1: <Nom> | B1: Kemijarvi | E1: Période | F1: 1 | Q1: /Fin/
Q2: /Fin/
A3: <Process> | B3: nectar needs (pallet) | C3: nectar needs (pallet) | D3: nectar (pallet) | E3: nectar sales (pallet) | F3: nectar sales (pallet) | G3: nectar turnover | H3: nectar turnover | I3: cost of nectar pallets storage | J3: cumulative result | K3: cumulative result | Q3: /Fin/
A4: Demand of nectar | B4: 1 | C4: -1 | D4: -1 | E4: 1 | F4: -1 | G4: 700 | H4: =-G4 -> -700 | I4: -12 | J4: =G4 -> 700 | K4: =-I4 -> 12 | Q4: /Fin/
A5: <Periode_Debut> | B5: 0 | C5: 1 | D5: 0 | E5: 0 | F5: 1 | G5: 0 | H5: 1 | I5: 0 | J5: 0 | K5: 0 | Q5: /Fin/
A6: <Periode_Prolongement> | B6: 0 | C6: 0 | D6: 0 | E6: 0 | F6: 0 | G6: 0 | H6: 0 | I6: 0 | J6: 0 | K6: 20 | Q6: /Fin/
A7: <Source> | B7: Kemijarvi | C7: Kemijarvi | D7: Kemijarvi | E7: Kemijarvi | F7: Kemijarvi | G7: Kemijarvi | H7: Kemijarvi | I7: Kemijarvi | J7: Account | K7: Account | Q7: /Fin/
Q8: /Fin/
A9: <Process> | B9: cordial needs (pallet) | C9: cordial needs (pallet) | D9: cordial (pallet) | E9: cordial sales (pallet) | F9: cordial sales (pallet) | G9: cordial turnover | H9: cordial turnover | I9: cost of cordial pallets storage | J9: cumulative result | K9: cumulative result | Q9: /Fin/
A10: Demand of cordial | B10: 1 | C10: -1 | D10: -1 | E10: 1 | F10: -1 | G10: 1300 | H10: =-G10 -> -1300 | I10: -19 | J10: =G10 -> 1300 | K10: =-I10 -> 19 | Q10: /Fin/
A11: <Periode_Debut> | B11: 0 | C11: 1 | D11: 0 | E11: 0 | F11: 1 | G11: 0 | H11: 1 | I11: 0 | J11: 0 | K11: 0 | Q11: /Fin/
A12: <Periode_Prolongement> | B12: 0 | C12: 0 | D12: 0 | E12: 0 | F12: 0 | G12: 0 | H12: 0 | I12: 0 | J12: 0 | K12: 20 | Q12: /Fin/
A13: <Source> | B13: Kemijarvi | C13: Kemijarvi | D13: Kemijarvi | E13: Kemijarvi | F13: Kemijarvi | G13: Kemijarvi | H13: Kemijarvi | I13: Kemijarvi | J13: Account | K13: Account | Q13: /Fin/
Q14: /Fin/
Q15: /Fin/
Q16: /Fin/
A17: <Etat des lieux> | B17: <Minimal> | C17: <Maximal> | D17: 0 | E17: 1 | F17: 2 | G17: 3 | H17: 4 | I17: 5 | J17: 6 | K17: 7 | L17: 8 | M17: 9 | N17: 10 | O17: 11 | P17: 12 | Q17: /Fin/
A18: nectar (pallet) | B18: 0 | C18: 750 | D18: 10 | E18: 0 | F18: 2 | Q18: /Fin/
A19: cordial (pallet) | B19: 0 | C19: 750 | D19: 10 | E19: 0 | F19: 3 | Q19: /Fin/
A20: nectar turnover | B20: -1000000000 | C20: 1000000000 | D20: 0 | E20: 11900 | F20: 11200 | G20: -11200 | Q20: /Fin/
A21: cordial turnover | B21: -1000000000 | C21: 1000000000 | D21: 0 | E21: 22100 | F21: 19500 | G21: -19500 | Q21: /Fin/
A22: cost of nectar pallets storage | B22: -1000000000 | C22: 1000000000 | E22: 0 | F22: 24 | Q22: /Fin/
A23: cost of cordial pallets storage | B23: -1000000000 | C23: 1000000000 | E23: 0 | F23: 57 | Q23: /Fin/
A24: nectar needs (pallet) | B24: -1000000000 | C24: 1000000000 | E24: 17 | F24: 16 | G24: -16
A25: cordial needs (pallet) | B25: -1000000000 | C25: 1000000000 | E25: 17 | F25: 15 | G25: -15 | Q25: /Fin/
A26: nectar sales (pallet) | B26: -1000000000 | C26: 1000000000 | E26: 17 | F26: 16 | G26: -16
A27: cordial sales (pallet) | B27: -1000000000 | C27: 1000000000 | E27: 17 | F27: 15 | G27: -15
Q28: /Fin/
A29: /Fin/ | B29: /Fin/ | C29: /Fin/ | D29: /Fin/ | E29: /Fin/ | F29: /Fin/ | G29: /Fin/ | H29: /Fin/ | I29: /Fin/ | J29: /Fin/ | K29: /Fin/ | L29: /Fin/ | M29: /Fin/ | N29: /Fin/ | O29: /Fin/ | P29: /Fin/ | Q29: /Fin/

Sheet Wharehouse9
A1: <Nom> | B1: Warsaw | E1: Période | F1: 1 | Q1: /Fin/
Q2: /Fin/
A3: <Process> | B3: nectar needs (pallet) | C3: nectar needs (pallet) | D3: nectar (pallet) | E3: nectar sales (pallet) | F3: nectar sales (pallet) | G3: nectar turnover | H3: nectar turnover | I3: cost of nectar pallets storage | J3: cumulative result | K3: cumulative result | Q3: /Fin/
A4: Demand of nectar | B4: 1 | C4: -1 | D4: -1 | E4: 1 | F4: -1 | G4: 800 | H4: =-G4 -> -800 | I4: -12 | J4: =G4 -> 800 | K4: =-I4 -> 12 | Q4: /Fin/
A5: <Periode_Debut> | B5: 0 | C5: 1 | D5: 0 | E5: 0 | F5: 1 | G5: 0 | H5: 1 | I5: 0 | J5: 0 | K5: 0 | Q5: /Fin/
A6: <Periode_Prolongement> | B6: 0 | C6: 0 | D6: 0 | E6: 0 | F6: 0 | G6: 0 | H6: 0 | I6: 0 | J6: 0 | K6: 20 | Q6: /Fin/
A7: <Source> | B7: Warsaw | C7: Warsaw | D7: Warsaw | E7: Warsaw | F7: Warsaw | G7: Warsaw | H7: Warsaw | I7: Warsaw | J7: Account | K7: Account | Q7: /Fin/
Q8: /Fin/
A9: <Process> | B9: cordial needs (pallet) | C9: cordial needs (pallet) | D9: cordial (pallet) | E9: cordial sales (pallet) | F9: cordial sales (pallet) | G9: cordial turnover | H9: cordial turnover | I9: cost of cordial pallets storage | J9: cumulative result | K9: cumulative result | Q9: /Fin/
A10: Demand of cordial | B10: 1 | C10: -1 | D10: -1 | E10: 1 | F10: -1 | G10: 1400 | H10: =-G10 -> -1400 | I10: -19 | J10: =G10 -> 1400 | K10: =-I10 -> 19 | Q10: /Fin/
A11: <Periode_Debut> | B11: 0 | C11: 1 | D11: 0 | E11: 0 | F11: 1 | G11: 0 | H11: 1 | I11: 0 | J11: 0 | K11: 0 | Q11: /Fin/
A12: <Periode_Prolongement> | B12: 0 | C12: 0 | D12: 0 | E12: 0 | F12: 0 | G12: 0 | H12: 0 | I12: 0 | J12: 0 | K12: 20 | Q12: /Fin/
A13: <Source> | B13: Warsaw | C13: Warsaw | D13: Warsaw | E13: Warsaw | F13: Warsaw | G13: Warsaw | H13: Warsaw | I13: Warsaw | J13: Account | K13: Account | Q13: /Fin/
Q14: /Fin/
Q15: /Fin/
Q16: /Fin/
A17: <Etat des lieux> | B17: <Minimal> | C17: <Maximal> | D17: 0 | E17: 1 | F17: 2 | G17: 3 | H17: 4 | I17: 5 | J17: 6 | K17: 7 | L17: 8 | M17: 9 | N17: 10 | O17: 11 | P17: 12 | Q17: /Fin/
A18: nectar (pallet) | B18: 0 | C18: 750 | D18: 10 | E18: 0 | F18: 2 | Q18: /Fin/
A19: cordial (pallet) | B19: 0 | C19: 750 | D19: 10 | E19: 23 | F19: 8 | Q19: /Fin/
A20: nectar turnover | B20: -1000000000 | C20: 1000000000 | D20: 0 | E20: 15200 | F20: 13600 | G20: -13600 | Q20: /Fin/
A21: cordial turnover | B21: -1000000000 | C21: 1000000000 | D21: 0 | E21: 23800 | F21: 21000 | G21: -21000 | Q21: /Fin/
A22: cost of nectar pallets storage | B22: -1000000000 | C22: 1000000000 | E22: 0 | F22: 24 | Q22: /Fin/
A23: cost of cordial pallets storage | B23: -1000000000 | C23: 1000000000 | E23: 437 | F23: 152 | Q23: /Fin/
A24: nectar needs (pallet) | B24: -1000000000 | C24: 1000000000 | E24: 19 | F24: 17 | G24: -17
A25: cordial needs (pallet) | B25: -1000000000 | C25: 1000000000 | E25: 17 | F25: 15 | G25: -15 | Q25: /Fin/
A26: nectar sales (pallet) | B26: -1000000000 | C26: 1000000000 | E26: 19 | F26: 17 | G26: -17
A27: cordial sales (pallet) | B27: -1000000000 | C27: 1000000000 | E27: 17 | F27: 15 | G27: -15
Q28: /Fin/
A29: /Fin/ | B29: /Fin/ | C29: /Fin/ | D29: /Fin/ | E29: /Fin/ | F29: /Fin/ | G29: /Fin/ | H29: /Fin/ | I29: /Fin/ | J29: /Fin/ | K29: /Fin/ | L29: /Fin/ | M29: /Fin/ | N29: /Fin/ | O29: /Fin/ | P29: /Fin/ | Q29: /Fin/

Sheet Wharehouse10
A1: <Nom> | B1: Berlin | E1: Période | F1: 1 | Q1: /Fin/
Q2: /Fin/
A3: <Process> | B3: nectar needs (pallet) | C3: nectar needs (pallet) | D3: nectar (pallet) | E3: nectar sales (pallet) | F3: nectar sales (pallet) | G3: nectar turnover | H3: nectar turnover | I3: cost of nectar pallets storage | J3: cumulative result | K3: cumulative result | Q3: /Fin/
A4: Demand of nectar | B4: 1 | C4: -1 | D4: -1 | E4: 1 | F4: -1 | G4: 1000 | H4: =-G4 -> -1000 | I4: -12 | J4: =G4 -> 1000 | K4: =-I4 -> 12 | Q4: /Fin/
A5: <Periode_Debut> | B5: 0 | C5: 1 | D5: 0 | E5: 0 | F5: 1 | G5: 0 | H5: 1 | I5: 0 | J5: 0 | K5: 0 | Q5: /Fin/
A6: <Periode_Prolongement> | B6: 0 | C6: 0 | D6: 0 | E6: 0 | F6: 0 | G6: 0 | H6: 0 | I6: 0 | J6: 0 | K6: 20 | Q6: /Fin/
A7: <Source> | B7: Berlin | C7: Berlin | D7: Berlin | E7: Berlin | F7: Berlin | G7: Berlin | H7: Berlin | I7: Berlin | J7: Account | K7: Account | Q7: /Fin/
Q8: /Fin/
A9: <Process> | B9: cordial needs (pallet) | C9: cordial needs (pallet) | D9: cordial (pallet) | E9: cordial sales (pallet) | F9: cordial sales (pallet) | G9: cordial turnover | H9: cordial turnover | I9: cost of cordial pallets storage | J9: cumulative result | K9: cumulative result | Q9: /Fin/
A10: Demand of cordial | B10: 1 | C10: -1 | D10: -1 | E10: 1 | F10: -1 | G10: 1600 | H10: =-G10 -> -1600 | I10: -19 | J10: =G10 -> 1600 | K10: =-I10 -> 19 | Q10: /Fin/
A11: <Periode_Debut> | B11: 0 | C11: 1 | D11: 0 | E11: 0 | F11: 1 | G11: 0 | H11: 1 | I11: 0 | J11: 0 | K11: 0 | Q11: /Fin/
A12: <Periode_Prolongement> | B12: 0 | C12: 0 | D12: 0 | E12: 0 | F12: 0 | G12: 0 | H12: 0 | I12: 0 | J12: 0 | K12: 20 | Q12: /Fin/
A13: <Source> | B13: Berlin | C13: Berlin | D13: Berlin | E13: Berlin | F13: Berlin | G13: Berlin | H13: Berlin | I13: Berlin | J13: Account | K13: Account | Q13: /Fin/
Q14: /Fin/
Q15: /Fin/
Q16: /Fin/
A17: <Etat des lieux> | B17: <Minimal> | C17: <Maximal> | D17: 0 | E17: 1 | F17: 2 | G17: 3 | H17: 4 | I17: 5 | J17: 6 | K17: 7 | L17: 8 | M17: 9 | N17: 10 | O17: 11 | P17: 12 | Q17: /Fin/
A18: nectar (pallet) | B18: 0 | C18: 750 | D18: 10 | E18: 0 | F18: 6 | Q18: /Fin/
A19: cordial (pallet) | B19: 0 | C19: 750 | D19: 10 | E19: 0 | F19: 34 | Q19: /Fin/
A20: nectar turnover | B20: -1000000000 | C20: 1000000000 | D20: 0 | E20: 25000 | F20: 24000 | G20: -24000 | Q20: /Fin/
A21: cordial turnover | B21: -1000000000 | C21: 1000000000 | D21: 0 | E21: 28800 | F21: 24000 | G21: -24000 | Q21: /Fin/
A22: cost of nectar pallets storage | B22: -1000000000 | C22: 1000000000 | E22: 0 | F22: 72 | Q22: /Fin/
A23: cost of cordial pallets storage | B23: -1000000000 | C23: 1000000000 | E23: 0 | F23: 646 | Q23: /Fin/
A24: nectar needs (pallet) | B24: -1000000000 | C24: 1000000000 | E24: 25 | F24: 24 | G24: -24
A25: cordial needs (pallet) | B25: -1000000000 | C25: 1000000000 | E25: 18 | F25: 15 | G25: -15 | Q25: /Fin/
A26: nectar sales (pallet) | B26: -1000000000 | C26: 1000000000 | E26: 25 | F26: 24 | G26: -24
A27: cordial sales (pallet) | B27: -1000000000 | C27: 1000000000 | E27: 18 | F27: 15 | G27: -15
Q28: /Fin/
A29: /Fin/ | B29: /Fin/ | C29: /Fin/ | D29: /Fin/ | E29: /Fin/ | F29: /Fin/ | G29: /Fin/ | H29: /Fin/ | I29: /Fin/ | J29: /Fin/ | K29: /Fin/ | L29: /Fin/ | M29: /Fin/ | N29: /Fin/ | O29: /Fin/ | P29: /Fin/ | Q29: /Fin/

Sheet Liste_Elements
A1: Nom | B1: Feuille | D1: /Fin/
A2: Account | B2: Account | D2: /Fin/
A3: Auckland factory | B3: Auckland | D3: /Fin/
A4: Intercontinental transport | B4: Intercontinental_transport | D4: /Fin/
A5: Purchasing | B5: Purchasing | D5: /Fin/
A6: Arnhem factory | B6: Arnhem | D6: /Fin/
A7: Vesoul factory | B7: Vesoul | D7: /Fin/
A8: Lorry 1 | B8: Lorry1 | D8: /Fin/
A9: Lorry 2 | B9: Lorry2 | D9: /Fin/
A10: Lorry 3 | B10: Lorry3 | D10: /Fin/
A11: Paris | B11: Wharehouse1 | D11: /Fin/
A12: Rauma | B12: Wharehouse2 | D12: /Fin/
... A20: Berlin | B20: Wharehouse10 | D20: /Fin/
D21: /Fin/
A22: /Fin/ | B22: /Fin/ | C22: /Fin/ | D22: /Fin/

Sheet Intercontinental_transport
A1: <Nom> | B1: Intercontinental transport | E1: Période | F1: 1 | Q1: /Fin/
Q2: /Fin/
A3: <Process> | B3: puree (bin) | C3: puree (bin) | D3: Intercontinental transport cost | E3: Intercontinental transport cost | F3: CO2 production | G3: CO2 production | H3: puree storage cost | I3: puree storage cost | J3: cumulative result | K3: cumulative result | L3: cumulative result | M3: cumulative CO2 | Q3: /Fin/
A4: Puree transport to Arnhem | B4: 1 | C4: =-B4 -> -1 | D4: 200 | E4: =-D4 -> -200 | F4: 190 | G4: =-F4 -> -190 | H4: =-40 -> -40 | I4: =(2000+D4)*0.02 -> 44 | J4: =-D4 -> -200 | K4: =-H4 -> 40 | L4: =-I4 -> -44 | M4: =F4 -> 190 | Q4: /Fin/
A5: <Periode_Debut> | B5: 1 | C5: 0 | D5: 0 | E5: 1 | F5: 0 | G5: 1 | H5: 0 | I5: 2 | J5: 0 | K5: 0 | L5: 2 | M5: 0 | Q5: /Fin/
A6: <Periode_Prolongement> | B6: 0 | C6: 0 | D6: 0 | E6: 0 | F6: 0 | G6: 0 | H6: 0 | I6: 0 | J6: 0 | K6: 20 | L6: 20 | M6: 0 | Q6: /Fin/
A7: <Source> | B7: Arnhem factory | C7: Auckland factory | D7: Intercontinental transport | E7: Intercontinental transport | F7: Intercontinental transport | G7: Intercontinental transport | H7: Auckland factory | I7: Arnhem factory | J7: Account | K7: Account | L7: Account | M7: Account | Q7: /Fin/
Q8: /Fin/
A9: <Process> | B9: concentrate (bin) | C9: concentrate (bin) | D9: Intercontinental transport cost | E9: Intercontinental transport cost | F9: CO2 production | G9: CO2 production | H9: concentrate storage cost | I9: concentrate storage cost | J9: cumulative result | K9: cumulative result | L9: cumulative result | M9: cumulative CO2 | Q9: /Fin/
A10: Concentrate transport to Arnhem | B10: 1 | C10: =-B10 -> -1 | D10: 200 | E10: =-D10 -> -200 | F10: 190 | G10: =-F10 -> -190 | H10: =-60 -> -60 | I10: =(3000+D10)*0.02 -> 64 | J10: =-D10 -> -200 | K10: =-H10 -> 60 | L10: =-I10 -> -64 | M10: =F10 -> 190 | Q10: /Fin/
A11: <Periode_Debut> | B11: 1 | C11: 0 | D11: 0 | E11: 1 | F11: 0 | G11: 1 | H11: 0 | I11: 2 | J11: 0 | K11: 0 | L11: 2 | M11: 0 | Q11: /Fin/
A12: <Periode_Prolongement> | B12: 0 | C12: 0 | D12: 0 | E12: 0 | F12: 0 | G12: 0 | H12: 0 | I12: 0 | J12: 0 | K12: 20 | L12: 20 | M12: 0 | Q12: /Fin/
A13: <Source> | B13: Arnhem factory | C13: Auckland factory | D13: Intercontinental transport | E13: Intercontinental transport | F13: Intercontinental transport | G13: Intercontinental transport | H13: Auckland factory | I13: Arnhem factory | J13: Account | K13: Account | L13: Account | M13: Account | Q13: /Fin/
Q14: /Fin/
A15: <Process> | B15: concentrate (bin) | C15: concentrate (bin) | D15: Intercontinental transport cost | E15: Intercontinental transport cost | F15: CO2 production | G15: CO2 production | H15: concentrate storage cost | I15: concentrate storage cost | J15: cumulative result | K15: cumulative result | L15: cumulative result | M15: cumulative CO2 | Q15: /Fin/
A16: Concentrate transport to Vesoul | B16: 1 | C16: =-B16 -> -1 | D16: 200 | E16: =-D16 -> -200 | F16: 190 | G16: =-F16 -> -190 | H16: =-60 -> -60 | I16: =(3000+D16)*0.02 -> 64 | J16: =-D16 -> -200 | K16: =-H16 -> 60 | L16: =-I16 -> -64 | M16: =F16 -> 190 | Q16: /Fin/
A17: <Periode_Debut> | B17: 1 | C17: 0 | D17: 0 | E17: 1 | F17: 0 | G17: 1 | H17: 0 | I17: 2 | J17: 0 | K17: 0 | L17: 2 | M17: 0 | Q17: /Fin/
A18: <Periode_Prolongement> | B18: 0 | C18: 0 | D18: 0 | E18: 0 | F18: 0 | G18: 0 | H18: 0 | I18: 0 | J18: 0 | K18: 20 | L18: 20 | M18: 0 | Q18: /Fin/
A19: <Source> | B19: Vesoul factory | C19: Auckland factory | D19: Intercontinental transport | E19: Intercontinental transport | F19: Intercontinental transport | G19: Intercontinental transport | H19: Auckland factory | I19: Vesoul factory | J19: Account | K19: Account | L19: Account | M19: Account | Q19: /Fin/
Q20: /Fin/
Q21: /Fin/
A22: <Etat des lieux> | B22: <Minimal> | C22: <Maximal> | D22: 0 | E22: 1 | F22: 2 | G22: 3 | H22: 4 | I22: 5 | J22: 6 | K22: 7 | L22: 8 | M22: 9 | N22: 10 | O22: 11 | P22: 12 | Q22: /Fin/
A23: Intercontinental transport cost | B23: -1000000000 | C23: 1000000000 | E23: 15000 | F23: 15000 | G23: -15000 | Q23: /Fin/
A24: CO2 production | B24: -1000000000 | C24: 1000000000 | E24: 14250 | F24: 14250 | G24: -14250 | Q24: /Fin/
Q25: /Fin/
A26: /Fin/ | B26: /Fin/ | C26: /Fin/ | D26: /Fin/ | E26: /Fin/ | F26: /Fin/ | G26: /Fin/ | H26: /Fin/ | I26: /Fin/ | J26: /Fin/ | K26: /Fin/ | L26: /Fin/ | M26: /Fin/ | N26: /Fin/ | O26: /Fin/ | P26: /Fin/ | Q26: /Fin/

Sheet Purchasing
A1: <Nom> | B1: Purchasing | E1: Période | F1: 1 | Q1: /Fin/
Q2: /Fin/
Q3: /Fin/
A4: <Process> | B4: puree (bin) | C4: Puree Purchasing cost | D4: Puree Purchasing cost | E4: CO2 from puree purchasing | F4: CO2 from puree purchasing | G4: puree storage cost | H4: cumulative result | I4: cumulative result | J4: cumulative CO2 | Q4: /Fin/
A5: Puree Purchasing | B5: 1 | C5: 6000 | D5: =-C5 -> -6000 | E5: 3100 | F5: =-E5 -> -3100 | G5: 44 | H5: =-C5 -> -6000 | I5: =-G5 -> -44 | J5: =E5 -> 3100 | Q5: /Fin/
A6: <Periode_Debut> | B6: 0 | C6: 0 | D6: 1 | E6: 0 | F6: 1 | G6: 1 | H6: 0 | I6: 1 | J6: 0 | Q6: /Fin/
A7: <Periode_Prolongement> | B7: 0 | C7: 0 | D7: 0 | E7: 0 | F7: 0 | G7: 0 | H7: 0 | I7: 20 | J7: 0 | Q7: /Fin/
A8: <Source> | B8: Arnhem factory | C8: Purchasing | D8: Purchasing | E8: Purchasing | F8: Purchasing | G8: Arnhem factory | H8: Account | I8: Account | J8: Account | Q8: /Fin/
Q9: /Fin/
A10: <Process> | B10: concentrate (bin) | C10: concentrate Purchasing cost | D10: concentrate Purchasing cost | E10: CO2 from concentrate purchasing | F10: CO2 from concentrate purchasing | G10: concentrate storage cost | H10: cumulative result | I10: cumulative result | J10: cumulative CO2 | Q10: /Fin/
A11: Concentrate Purchasing for Arnhem | B11: 1 | C11: 9000 | D11: =-C11 -> -9000 | E11: 4400 | F11: =-E11 -> -4400 | G11: 64 | H11: =-C11 -> -9000 | I11: =-G11 -> -64 | J11: =E11 -> 4400 | Q11: /Fin/
A12: <Periode_Debut> | B12: 0 | C12: 0 | D12: 1 | E12: 0 | F12: 1 | G12: 1 | H12: 0 | I12: 1 | J12: 0 | Q12: /Fin/
A13: <Periode_Prolongement> | B13: 0 | C13: 0 | D13: 0 | E13: 0 | F13: 0 | G13: 0 | H13: 0 | I13: 20 | J13: 0 | Q13: /Fin/
A14: <Source> | B14: Arnhem factory | C14: Purchasing | D14: Purchasing | E14: Purchasing | F14: Purchasing | G14: Arnhem factory | H14: Account | I14: Account | J14: Account | Q14: /Fin/
Q15: /Fin/
A16: <Process> | B16: concentrate (bin) | C16: concentrate Purchasing cost | D16: concentrate Purchasing cost | E16: CO2 from concentrate purchasing | F16: CO2 from concentrate purchasing | G16: concentrate storage cost | H16: cumulative result | I16: cumulative result | J16: cumulative CO2 | Q16: /Fin/
A17: Concentrate Purchasing for Vesoul | B17: 1 | C17: 9000 | D17: =-C17 -> -9000 | E17: 4400 | F17: =-E17 -> -4400 | G17: 64 | H17: =-C17 -> -9000 | I17: =-G17 -> -64 | J17: =E17 -> 4400 | Q17: /Fin/
A18: <Periode_Debut> | B18: 0 | C18: 0 | D18: 1 | E18: 0 | F18: 1 | G18: 1 | H18: 0 | I18: 1 | J18: 0 | Q18: /Fin/
A19: <Periode_Prolongement> | B19: 0 | C19: 0 | D19: 0 | E19: 0 | F19: 0 | G19: 0 | H19: 0 | I19: 20 | J19: 0 | Q19: /Fin/
A20: <Source> | B20: Vesoul factory | C20: Purchasing | D20: Purchasing | E20: Purchasing | F20: Purchasing | G20: Vesoul factory | H20: Account | I20: Account | J20: Account | Q20: /Fin/
Q21: /Fin/
A22: <Process> | B22: pack (batch) | C22: Pack Purchasing cost | D22: Pack Purchasing cost | E22: CO2 from pack purchasing | F22: CO2 from pack purchasing | G22: pack storage cost | H22: cumulative result | I22: cumulative result | J22: cumulative CO2 | Q22: /Fin/
A23: Pack Purchasing | B23: 1 | C23: 1000 | D23: =-C23 -> -1000 | E23: 900 | F23: =-E23 -> -900 | G23: =0.02*C23 -> 20 | H23: =-C23 -> -1000 | I23: =-G23 -> -20 | J23: =E23 -> 900 | Q23: /Fin/
A24: <Periode_Debut> | B24: 0 | C24: 0 | D24: 1 | E24: 0 | F24: 1 | G24: 1 | H24: 0 | I24: 1 | J24: 0 | Q24: /Fin/
A25: <Periode_Prolongement> | B25: 0 | C25: 0 | D25: 0 | E25: 0 | F25: 0 | G25: 0 | H25: 0 | I25: 20 | J25: 0 | Q25: /Fin/
A26: <Source> | B26: Arnhem factory | C26: Purchasing | D26: Purchasing | E26: Purchasing | F26: Purchasing | G26: Arnhem factory | H26: Account | I26: Account | J26: Account | Q26: /Fin/
Q27: /Fin/
A28: <Process> | B28: bottle (batch) | C28: bottles Purchasing cost | D28: bottles Purchasing cost | E28: CO2 from bottle purchasing | F28: CO2 from bottle purchasing | G28: bottles storage cost | H28: cumulative result | I28: cumulative result | J28: cumulative CO2 | Q28: /Fin/
A29: Bottle Purchasing | B29: 1 | C29: 3000 | D29: =-C29 -> -3000 | E29: 4000 | F29: =-E29 -> -4000 | G29: =0.02*C29 -> 60 | H29: =-C29 -> -3000 | I29: =-G29 -> -60 | J29: =E29 -> 4000 | Q29: /Fin/
A30: <Periode_Debut> | B30: 0 | C30: 0 | D30: 1 | E30: 0 | F30: 1 | G30: 1 | H30: 0 | I30: 1 | J30: 0 | Q30: /Fin/
A31: <Periode_Prolongement> | B31: 0 | C31: 0 | D31: 0 | E31: 0 | F31: 0 | G31: 0 | H31: 0 | I31: 20 | J31: 0 | Q31: /Fin/
A32: <Source> | B32: Vesoul factory | C32: Purchasing | D32: Purchasing | E32: Purchasing | F32: Purchasing | G32: Vesoul factory | H32: Account | I32: Account | J32: Account | Q32: /Fin/
Q33: /Fin/
A34: <Process> | B34: sugar (tonne) | C34: Sugar Purchasing cost | D34: Sugar Purchasing cost | E34: CO2 from sugar purchasing | F34: CO2 from sugar purchasing | G34: sugar storage cost | H34: cumulative result | I34: cumulative result | J34: cumulative CO2 | Q34: /Fin/
A35: Sugar Purchasing | B35: 1 | C35: 400 | D35: =-C35 -> -400 | E35: 300 | F35: =-E35 -> -300 | G35: =0.02*C35 -> 8 | H35: =-C35 -> -400 | I35: =-G35 -> -8 | J35: =E35 -> 300 | Q35: /Fin/
A36: <Periode_Debut> | B36: 0 | C36: 0 | D36: 1 | E36: 0 | F36: 1 | G36: 1 | H36: 0 | I36: 1 | J36: 0 | Q36: /Fin/
A37: <Periode_Prolongement> | B37: 0 | C37: 0 | D37: 0 | E37: 0 | F37: 0 | G37: 0 | H37: 0 | I37: 20 | J37: 0 | Q37: /Fin/
A38: <Source> | B38: Vesoul factory | C38: Purchasing | D38: Purchasing | E38: Purchasing | F38: Purchasing | G38: Vesoul factory | H38: Account | I38: Account | J38: Account | Q38: /Fin/
Q39: /Fin/
Q40: /Fin/
A41: <Etat des lieux> | B41: <Minimal> | C41: <Maximal> | D41: 0 | E41: 1 | F41: 2 | G41: 3 | H41: 4 | I41: 5 | J41: 6 | K41: 7 | L41: 8 | M41: 9 | N41: 10 | O41: 11 | P41: 12 | Q41: /Fin/
A42: Puree Purchasing cost | B42: -1000000000 | C42: 1000000000 | E42: 0 | F42: 0 | G42: 0 | Q42: /Fin/
A43: concentrate Purchasing cost | B43: -1000000000 | C43: 1000000000 | E43: 0 | F43: 0 | G43: 0 | Q43: /Fin/
A44: Pack Purchasing cost | B44: -1000000000 | C44: 1000000000 | E44: 20000 | F44: 10000 | G44: -10000 | Q44: /Fin/
A45: bottles Purchasing cost | B45: -1000000000 | C45: 1000000000 | E45: 60000 | F45: 30000 | G45: -30000 | Q45: /Fin/
A46: Sugar Purchasing cost | B46: -1000000000 | C46: 1000000000 | E46: 8000 | F46: 4000 | G46: -4000 | Q46: /Fin/
A47: CO2 from puree purchasing | B47: -1000000000 | C47: 1000000000 | E47: 0 | F47: 0 | G47: 0 | Q47: /Fin/
A48: CO2 from concentrate purchasing | B48: -1000000000 | C48: 1000000000 | E48: 0 | F48: 0 | G48: 0 | Q48: /Fin/
A49: CO2 from pack purchasing | B49: -1000000000 | C49: 1000000000 | E49: 18000 | F49: 9000 | G49: -9000 | Q49: /Fin/
A50: CO2 from bottle purchasing | B50: -1000000000 | C50: 1000000000 | E50: 80000 | F50: 40000 | G50: -40000 | Q50: /Fin/
A51: CO2 from sugar purchasing | B51: -1000000000 | C51: 1000000000 | E51: 6000 | F51: 3000 | G51: -3000 | Q51: /Fin/
Q52: /Fin/
Q53: /Fin/
A54: /Fin/ | B54: /Fin/ | C54: /Fin/ | D54: /Fin/ | E54: /Fin/ | F54: /Fin/ | G54: /Fin/ | H54: /Fin/ | I54: /Fin/ | J54: /Fin/ | K54: /Fin/ | L54: /Fin/ | M54: /Fin/ | N54: /Fin/ | O54: /Fin/ | P54: /Fin/ | Q54: /Fin/

Sheet Demande_alea
K1: 1 | L1: 2 | M1: 3 | N1: 4 | O1: 5 | P1: 6 | Q1: 7 | R1: 8 | S1: 9 | T1: 10 | U1: 11 | V1: 12 | W1: 13 | X1: 14 | Y1: 15 | Z1: 16 | AA1: 17 | AB1: 18 | AC1: 19 | AD1: 20 | AE1: 21 | AF1: 22 | AG1: 23 | AH1: 24
D2: Coeff. Dir. | E2: Constante | F2: Fréquence | G2: Amplitude | H2: Décalage | I2: Ecart-type | J2: Prix | K2: -23 | L2: -22 | M2: -21 | N2: -20 | O2: -19 | P2: -18 | Q2: -17 | R2: -16 | S2: -15 | T2: -14 | U2: -13 | V2: -12 | W2: -11 | X2: -10 | Y2: -9 | Z2: -8 | AA2: -7 | AB2: -6 | AC2: -5 | AD2: -4 | AE2: -3 | AF2: -2 | AG2: -1 | AH2: 0 | AI2: 1 | AJ2: 2 | AK2: 3 | AL2: 4 | AM2: 5 | AN2: 6 | AO2: 7 | AP2: 8 | AQ2: 9 | AR2: 10 | AS2: 11 | AT2: 12 | AU2: 13 | AV2: 14 | AW2: 15 | AX2: 16 | AY2: 17 | AZ2: 18 | BA2: 19 | BB2: 20 | BC2: 21 | BD2: 22 | BE2: 23 | BF2: 24
D3: a | E3: b | F3: f | G3: k | H3: d | I3: s
A4: Paris | B4: Wharehouse 1 | C4: Nectar | D4: 0.3 | E4: 22 | F4: 1 | G4: 0.2 | H4: 3 | I4: 1 | J4: 1000 | K4: =MAX(ARRONDI(($D4*K$2+$E4)*(1+$G4*SIN($F4*2*PI()/12*(K$2-$H4)))+($I4*LOI.NORMALE.STANDARD.INVERSE(ALEA()));0);0) | M4: MAX(ARRONDI((a*t+b)*(1+k*SIN(f*2*PI()/12*(t-d)))+(s*LOI.NORMALE.STANDARD.INVERSE(ALEA()));0);0)
A5: Paris | B5: Wharehouse 1 | C5: Cordial | D5: 0.3 | E5: 15 | F5: 2 | G5: 0.2 | H5: 0 | I5: 1 | J5: 1600
A6: Rauma | B6: Wharehouse 2 | C6: Nectar | D6: 0.15 | E6: 22 | F6: -1 | G6: 0.2 | H6: 0 | I6: 1 | J6: 700
A7: Rauma | B7: Wharehouse 2 | C7: Cordial | D7: 0.15 | E7: 15 | F7: 2 | G7: 0.2 | H7: 0 | I7: 1 | J7: 1300
A8: Madrid | B8: Wharehouse 3 | C8: Nectar | D8: 0.5 | E8: 22 | F8: 1 | G8: 0.05 | H8: 3 | I8: 1 | J8: 900
A9: Madrid | B9: Wharehouse 3 | C9: Cordial | D9: 0.5 | E9: 15 | F9: 0 | G9: 0.2 | H9: 0 | I9: 1 | J9: 1500
A10: Milan | B10: Wharehouse 4 | C10: Nectar | D10: 0 | E10: 22 | F10: 0 | G10: 0.2 | H10: 0 | I10: 1 | J10: 900
A11: Milan | B11: Wharehouse 4 | C11: Cordial | D11: 0 | E11: 15 | F11: 0 | G11: 0.2 | H11: 0 | I11: 1 | J11: 1500
A12: Rome | B12: Wharehouse 5 | C12: Nectar | D12: 0.15 | E12: 22 | F12: -1 | G12: 0.5 | H12: 0 | I12: 2 | J12: 1000
A13: Rome | B13: Wharehouse 5 | C13: Cordial | D13: 0.15 | E13: 15 | F13: 2 | G13: 0.5 | H13: 0 | I13: 2 | J13: 1600
A14: Bucharest | B14: Wharehouse 6 | C14: Nectar | D14: 0.1 | E14: 22 | F14: -1 | G14: 0.5 | H14: 0 | I14: 2 | J14: 600
A15: Bucharest | B15: Wharehouse 6 | C15: Cordial | D15: 0.1 | E15: 15 | F15: 2 | G15: 0.5 | H15: 0 | I15: 2 | J15: 1200
A16: Budapest | B16: Wharehouse 7 | C16: Nectar | D16: 0.3 | E16: 22 | F16: 1 | G16: 0.5 | H16: 3 | I16: 2 | J16: 1100
... A23: Berlin | B23: Wharehouse 10 | C23: Cordial | D23: -0.5 | E23: 15 | F23: -1 | G23: 0.05 | H23: 0 | I23: 1 | J23: 1600

Sheet Demand
K1: 1 | L1: 2 | M1: 3 | N1: 4 | O1: 5 | P1: 6 | Q1: 7 | R1: 8 | S1: 9 | T1: 10 | U1: 11 | V1: 12 | W1: 13 | X1: 14 | Y1: 15 | Z1: 16 | AA1: 17 | AB1: 18 | AC1: 19 | AD1: 20 | AE1: 21 | AF1: 22 | AG1: 23 | AH1: 24
D2: Coeff. Dir. | E2: Constante | F2: Fréquence | G2: Amplitude | H2: Décalage | I2: Ecart-type | J2: Prix | K2: -23 | L2: -22 | M2: -21 | N2: -20 | O2: -19 | P2: -18 | Q2: -17 | R2: -16 | S2: -15 | T2: -14 | U2: -13 | V2: -12 | W2: -11 | X2: -10 | Y2: -9 | Z2: -8 | AA2: -7 | AB2: -6 | AC2: -5 | AD2: -4 | AE2: -3 | AF2: -2 | AG2: -1 | AH2: 0 | AI2: 1 | AJ2: 2 | AK2: 3 | AL2: 4 | AM2: 5 | AN2: 6 | AO2: 7 | AP2: 8 | AQ2: 9 | AR2: 10 | AS2: 11 | AT2: 12 | AU2: 13 | AV2: 14 | AW2: 15 | AX2: 16 | AY2: 17 | AZ2: 18 | BA2: 19 | BB2: 20 | BC2: 21 | BD2: 22 | BE2: 23 | BF2: 24
D3: a | E3: b | F3: f | G3: k | H3: d | I3: s
A4: Paris | B4: Wharehouse1 | C4: nectar | D4: 0.4 | E4: 21 | F4: 1 | G4: 0.2 | H4: 2 | I4: 1 | J4: 1000 | K4: 10 | L4: 14 | M4: 15 | N4: 15 | O4: 15 | P4: 16 | Q4: 15 | R4: 15 | S4: 14 | T4: 13 | U4: 13 | V4: 13 | W4: 15 | X4: 16 | Y4: 22 | Z4: 20 | AA4: 21 | AB4: 22 | AC4: 19 | AD4: 19 | AE4: 18 | AF4: 17 | AG4: 16 | AH4: 19 | AI4: 20 | AJ4: 22 | AK4: 24 | AL4: 26 | AM4: 28 | AN4: 28 | AO4: 25 | AP4: 25 | AQ4: 22 | AR4: 19 | AS4: 21 | AT4: 20 | AU4: 24 | AV4: 26 | AW4: 28 | AX4: 31 | AY4: 34 | AZ4: 33 | BA4: 32 | BB4: 30 | BC4: 27 | BD4: 24 | BE4: 23 | BF4: 24
A5: Paris | B5: Wharehouse1 | C5: cordial | D5: 0.4 | E5: 16 | F5: 1 | G5: 0.2 | H5: 2 | I5: 1 | J5: 1600 | K5: 5 | L5: 6 | M5: 8 | N5: 10 | O5: 11 | P5: 11 | Q5: 11 | R5: 11 | S5: 10 | T5: 9 | U5: 8 | V5: 8 | W5: 12 | X5: 13 | Y5: 15 | Z5: 15 | AA5: 15 | AB5: 15 | AC5: 15 | AD5: 15 | AE5: 12 | AF5: 13 | AG5: 13 | AH5: 13 | AI5: 15 | AJ5: 17 | AK5: 20 | AL5: 21 | AM5: 20 | AN5: 23 | AO5: 22 | AP5: 18 | AQ5: 18 | AR5: 17 | AS5: 16 | AT5: 17 | AU5: 19 | AV5: 20 | AW5: 25 | AX5: 25 | AY5: 29 | AZ5: 26 | BA5: 25 | BB5: 24 | BC5: 22 | BD5: 21 | BE5: 19 | BF5: 20
A6: Rauma | B6: Wharehouse2 | C6: nectar | D6: 0 | E6: 22 | F6: 0 | G6: 0.2 | H6: 0 | I6: 1 | J6: 700 | K6: 22 | L6: 20 | M6: 24 | N6: 21 | O6: 23 | P6: 21 | Q6: 22 | R6: 21 | S6: 22 | T6: 22 | U6: 23 | V6: 23 | W6: 21 | X6: 22 | Y6: 22 | Z6: 22 | AA6: 23 | AB6: 21 | AC6: 21 | AD6: 21 | AE6: 23 | AF6: 22 | AG6: 24 | AH6: 21 | AI6: 20 | AJ6: 22 | AK6: 20 | AL6: 21 | AM6: 22 | AN6: 21 | AO6: 22 | AP6: 22 | AQ6: 24 | AR6: 22 | AS6: 23 | AT6: 23 | AU6: 23 | AV6: 22 | AW6: 23 | AX6: 22 | AY6: 24 | AZ6: 22 | BA6: 21 | BB6: 21 | BC6: 20 | BD6: 23 | BE6: 21 | BF6: 23
A7: Rauma | B7: Wharehouse2 | C7: cordial | D7: 0 | E7: 15 | F7: 0 | G7: 0.2 | H7: 0 | I7: 1 | J7: 1300 | K7: 15 | L7: 14 | M7: 15 | N7: 15 | O7: 14 | P7: 15 | Q7: 15 | R7: 13 | S7: 14 | T7: 14 | U7: 15 | V7: 15 | W7: 15 | X7: 14 | Y7: 14 | Z7: 17 | AA7: 13 | AB7: 14 | AC7: 14 | AD7: 17 | AE7: 15 | AF7: 16 | AG7: 14 | AH7: 13 | AI7: 14 | AJ7: 17 | AK7: 16 | AL7: 15 | AM7: 14 | AN7: 15 | AO7: 15 | AP7: 15 | AQ7: 16 | AR7: 16 | AS7: 15 | AT7: 14 | AU7: 15 | AV7: 16 | AW7: 15 | AX7: 15 | AY7: 17 | AZ7: 15 | BA7: 16 | BB7: 16 | BC7: 14 | BD7: 15 | BE7: 16 | BF7: 13
A8: Madrid | B8: Wharehouse3 | C8: nectar | D8: 0 | E8: 22 | F8: -1 | G8: 0.2 | H8: 3 | I8: 1 | J8: 900 | K8: 27 | L8: 24 | M8: 22 | N8: 21 | O8: 19 | P8: 19 | Q8: 19 | R8: 19 | S8: 21 | T8: 24 | U8: 26 | V8: 26 | W8: 26 | X8: 25 | Y8: 24 | Z8: 22 | AA8: 17 | AB8: 16 | AC8: 20 | AD8: 18 | AE8: 22 | AF8: 25 | AG8: 25 | AH8: 25 | AI8: 24 | AJ8: 24 | AK8: 21 | AL8: 22 | AM8: 17 | AN8: 16 | AO8: 19 | AP8: 20 | AQ8: 21 | AR8: 24 | AS8: 25 | AT8: 27 | AU8: 25 | AV8: 25 | AW8: 21 | AX8: 21 | AY8: 19 | AZ8: 18 | BA8: 19 | BB8: 20 | BC8: 23 | BD8: 23 | BE8: 26 | BF8: 25
A9: Madrid | B9: Wharehouse3 | C9: cordial | D9: 0 | E9: 15 | F9: -1 | G9: 0.2 | H9: 0 | I9: 1 | J9: 1500 | K9: 13 | L9: 14 | M9: 14 | N9: 14 | O9: 13 | P9: 14 | Q9: 17 | R9: 16 | S9: 19 | T9: 17 | U9: 17 | V9: 15 | W9: 13 | X9: 11 | Y9: 12 | Z9: 12 | AA9: 14 | AB9: 14 | AC9: 16 | AD9: 17 | AE9: 20 | AF9: 16 | AG9: 17 | AH9: 17 | AI9: 14 | AJ9: 13 | AK9: 12 | AL9: 11 | AM9: 14 | AN9: 14 | AO9: 17 | AP9: 17 | AQ9: 15 | AR9: 18 | AS9: 18 | AT9: 15 | AU9: 13 | AV9: 12 | AW9: 12 | AX9: 13 | AY9: 14 | AZ9: 16 | BA9: 18 | BB9: 16 | BC9: 17 | BD9: 19 | BE9: 16 | BF9: 14
A10: Milan | B10: Wharehouse4 | C10: nectar | D10: 0.4 | E10: 22 | F10: -0.5 | G10: 0.2 | H10: 0 | I10: 1 | J10: 900 | K10: 13 | L10: 11 | M10: 13 | N10: 10 | O10: 12 | P10: 13 | Q10: 13 | R10: 12 | S10: 14 | T10: 15 | U10: 17 | V10: 16 | W10: 19 | X10: 18 | Y10: 21 | Z10: 22 | AA10: 23 | AB10: 25 | AC10: 25 | AD10: 25 | AE10: 24 | AF10: 23 | AG10: 23 | AH10: 22 | AI10: 22 | AJ10: 22 | AK10: 22 | AL10: 19 | AM10: 20 | AN10: 18 | AO10: 20 | AP10: 20 | AQ10: 23 | AR10: 24 | AS10: 26 | AT10: 27 | AU10: 30 | AV10: 31 | AW10: 33 | AX10: 33 | AY10: 35 | AZ10: 34 | BA10: 36 | BB10: 36 | BC10: 34 | BD10: 34 | BE10: 32 | BF10: 32
A11: Milan | B11: Wharehouse4 | C11: cordial | D11: 0.4 | E11: 15 | F11: -0.5 | G11: 0.2 | H11: 0 | I11: 1 | J11: 1500 | K11: 7 | L11: 4 | M11: 6 | N11: 6 | O11: 5 | P11: 6 | Q11: 6 | R11: 8 | S11: 10 | T11: 10 | U11: 9 | V11: 9 | W11: 12 | X11: 14 | Y11: 15 | Z11: 15 | AA11: 14 | AB11: 16 | AC11: 15 | AD11: 15 | AE11: 16 | AF11: 15 | AG11: 15 | AH11: 15 | AI11: 15 | AJ11: 14 | AK11: 15 | AL11: 13 | AM11: 14 | AN11: 15 | AO11: 15 | AP11: 15 | AQ11: 16 | AR11: 16 | AS11: 17 | AT11: 19 | AU11: 20 | AV11: 24 | AW11: 26 | AX11: 26 | AY11: 27 | AZ11: 27 | BA11: 27 | BB11: 27 | BC11: 27 | BD11: 26 | BE11: 25 | BF11: 25
A12: Rome | B12: Wharehouse5 | C12: nectar | D12: 0.4 | E12: 22 | F12: 1 | G12: 0.2 | H12: 0 | I12: 2 | J12: 1000 | K12: 14 | L12: 17 | M12: 14 | N12: 20 | O12: 16 | P12: 16 | Q12: 11 | R12: 13 | S12: 15 | T12: 11 | U12: 16 | V12: 16 | W12: 22 | X12: 20 | Y12: 27 | Z12: 23 | AA12: 26 | AB12: 19 | AC12: 18 | AD12: 17 | AE12: 20 | AF12: 16 | AG12: 18 | AH12: 21 | AI12: 29 | AJ12: 26 | AK12: 31 | AL12: 25 | AM12: 24 | AN12: 25 | AO12: 25 | AP12: 19 | AQ12: 20 | AR12: 21 | AS12: 24 | AT12: 25 | AU12: 30 | AV12: 34 | AW12: 32 | AX12: 34 | AY12: 29 | AZ12: 29 | BA12: 27 | BB12: 28 | BC12: 23 | BD12: 22 | BE12: 26 | BF12: 30
A13: Rome | B13: Wharehouse5 | C13: cordial | D13: 0.4 | E13: 15 | F13: 1 | G13: 0.2 | H13: 0 | I13: 2 | J13: 1600 | K13: 10 | L13: 8 | M13: 7 | N13: 8 | O13: 10 | P13: 7 | Q13: 5 | R13: 6 | S13: 9 | T13: 8 | U13: 9 | V13: 10 | W13: 10 | X13: 14 | Y13: 13 | Z13: 15 | AA13: 17 | AB13: 10 | AC13: 10 | AD13: 11 | AE13: 7 | AF13: 12 | AG13: 15 | AH13: 16 | AI13: 19 | AJ13: 17 | AK13: 21 | AL13: 19 | AM13: 16 | AN13: 15 | AO13: 13 | AP13: 16 | AQ13: 17 | AR13: 19 | AS13: 20 | AT13: 16 | AU13: 22 | AV13: 21 | AW13: 23 | AX13: 25 | AY13: 23 | AZ13: 23 | BA13: 21 | BB13: 17 | BC13: 17 | BD13: 23 | BE13: 21 | BF13: 27
A14: Bucharest | B14: Wharehouse6 | C14: nectar | D14: -0.5 | E14: 22 | F14: -1 | G14: 0.2 | H14: 0 | I14: 2 | J14: 600 | K14: 33 | L14: 28 | M14: 24 | N14: 24 | O14: 29 | P14: 34 | Q14: 34 | R14: 38 | S14: 36 | T14: 30 | U14: 32 | V14: 26 | W14: 25 | X14: 18 | Y14: 21 | Z14: 20 | AA14: 21 | AB14: 21 | AC14: 29 | AD14: 28 | AE14: 25 | AF14: 26 | AG14: 26 | AH14: 21 | AI14: 16 | AJ14: 18 | AK14: 16 | AL14: 17 | AM14: 15 | AN14: 21 | AO14: 20 | AP14: 21 | AQ14: 24 | AR14: 19 | AS14: 20 | AT14: 15 | AU14: 12 | AV14: 14 | AW14: 15 | AX14: 9 | AY14: 13 | AZ14: 14 | BA14: 12 | BB14: 10 | BC14: 17 | BD14: 12 | BE14: 11 | BF14: 14
A15: Bucharest | B15: Wharehouse6 | C15: cordial | D15: -0.1 | E15: 15 | F15: -1 | G15: 0.2 | H15: 0 | I15: 2 | J15: 1200 | K15: 13 | L15: 10 | M15: 14 | N15: 18 | O15: 14 | P15: 17 | Q15: 20 | R15: 20 | S15: 19 | T15: 19 | U15: 17 | V15: 15 | W15: 13 | X15: 14 | Y15: 14 | Z15: 11 | AA15: 15 | AB15: 12 | AC15: 15 | AD15: 15 | AE15: 22 | AF15: 19 | AG15: 16 | AH15: 18 | AI15: 14 | AJ15: 14 | AK15: 13 | AL15: 14 | AM15: 12 | AN15: 15 | AO15: 18 | AP15: 17 | AQ15: 16 | AR15: 18 | AS15: 13 | AT15: 12 | AU15: 12 | AV15: 10 | AW15: 10 | AX15: 9 | AY15: 13 | AZ15: 13 | BA15: 14 | BB15: 17 | BC15: 19 | BD15: 16 | BE15: 14 | BF15: 11
... A23: Berlin | B23: Wharehouse10 | C23: cordial | D23: 0 | E23: 15 | F23: 1 | G23: 0.1 | H23: 0 | I23: 1 | J23: 1600 | K23: 16 | L23: 15 | M23: 18 | N23: 16 | O23: 15 | P23: 14 | Q23: 15 | R23: 13 | S23: 13 | T23: 14 | U23: 17 | V23: 15 | W23: 16 | X23: 17 | Y23: 15 | Z23: 17 | AA23: 18 | AB23: 15 | AC23: 14 | AD23: 14 | AE23: 12 | AF23: 14 | AG23: 15 | AH23: 14 | AI23: 18 | AJ23: 15 | AK23: 16 | AL23: 15 | AM23: 15 | AN23: 16 | AO23: 14 | AP23: 13 | AQ23: 14 | AR23: 12 | AS23: 16 | AT23: 15 | AU23: 17 | AV23: 16 | AW23: 15 | AX23: 15 | AY23: 14 | AZ23: 16 | BA23: 15 | BB23: 13 | BC23: 14 | BD23: 12 | BE23: 15 | BF23: 15
J24: Total nectar | K24: =SUM(K4,K6,K8,K10,K12,K14,K16,K18,K20,K22) -> 195 | L24: =SUM(L4,L6,L8,L10,L12,L14,L16,L18,L20,L22) -> 195 | M24: =SUM(M4,M6,M8,M10,M12,M14,M16,M18,M20,M22) -> 189 | N24: =SUM(N4,N6,N8,N10,N12,N14,N16,N18,N20,N22) -> 193 | O24: =SUM(O4,O6,O8,O10,O12,O14,O16,O18,O20,O22) -> 200 | P24: =SUM(P4,P6,P8,P10,P12,P14,P16,P18,P20,P22) -> 210 | Q24: =SUM(Q4,Q6,Q8,Q10,Q12,Q14,Q16,Q18,Q20,Q22) -> 205 | R24: =SUM(R4,R6,R8,R10,R12,R14,R16,R18,R20,R22) -> 205 | ... BF24: =SUM(BF4,BF6,BF8,BF10,BF12,BF14,BF16,BF18,BF20,BF22) -> 230
J25: Total cordial | K25: =SUM(K5,K7,K9,K11,K13,K15,K17,K19,K21,K23) -> 130 | L25: =SUM(L5,L7,L9,L11,L13,L15,L17,L19,L21,L23) -> 118 | M25: =SUM(M5,M7,M9,M11,M13,M15,M17,M19,M21,M23) -> 131 | N25: =SUM(N5,N7,N9,N11,N13,N15,N17,N19,N21,N23) -> 132 | O25: =SUM(O5,O7,O9,O11,O13,O15,O17,O19,O21,O23) -> 122 | P25: =SUM(P5,P7,P9,P11,P13,P15,P17,P19,P21,P23) -> 119 | Q25: =SUM(Q5,Q7,Q9,Q11,Q13,Q15,Q17,Q19,Q21,Q23) -> 126 | R25: =SUM(R5,R7,R9,R11,R13,R15,R17,R19,R21,R23) -> 126 | ... BF25: =SUM(BF5,BF7,BF9,BF11,BF13,BF15,BF17,BF19,BF21,BF23) -> 173
A45: Prix de vente
B46: janv | C46: févr | D46: mars | E46: avr | F46: mai | G46: juin | H46: juil | I46: août | J46: sept | K46: oct | L46: nov | M46: déc
A47: 2022
A48: 2023
A50: Paris | B50: nectar | C50: 10 | D50: 14 | E50: 15 | F50: 15 | G50: 15 | H50: 16 | I50: 15 | J50: 15 | K50: 14 | L50: 13 | M50: 13 | N50: 13
C51: 15 | D51: 16 | E51: 22 | F51: 20 | G51: 21 | H51: 22 | I51: 19 | J51: 19 | K51: 18 | L51: 17 | M51: 16 | N51: 19
A52: Paris | B52: cordial | C52: 5 | D52: 6 | E52: 8 | F52: 10 | G52: 11 | H52: 11 | I52: 11 | J52: 11 | K52: 10 | L52: 9 | M52: 8 | N52: 8
C53: 12 | D53: 13 | E53: 15 | F53: 15 | G53: 15 | H53: 15 | I53: 15 | J53: 15 | K53: 12 | L53: 13 | M53: 13 | N53: 13
A54: Rauma | B54: nectar | C54: 22 | D54: 20 | E54: 24 | F54: 21 | G54: 23 | H54: 21 | I54: 22 | J54: 21 | K54: 22 | L54: 22 | M54: 23 | N54: 23
C55: 21 | D55: 22 | E55: 22 | F55: 22 | G55: 23 | H55: 21 | I55: 21 | J55: 21 | K55: 23 | L55: 22 | M55: 24 | N55: 21
A56: Rauma | B56: cordial | C56: 15 | D56: 14 | E56: 15 | F56: 15 | G56: 14 | H56: 15 | I56: 15 | J56: 13 | K56: 14 | L56: 14 | M56: 15 | N56: 15
C57: 15 | D57: 14 | E57: 14 | F57: 17 | G57: 13 | H57: 14 | I57: 14 | J57: 17 | K57: 15 | L57: 16 | M57: 14 | N57: 13
A58: Madrid | B58: nectar | C58: 27 | D58: 24 | E58: 22 | F58: 21 | G58: 19 | H58: 19 | I58: 19 | J58: 19 | K58: 21 | L58: 24 | M58: 26 | N58: 26
C59: 26 | D59: 25 | E59: 24 | F59: 22 | G59: 17 | H59: 16 | I59: 20 | J59: 18 | K59: 22 | L59: 25 | M59: 25 | N59: 25
A60: Madrid | B60: cordial | C60: 13 | D60: 14 | E60: 14 | F60: 14 | G60: 13 | H60: 14 | I60: 17 | J60: 16 | K60: 19 | L60: 17 | M60: 17 | N60: 15
C61: 13 | D61: 11 | E61: 12 | F61: 12 | G61: 14 | H61: 14 | I61: 16 | J61: 17 | K61: 20 | L61: 16 | M61: 17 | N61: 17
A62: Milan | B62: nectar | C62: 13 | D62: 11 | E62: 13 | F62: 10 | G62: 12 | H62: 13 | I62: 13 | J62: 12 | K62: 14 | L62: 15 | M62: 17 | N62: 16
C63: 19 | D63: 18 | E63: 21 | F63: 22 | G63: 23 | H63: 25 | I63: 25 | J63: 25 | K63: 24 | L63: 23 | M63: 23 | N63: 22
A64: Milan | B64: cordial | C64: 7 | D64: 4 | E64: 6 | F64: 6 | G64: 5 | H64: 6 | I64: 6 | J64: 8 | K64: 10 | L64: 10 | M64: 9 | N64: 9
C65: 12 | D65: 14 | E65: 15 | F65: 15 | G65: 14 | H65: 16 | I65: 15 | J65: 15 | K65: 16 | L65: 15 | M65: 15 | N65: 15
A66: Rome | B66: nectar | C66: 14 | D66: 17 | E66: 14 | F66: 20 | G66: 16 | H66: 16 | I66: 11 | J66: 13 | K66: 15 | L66: 11 | M66: 16 | N66: 16
C67: 22 | D67: 20 | E67: 27 | F67: 23 | G67: 26 | H67: 19 | I67: 18 | J67: 17 | K67: 20 | L67: 16 | M67: 18 | N67: 21
A68: Rome | B68: cordial | C68: 10 | D68: 8 | E68: 7 | F68: 8 | G68: 10 | H68: 7 | I68: 5 | J68: 6 | K68: 9 | L68: 8 | M68: 9 | N68: 10
C69: 10 | D69: 14 | E69: 13 | F69: 15 | G69: 17 | H69: 10 | I69: 10 | J69: 11 | K69: 7 | L69: 12 | M69: 15 | N69: 16
A70: Bucharest | B70: nectar | C70: 33 | D70: 28 | E70: 24 | F70: 24 | G70: 29 | H70: 34 | I70: 34 | J70: 38 | K70: 36 | L70: 30 | M70: 32 | N70: 26
C71: 25 | D71: 18 | E71: 21 | F71: 20 | G71: 21 | H71: 21 | I71: 29 | J71: 28 | K71: 25 | L71: 26 | M71: 26 | N71: 21
A72: Bucharest | B72: cordial | C72: 13 | D72: 10 | E72: 14 | F72: 18 | G72: 14 | H72: 17 | I72: 20 | J72: 20 | K72: 19 | L72: 19 | M72: 17 | N72: 15
C73: 13 | D73: 14 | E73: 14 | F73: 11 | G73: 15 | H73: 12 | I73: 15 | J73: 15 | K73: 22 | L73: 19 | M73: 16 | N73: 18
A74: Budapest | B74: nectar | C74: 19 | D74: 25 | E74: 25 | F74: 29 | G74: 31 | H74: 32 | I74: 32 | J74: 28 | K74: 23 | L74: 21 | M74: 17 | N74: 22
C75: 21 | D75: 23 | E75: 26 | F75: 25 | G75: 24 | H75: 27 | I75: 29 | J75: 27 | K75: 22 | L75: 25 | M75: 18 | N75: 20
A76: Budapest | B76: cordial | C76: 21 | D76: 20 | E76: 24 | F76: 23 | G76: 21 | H76: 18 | I76: 17 | J76: 16 | K76: 15 | L76: 12 | M76: 14 | N76: 17
C77: 19 | D77: 20 | E77: 22 | F77: 19 | G77: 19 | H77: 19 | I77: 19 | J77: 14 | K77: 13 | L77: 10 | M77: 14 | N77: 13
A78: Kemijarvi | B78: nectar | C78: 0 | D78: 0 | E78: 0 | F78: 0 | G78: 0 | H78: 1 | I78: 2 | J78: 1 | K78: 2 | L78: 2 | M78: 5 | N78: 7
C79: 4 | D79: 6 | E79: 9 | F79: 10 | G79: 9 | H79: 12 | I79: 10 | J79: 11 | K79: 14 | L79: 12 | M79: 13 | N79: 14
A80: Kemijarvi | B80: cordial | C80: 0 | D80: 0 | E80: 0 | F80: 0 | G80: 0 | H80: 1 | I80: 1 | J80: 2 | K80: 3 | L80: 3 | M80: 4 | N80: 6
C81: 6 | D81: 5 | E81: 6 | F81: 9 | G81: 11 | H81: 9 | I81: 11 | J81: 13 | K81: 13 | L81: 14 | M81: 14 | N81: 15
A82: Warsaw | B82: nectar | C82: 33 | D82: 31 | E82: 28 | F82: 29 | G82: 31 | H82: 35 | I82: 37 | J82: 39 | K82: 40 | L82: 36 | M82: 34 | N82: 30
C83: 27 | D83: 25 | E83: 24 | F83: 24 | G83: 25 | H83: 27 | I83: 28 | J83: 29 | K83: 29 | L83: 25 | M83: 24 | N83: 22
A84: Warsaw | B84: cordial | C84: 30 | D84: 27 | E84: 25 | F84: 22 | G84: 19 | H84: 16 | I84: 19 | J84: 21 | K84: 22 | L84: 25 | M84: 25 | N84: 25
C85: 23 | D85: 22 | E85: 19 | F85: 16 | G85: 14 | H85: 14 | I85: 14 | J85: 15 | K85: 18 | L85: 17 | M85: 18 | N85: 18
A86: Berlin | B86: nectar | C86: 24 | D86: 25 | E86: 24 | F86: 24 | G86: 24 | H86: 23 | I86: 20 | J86: 19 | K86: 19 | L86: 22 | M86: 20 | N86: 22
C87: 22 | D87: 23 | E87: 24 | F87: 24 | G87: 23 | H87: 22 | I87: 21 | J87: 22 | K87: 18 | L87: 19 | M87: 21 | N87: 22
A88: Berlin | B88: cordial | C88: 16 | D88: 15 | E88: 18 | F88: 16 | G88: 15 | H88: 14 | I88: 15 | J88: 13 | K88: 13 | L88: 14 | M88: 17 | N88: 15
C89: 16 | D89: 17 | E89: 15 | F89: 17 | G89: 18 | H89: 15 | I89: 14 | J89: 14 | K89: 12 | L89: 14 | M89: 15 | N89: 14

Sheet Distances
C3: distance (km) | E3: CD1 | F3: CD2 | G3: Usine1 | H3: Usine2 | I3: Usine3
C5: CD1 | F5: 700 | G5: 400 | H5: 300 | I5: 800
C6: CD2 | E6: 700 | G6: 600 | H6: 500 | I6: 900
C7: Usine1 | E7: 400 | F7: 600 | H7: 200 | I7: 300
C8: Usine2 | E8: 300 | F8: 500 | G8: 200 | I8: 100
C9: Usine3 | E9: 800 | F9: 900 | G9: 300 | H9: 100
E12: 1 | F12: 2 | G12: 3 | H12: 4 | I12: 5 | J12: 6 | K12: 7 | L12: 8 | M12: 9 | N12: 10 | O12: 11 | P12: 12 | Q12: 13 | R12: 14 | S12: 15
C13: distance (km) | E13: Arnhem factory | F13: Vesoul factory | G13: Paris | H13: Rauma | I13: Madrid | J13: Milan | K13: Rome | L13: Bucharest | M13: Budapest | N13: Kemijarvi | O13: Warsaw | P13: Berlin | R13: Gauche | S13: Haut
B15: 1 | C15: Arnhem factory | F15: 637 | G15: 509 | H15: 1771 | I15: 1764 | J15: 979 | K15: 1577 | L15: 2197 | M15: 1301 | N15: 2597 | O15: 1134 | P15: 597 | R15: 192 | S15: 262.5
B16: 2 | C16: Vesoul factory | E16: 637 | G16: 360 | H16: 2282 | I16: 1527 | J16: 484 | K16: 1081 | L16: 2120 | M16: 1224 | N16: 3106 | O16: 1504 | P16: 967 | R16: 186.75 | S16: 346.5
B17: 3 | C17: Paris | E17: 509 | F17: 360 | H17: 2266 | I17: 1274 | J17: 844 | K17: 1423 | L17: 2284 | M17: 1495 | N17: 3092 | O17: 1603 | P17: 1408 | R17: 318.75 | S17: 346.5
B18: 4 | C18: Rauma | E18: 1771 | F18: 2282 | G18: 2266 | I18: 3528 | J18: 2481 | K18: 3115 | L18: 3020 | M18: 2193 | N18: 832 | O18: 1308 | P18: 1483 | R18: 471.75 | S18: 165
B19: 5 | C19: Madrid | E19: 1764 | F19: 1527 | G19: 1274 | H19: 3528 | J19: 1564 | K19: 1967 | L19: 3187 | M19: 2541 | N19: 4357 | O19: 2879 | P19: 2324 | R19: 251.25 | S19: 419.25
B20: 6 | C20: Milan | E20: 979 | F20: 484 | G20: 844 | H20: 2481 | I20: 1564 | K20: 584 | L20: 1628 | M20: 982 | N20: 3305 | O20: 1564 | P20: 1028 | R20: 400 | S20: 370
B21: 7 | C21: Rome | E21: 1577 | F21: 1081 | G21: 1423 | H21: 3115 | I21: 1967 | J21: 584 | L21: 1895 | M21: 1249 | N21: 3772 | O21: 1815 | P21: 1523 | R21: 318.75 | S21: 263.25
B22: 8 | C22: Bucharest | E22: 2197 | F22: 2120 | G22: 2284 | H22: 3020 | I22: 3187 | J22: 1628 | K22: 1895 | M22: 796 | N22: 3318 | O22: 1189 | P22: 1660 | R22: 29.25 | S22: 399.75
B23: 9 | C23: Budapest | E23: 1301 | F23: 1224 | G23: 1495 | H23: 2193 | I23: 2541 | J23: 982 | K23: 1249 | L23: 796 | N23: 2813 | O23: 696 | P23: 871 | R23: 80.25 | S23: 418.5
B24: 10 | C24: Kemijarvi | E24: 2597 | F24: 3106 | G24: 3092 | H24: 832 | I24: 4357 | J24: 3305 | K24: 3772 | L24: 3318 | M24: 2813 | O24: 1952 | P24: 2309 | R24: 350 | S24: 470
B25: 11 | C25: Warsaw | E25: 1134 | F25: 1504 | G25: 1603 | H25: 1308 | I25: 2879 | J25: 1564 | K25: 1815 | L25: 1189 | M25: 696 | N25: 1952 | P25: 561 | R25: 237 | S25: 263.25
B26: 12 | C26: Berlin | E26: 597 | F26: 967 | G26: 1408 | H26: 1483 | I26: 2324 | J26: 1028 | K26: 1523 | L26: 1660 | M26: 871 | N26: 2309 | O26: 561 | R26: 156 | S26: 326.25

Sheet Cout_revient
D12: Arnhem factory | H12: Vesoul factory
D13: Packaging
D14: Quantity | E14: Value per unit | F14: Total | H14: Quantity | I14: Value per unit | J14: Total
B15: nectar (pallet) | D15: 30 | E15: =F15/D15 -> 600 | F15: =SUM(F16:F22) -> 18000
B16: cordial (pallet) | H16: 20 | I16: =J16/H16 -> 950 | J16: =SUM(J17:J22) -> 19000
B17: nectar (vat) | D17: 1 | E17: =E25 -> 16500 | F17: =D17*E17 -> 16500
B18: cordial (vat) | H18: 1 | I18: =I26 -> 15500 | J18: =H18*I18 -> 15500
B19: pack (batch) | D19: 1 | E19: 1000 | F19: =D19*E19 -> 1000
B20: bottle (batch) | H20: 1 | I20: 3000 | J20: =H20*I20 -> 3000
B21: production cost (wages excluded) | D21: 1 | E21: 100 | F21: =D21*E21 -> 100 | H21: 1 | I21: 100 | J21: =H21*I21 -> 100
B22: Labour | D22: 20 | E22: 20 | F22: =D22*E22 -> 400 | H22: 20 | I22: 20 | J22: =H22*I22 -> 400
D23: Production
D24: Quantity | E24: Value per unit | F24: Total | H24: Quantity | I24: Value per unit | J24: Total
B25: nectar (vat) | D25: 1 | E25: =F25/D25 -> 16500 | F25: =SUM(F26:F31) -> 16500
B26: cordial (vat) | H26: 1 | I26: =J26/H26 -> 15500 | J26: =SUM(J27:J31) -> 15500
B27: Puree after transport (bin) | D27: 5 | E27: =E35 -> 2200 | F27: =D27*E27 -> 11000
B28: Concentrate after transport (bin) | D28: 1 | E28: =I36 -> 3200 | F28: =D28*E28 -> 3200 | H28: 4 | I28: =I36 -> 3200 | J28: =H28*I28 -> 12800
B29: sugar (tonne) | H29: 1 | I29: 400 | J29: =H29*I29 -> 400
B30: production cost (wages excluded) | D30: 1 | E30: 300 | F30: =D30*E30 -> 300 | H30: 1 | I30: 300 | J30: =H30*I30 -> 300
B31: Labour | D31: 100 | E31: 20 | F31: =D31*E31 -> 2000 | H31: 100 | I31: 20 | J31: =H31*I31 -> 2000
D33: International transport
D34: Quantity | E34: Value per unit | F34: Total | H34: Quantity | I34: Value per unit | J34: Total
B35: Puree after transport (bin) | D35: 1 | E35: =F35/D35 -> 2200 | F35: =SUM(F37:F38) -> 2200
B36: Concentrate after transport (bin) | H36: 1 | I36: =J36/H36 -> 3200 | J36: =SUM(J37:J39) -> 3200
B37: Transport | D37: 1 | E37: 200 | F37: =D37*E37 -> 200 | H37: 1 | I37: 200 | J37: =H37*I37 -> 200
B38: Puree at Auckland (bin) | D38: 1 | E38: 2000 | F38: =D38*E38 -> 2000
B39: Concentrate at Auckland (bin) | H39: 1 | I39: 3000 | J39: =H39*I39 -> 3000
D41: Auckland factory
D42: Quantity | E42: Value per unit | F42: Total
B43: Produced puree (4 bins) + produced concentrate (1 bin) | D43: 1 | E43: =F43/D43 -> 11000 | F43: =SUM(F44:F45) -> 11000
B44: production cost (wages excluded) | D44: 1 | E44: 10000 | F44: =D44*E44 -> 10000
B45: Labour | D45: 50 | E45: 20 | F45: =D45*E45 -> 1000

Sheet Nomenclature
F9: Nectar conditionné 30 palettes | L9: Sirop conditionné 20 palettes
E10: x 1 vat | F10: 1 mois | H10: x 1 batch | K10: x 1 vat | L10: 1 mois | N10: x 1 batch
E11: Nectar 1 cuve | H11: Pack disponible | K11: Sirop 1 cuve | N11: Flacon disponible
D12: x 5 bins | E12: 1 mois | F12: x 1 bin | H12: 1 mois | J12: x 1 tonne | K12: 1 mois | L12: x 4 bins | N12: 1 mois
D13: Purée transportée | F13: Concentré transporté | J13: Sucre disponible | L13: Concentré transporté
D14: 2 mois | F14: 2 mois | J14: 1 mois | L14: 2 mois
D15: Purée | F15: Concentré | L15: Concentré
D16: 1 mois | F16: 1 mois | L16: 1 mois
D17: Kiwis | F17: Kiwis | H17: Pack | J17: Sucre | L17: Kiwis | N17: Flacon
F20: Nectar conditionné 30 palettes | L20: Sirop conditionné 20 palettes
E21: x cuve | F21: mois | H21: x lot | K21: x cuve | L21: mois | N21: x lot
E22: Nectar 1 cuve | H22: Pack disponible | K22: Sirop 1 cuve | N22: Flacon disponible
D23: x bins | E23: mois | F23: x bin | H23: mois | J23: x tonne | K23: mois | L23: x bins | N23: mois
D24: Purée transportée | F24: Concentré transporté | J24: Sucre disponible | L24: Concentré transporté
D25: mois | F25: mois | J25: mois | L25: mois
D26: Purée | F26: Concentré | L26: Concentré
D27: mois | F27: mois | L27: mois
D28: Kiwis | F28: Kiwis | H28: Pack | J28: Sucre | L28: Kiwis | N28: Flacon

Sheet Process

Sheet Translation
A1: Français | B1: Anglais
A3: Compte | B3: Account
A4: résultat cumulé | B4: cumulative result
A5: cordial nectar | B5: cordial turnover
D6: Penser à à préciser "Classeur" dans le menu édition / remplacer
A7: Usine d'Auckland | B7: Auckland factory
A8: concentré (bin) | B8: concentrate (bin)
A9: purée (bin) | B9: puree (bin)
A10: personnel | B10: staff
A11: temps disponible | B11: Time not used
A12: vente de purée | B12: Puree sale
A13: vente de concentré | B13: Concentrate sale
A14: coût de production (hors salaire) | B14: production cost (wages excluded)
A15: coût stockage concentré | B15: concentrate storage cost
A16: coût stockage purée | B16: puree storage cost
A17: coût d'embauche | B17: Hiring cost
A18: coût de licenciement | B18: Laying-off cost
... A269: valeur unitaire | B269: Value per unit
A270: /Fin/

Sheet Order
G2: IUT Vesoul Transport - Logistique
S3: non
L4: Software
F7: Game of International Supply chain for Efficient Logistics
J11: WIKI Company
F19: Period | H19: 2 | L19: Team03
C22: 1 | E22: Distribution
A24: 1 | C24: =VLOOKUP(FALSE,C28:$AA$52,COLUMN($AA$24)-COLUMN(B24),FALSE) -> #N/A | D24: =IF(ISNA(C24),"","The line " &C24&" is not completed") | K24: =VLOOKUP(FALSE,K28:$AA$52,COLUMN($AA$24)-COLUMN(J24),FALSE) -> #N/A | L24: =IF(ISNA(K24),"","The line " &K24&" is not completed") | S24: =VLOOKUP(FALSE,S28:$AA$52,COLUMN($AA$24)-COLUMN(R24),FALSE) -> #N/A | T24: =IF(ISNA(S24),"","The line " &S24&" is not completed")
D26: Lorry | E26: Town | F26: Loading | H26: Unloading | L26: Lorry | M26: Town | N26: Loading | P26: Unloading | T26: Lorry | U26: Town | V26: Loading | X26: Unloading | AB26: Camions | AC26: Villes | AD26: Rien | AG26: QUESTIONS POSSIBLES : Un fichier nommé ‘… decision.xls’ existe déjà à cet emplacement. Voulez-vous le remplacer ? Répondre OUI Voulez-vous enregistrer les modifications apportées à ‘decision…xls’ ? Répondre ENREGISTRER
F27: Nectar | G27: Cordial | H27: Nectar | I27: Cordial | N27: Nectar | O27: Cordial | P27: Nectar | Q27: Cordial | V27: Nectar | W27: Cordial | X27: Nectar | Y27: Cordial | AD27: <-- choose a lorry first !
C28: =OR(AND(D28<>0,E28<>0,E28<>$AD$27),AND(D28=0,E28=0,F28=0,G28=0,H28=0,I28=0)) -> TRUE | D28: Lorry 1 | E28: Arnhem factory | F28: 66 | K28: =OR(AND(L28<>0,M28<>0,M28<>$AD$27),AND(L28=0,M28=0,N28=0,O28=0,P28=0,Q28=0)) -> TRUE | L28: Lorry 2 | M28: Paris | Q28: 20 | S28: =OR(AND(T28<>0,U28<>0,U28<>$AD$27),AND(T28=0,U28=0,V28=0,W28=0,X28=0,Y28=0)) -> TRUE | T28: Lorry 3 | U28: Paris | V28: 24 | Z28: =IF(AND(T28<>"",U28<>"",U28<>$AD$27),0,1000000000000000) -> 0 | AA28: =ROW(Y28) -> 28 | AB28: Lorry 1 | AC28: =Distances!C15 -> Arnhem factory
C29: =OR(AND(D29<>0,E29<>0,E29<>$AD$27),AND(D29=0,E29=0,F29=0,G29=0,H29=0,I29=0)) -> TRUE | D29: Lorry 2 | E29: Vesoul factory | G29: 48 | K29: =OR(AND(L29<>0,M29<>0,M29<>$AD$27),AND(L29=0,M29=0,N29=0,O29=0,P29=0,Q29=0)) -> TRUE | L29: Lorry 2 | M29: Berlin | Q29: 30 | S29: =OR(AND(T29<>0,U29<>0,U29<>$AD$27),AND(T29=0,U29=0,V29=0,W29=0,X29=0,Y29=0)) -> TRUE | T29: Lorry 3 | U29: Madrid | X29: 24 | Z29: =IF(AND(T29<>"",U29<>"",U29<>$AD$27),0,1000000000000000) -> 0 | AA29: =ROW(Y29) -> 29 | AB29: Lorry 2 | AC29: =Distances!C16 -> Vesoul factory
C30: =OR(AND(D30<>0,E30<>0,E30<>$AD$27),AND(D30=0,E30=0,F30=0,G30=0,H30=0,I30=0)) -> TRUE | D30: Lorry 3 | E30: Paris | K30: =OR(AND(L30<>0,M30<>0,M30<>$AD$27),AND(L30=0,M30=0,N30=0,O30=0,P30=0,Q30=0)) -> TRUE | L30: Lorry 2 | M30: Vesoul factory | O30: 15 | S30: =OR(AND(T30<>0,U30<>0,U30<>$AD$27),AND(T30=0,U30=0,V30=0,W30=0,X30=0,Y30=0)) -> TRUE | T30: Lorry 3 | U30: Paris | V30: 3 | Z30: =IF(AND(T30<>"",U30<>"",U30<>$AD$27),0,1000000000000000) -> 0 | AA30: =ROW(Y30) -> 30 | AB30: Lorry 3 | AC30: =Distances!C17 -> Paris
C31: =OR(AND(D31<>0,E31<>0,E31<>$AD$27),AND(D31=0,E31=0,F31=0,G31=0,H31=0,I31=0)) -> TRUE | D31: Lorry 1 | E31: Paris | H31: 66 | K31: =OR(AND(L31<>0,M31<>0,M31<>$AD$27),AND(L31=0,M31=0,N31=0,O31=0,P31=0,Q31=0)) -> TRUE | L31: Lorry 1 | M31: Warsaw | P31: 19 | S31: =OR(AND(T31<>0,U31<>0,U31<>$AD$27),AND(T31=0,U31=0,V31=0,W31=0,X31=0,Y31=0)) -> TRUE | T31: Lorry 3 | U31: Vesoul factory | W31: 21 | Z31: =IF(AND(T31<>"",U31<>"",U31<>$AD$27),0,1000000000000000) -> 0 | AA31: =ROW(Y31) -> 31 | AC31: =Distances!C18 -> Rauma
C32: =OR(AND(D32<>0,E32<>0,E32<>$AD$27),AND(D32=0,E32=0,F32=0,G32=0,H32=0,I32=0)) -> TRUE | D32: Lorry 1 | E32: Vesoul factory | G32: 50 | K32: =OR(AND(L32<>0,M32<>0,M32<>$AD$27),AND(L32=0,M32=0,N32=0,O32=0,P32=0,Q32=0)) -> TRUE | L32: Lorry 1 | M32: Kemijarvi | P32: 18 | S32: =OR(AND(T32<>0,U32<>0,U32<>$AD$27),AND(T32=0,U32=0,V32=0,W32=0,X32=0,Y32=0)) -> TRUE | T32: Lorry 3 | U32: Madrid | X32: 3 | Y32: 21 | Z32: =IF(AND(T32<>"",U32<>"",U32<>$AD$27),0,1000000000000000) -> 0 | AA32: =ROW(Y32) -> 32 | AC32: =Distances!C19 -> Madrid
C33: =OR(AND(D33<>0,E33<>0,E33<>$AD$27),AND(D33=0,E33=0,F33=0,G33=0,H33=0,I33=0)) -> TRUE | D33: Lorry 1 | E33: Berlin | I33: 15 | K33: =OR(AND(L33<>0,M33<>0,M33<>$AD$27),AND(L33=0,M33=0,N33=0,O33=0,P33=0,Q33=0)) -> TRUE | L33: Lorry 1 | M33: Rauma | P33: 24 | S33: =OR(AND(T33<>0,U33<>0,U33<>$AD$27),AND(T33=0,U33=0,V33=0,W33=0,X33=0,Y33=0)) -> TRUE | T33: Lorry 3 | U33: Paris | Z33: =IF(AND(T33<>"",U33<>"",U33<>$AD$27),0,1000000000000000) -> 0 | AA33: =ROW(Y33) -> 33 | AC33: =Distances!C20 -> Milan
C34: =OR(AND(D34<>0,E34<>0,E34<>$AD$27),AND(D34=0,E34=0,F34=0,G34=0,H34=0,I34=0)) -> TRUE | D34: Lorry 1 | E34: Rauma | I34: 17 | K34: =OR(AND(L34<>0,M34<>0,M34<>$AD$27),AND(L34=0,M34=0,N34=0,O34=0,P34=0,Q34=0)) -> TRUE | L34: Lorry 1 | M34: Berlin | P34: 5 | S34: =OR(AND(T34<>0,U34<>0,U34<>$AD$27),AND(T34=0,U34=0,V34=0,W34=0,X34=0,Y34=0)) -> TRUE | Z34: =IF(AND(T34<>"",U34<>"",U34<>$AD$27),0,1000000000000000) -> 1e+15 | AA34: =ROW(Y34) -> 34 | AC34: =Distances!C21 -> Rome
C35: =OR(AND(D35<>0,E35<>0,E35<>$AD$27),AND(D35=0,E35=0,F35=0,G35=0,H35=0,I35=0)) -> TRUE | D35: Lorry 1 | E35: Kemijarvi | I35: 18 | K35: =OR(AND(L35<>0,M35<>0,M35<>$AD$27),AND(L35=0,M35=0,N35=0,O35=0,P35=0,Q35=0)) -> TRUE | L35: Lorry 1 | M35: Arnhem factory | N35: 66 | S35: =OR(AND(T35<>0,U35<>0,U35<>$AD$27),AND(T35=0,U35=0,V35=0,W35=0,X35=0,Y35=0)) -> TRUE | Z35: =IF(AND(T35<>"",U35<>"",U35<>$AD$27),0,1000000000000000) -> 1e+15 | AA35: =ROW(Y35) -> 35 | AC35: =Distances!C22 -> Bucharest
C36: =OR(AND(D36<>0,E36<>0,E36<>$AD$27),AND(D36=0,E36=0,F36=0,G36=0,H36=0,I36=0)) -> TRUE | D36: Lorry 1 | E36: Arnhem factory | F36: 66 | K36: =OR(AND(L36<>0,M36<>0,M36<>$AD$27),AND(L36=0,M36=0,N36=0,O36=0,P36=0,Q36=0)) -> TRUE | L36: Lorry 3 | M36: Vesoul factory | O36: 4 | S36: =OR(AND(T36<>0,U36<>0,U36<>$AD$27),AND(T36=0,U36=0,V36=0,W36=0,X36=0,Y36=0)) -> TRUE | Z36: =IF(AND(T36<>"",U36<>"",U36<>$AD$27),0,1000000000000000) -> 1e+15 | AA36: =ROW(Y36) -> 36 | AC36: =Distances!C23 -> Budapest
C37: =OR(AND(D37<>0,E37<>0,E37<>$AD$27),AND(D37=0,E37=0,F37=0,G37=0,H37=0,I37=0)) -> TRUE | K37: =OR(AND(L37<>0,M37<>0,M37<>$AD$27),AND(L37=0,M37=0,N37=0,O37=0,P37=0,Q37=0)) -> TRUE | L37: Lorry 3 | M37: Arnhem factory | N37: 20 | S37: =OR(AND(T37<>0,U37<>0,U37<>$AD$27),AND(T37=0,U37=0,V37=0,W37=0,X37=0,Y37=0)) -> TRUE | Z37: =IF(AND(T37<>"",U37<>"",U37<>$AD$27),0,1000000000000000) -> 1e+15 | AA37: =ROW(Y37) -> 37 | AC37: =Distances!C24 -> Kemijarvi
C38: =OR(AND(D38<>0,E38<>0,E38<>$AD$27),AND(D38=0,E38=0,F38=0,G38=0,H38=0,I38=0)) -> TRUE | K38: =OR(AND(L38<>0,M38<>0,M38<>$AD$27),AND(L38=0,M38=0,N38=0,O38=0,P38=0,Q38=0)) -> TRUE | L38: Lorry 3 | M38: Berlin | P38: 20 | Q38: 4 | S38: =OR(AND(T38<>0,U38<>0,U38<>$AD$27),AND(T38=0,U38=0,V38=0,W38=0,X38=0,Y38=0)) -> TRUE | Z38: =IF(AND(T38<>"",U38<>"",U38<>$AD$27),0,1000000000000000) -> 1e+15 | AA38: =ROW(Y38) -> 38 | AC38: =Distances!C25 -> Warsaw
C39: =OR(AND(D39<>0,E39<>0,E39<>$AD$27),AND(D39=0,E39=0,F39=0,G39=0,H39=0,I39=0)) -> TRUE | K39: =OR(AND(L39<>0,M39<>0,M39<>$AD$27),AND(L39=0,M39=0,N39=0,O39=0,P39=0,Q39=0)) -> TRUE | L39: Lorry 3 | M39: Paris | S39: =OR(AND(T39<>0,U39<>0,U39<>$AD$27),AND(T39=0,U39=0,V39=0,W39=0,X39=0,Y39=0)) -> TRUE | Z39: =IF(AND(T39<>"",U39<>"",U39<>$AD$27),0,1000000000000000) -> 1e+15 | AA39: =ROW(Y39) -> 39 | AC39: =Distances!C26 -> Berlin
C40: =OR(AND(D40<>0,E40<>0,E40<>$AD$27),AND(D40=0,E40=0,F40=0,G40=0,H40=0,I40=0)) -> TRUE | K40: =OR(AND(L40<>0,M40<>0,M40<>$AD$27),AND(L40=0,M40=0,N40=0,O40=0,P40=0,Q40=0)) -> TRUE | L40: Lorry 1 | M40: Budapest | P40: 66 | S40: =OR(AND(T40<>0,U40<>0,U40<>$AD$27),AND(T40=0,U40=0,V40=0,W40=0,X40=0,Y40=0)) -> TRUE | Z40: =IF(AND(T40<>"",U40<>"",U40<>$AD$27),0,1000000000000000) -> 1e+15 | AA40: =ROW(Y40) -> 40
C41: =OR(AND(D41<>0,E41<>0,E41<>$AD$27),AND(D41=0,E41=0,F41=0,G41=0,H41=0,I41=0)) -> TRUE | K41: =OR(AND(L41<>0,M41<>0,M41<>$AD$27),AND(L41=0,M41=0,N41=0,O41=0,P41=0,Q41=0)) -> TRUE | L41: Lorry 1 | M41: Arnhem factory | N41: 66 | S41: =OR(AND(T41<>0,U41<>0,U41<>$AD$27),AND(T41=0,U41=0,V41=0,W41=0,X41=0,Y41=0)) -> TRUE | Z41: =IF(AND(T41<>"",U41<>"",U41<>$AD$27),0,1000000000000000) -> 1e+15 | AA41: =ROW(Y41) -> 41
C42: =OR(AND(D42<>0,E42<>0,E42<>$AD$27),AND(D42=0,E42=0,F42=0,G42=0,H42=0,I42=0)) -> TRUE | D42: Lorry 2 | E42: Paris | F42: 16 | I42: 12 | K42: =OR(AND(L42<>0,M42<>0,M42<>$AD$27),AND(L42=0,M42=0,N42=0,O42=0,P42=0,Q42=0)) -> TRUE | L42: Lorry 1 | M42: Rauma | P42: 66 | S42: =OR(AND(T42<>0,U42<>0,U42<>$AD$27),AND(T42=0,U42=0,V42=0,W42=0,X42=0,Y42=0)) -> TRUE | Z42: =IF(AND(T42<>"",U42<>"",U42<>$AD$27),0,1000000000000000) -> 1e+15 | AA42: =ROW(Y42) -> 42
C43: =OR(AND(D43<>0,E43<>0,E43<>$AD$27),AND(D43=0,E43=0,F43=0,G43=0,H43=0,I43=0)) -> TRUE | D43: Lorry 2 | E43: Bucharest | H43: 16 | I43: 17 | K43: =OR(AND(L43<>0,M43<>0,M43<>$AD$27),AND(L43=0,M43=0,N43=0,O43=0,P43=0,Q43=0)) -> TRUE | L43: Lorry 2 | M43: Arnhem factory | N43: 50 | S43: =OR(AND(T43<>0,U43<>0,U43<>$AD$27),AND(T43=0,U43=0,V43=0,W43=0,X43=0,Y43=0)) -> TRUE | Z43: =IF(AND(T43<>"",U43<>"",U43<>$AD$27),0,1000000000000000) -> 1e+15 | AA43: =ROW(Y43) -> 43
C44: =OR(AND(D44<>0,E44<>0,E44<>$AD$27),AND(D44=0,E44=0,F44=0,G44=0,H44=0,I44=0)) -> TRUE | D44: Lorry 2 | E44: Budapest | I44: 21 | K44: =OR(AND(L44<>0,M44<>0,M44<>$AD$27),AND(L44=0,M44=0,N44=0,O44=0,P44=0,Q44=0)) -> TRUE | L44: Lorry 2 | M44: Madrid | P44: 50 | Q44: 15 | S44: =OR(AND(T44<>0,U44<>0,U44<>$AD$27),AND(T44=0,U44=0,V44=0,W44=0,X44=0,Y44=0)) -> TRUE | Z44: =IF(AND(T44<>"",U44<>"",U44<>$AD$27),0,1000000000000000) -> 1e+15 | AA44: =ROW(Y44) -> 44
C45: =OR(AND(D45<>0,E45<>0,E45<>$AD$27),AND(D45=0,E45=0,F45=0,G45=0,H45=0,I45=0)) -> TRUE | D45: Lorry 2 | E45: Vesoul factory | G45: 50 | K45: =OR(AND(L45<>0,M45<>0,M45<>$AD$27),AND(L45=0,M45=0,N45=0,O45=0,P45=0,Q45=0)) -> TRUE | L45: Lorry 2 | M45: Vesoul factory | S45: =OR(AND(T45<>0,U45<>0,U45<>$AD$27),AND(T45=0,U45=0,V45=0,W45=0,X45=0,Y45=0)) -> TRUE | Z45: =IF(AND(T45<>"",U45<>"",U45<>$AD$27),0,1000000000000000) -> 1e+15 | AA45: =ROW(Y45) -> 45
C46: =OR(AND(D46<>0,E46<>0,E46<>$AD$27),AND(D46=0,E46=0,F46=0,G46=0,H46=0,I46=0)) -> TRUE | D46: Lorry 1 | E46: Rome | H46: 31 | K46: =OR(AND(L46<>0,M46<>0,M46<>$AD$27),AND(L46=0,M46=0,N46=0,O46=0,P46=0,Q46=0)) -> TRUE | L46: Lorry 3 | M46: Vesoul factory | O46: 24 | S46: =OR(AND(T46<>0,U46<>0,U46<>$AD$27),AND(T46=0,U46=0,V46=0,W46=0,X46=0,Y46=0)) -> TRUE | Z46: =IF(AND(T46<>"",U46<>"",U46<>$AD$27),0,1000000000000000) -> 1e+15 | AA46: =ROW(Y46) -> 46
C47: =OR(AND(D47<>0,E47<>0,E47<>$AD$27),AND(D47=0,E47=0,F47=0,G47=0,H47=0,I47=0)) -> TRUE | D47: Lorry 1 | E47: Milan | H47: 30 | K47: =OR(AND(L47<>0,M47<>0,M47<>$AD$27),AND(L47=0,M47=0,N47=0,O47=0,P47=0,Q47=0)) -> TRUE | L47: Lorry 3 | M47: Paris | Q47: 24 | S47: =OR(AND(T47<>0,U47<>0,U47<>$AD$27),AND(T47=0,U47=0,V47=0,W47=0,X47=0,Y47=0)) -> TRUE | Z47: =IF(AND(T47<>"",U47<>"",U47<>$AD$27),0,1000000000000000) -> 1e+15 | AA47: =ROW(Y47) -> 47
C48: =OR(AND(D48<>0,E48<>0,E48<>$AD$27),AND(D48=0,E48=0,F48=0,G48=0,H48=0,I48=0)) -> TRUE | D48: Lorry 1 | E48: Berlin | H48: 5 | K48: =OR(AND(L48<>0,M48<>0,M48<>$AD$27),AND(L48=0,M48=0,N48=0,O48=0,P48=0,Q48=0)) -> TRUE | S48: =OR(AND(T48<>0,U48<>0,U48<>$AD$27),AND(T48=0,U48=0,V48=0,W48=0,X48=0,Y48=0)) -> TRUE | Z48: =IF(AND(T48<>"",U48<>"",U48<>$AD$27),0,1000000000000000) -> 1e+15 | AA48: =ROW(Y48) -> 48
C49: =OR(AND(D49<>0,E49<>0,E49<>$AD$27),AND(D49=0,E49=0,F49=0,G49=0,H49=0,I49=0)) -> TRUE | D49: Lorry 1 | E49: Arnhem factory | F49: 66 | K49: =OR(AND(L49<>0,M49<>0,M49<>$AD$27),AND(L49=0,M49=0,N49=0,O49=0,P49=0,Q49=0)) -> TRUE | S49: =OR(AND(T49<>0,U49<>0,U49<>$AD$27),AND(T49=0,U49=0,V49=0,W49=0,X49=0,Y49=0)) -> TRUE | Z49: =IF(AND(T49<>"",U49<>"",U49<>$AD$27),0,1000000000000000) -> 1e+15 | AA49: =ROW(Y49) -> 49
C50: =OR(AND(D50<>0,E50<>0,E50<>$AD$27),AND(D50=0,E50=0,F50=0,G50=0,H50=0,I50=0)) -> TRUE | D50: Lorry 2 | E50: Rome | I50: 25 | K50: =OR(AND(L50<>0,M50<>0,M50<>$AD$27),AND(L50=0,M50=0,N50=0,O50=0,P50=0,Q50=0)) -> TRUE | S50: =OR(AND(T50<>0,U50<>0,U50<>$AD$27),AND(T50=0,U50=0,V50=0,W50=0,X50=0,Y50=0)) -> TRUE | T50: Lorry 1 | U50: Arnhem factory | Z50: =IF(AND(T50<>"",U50<>"",U50<>$AD$27),0,1000000000000000) -> 0 | AA50: =ROW(Y50) -> 50
C51: =OR(AND(D51<>0,E51<>0,E51<>$AD$27),AND(D51=0,E51=0,F51=0,G51=0,H51=0,I51=0)) -> TRUE | D51: Lorry 2 | E51: Milan | I51: 22 | K51: =OR(AND(L51<>0,M51<>0,M51<>$AD$27),AND(L51=0,M51=0,N51=0,O51=0,P51=0,Q51=0)) -> TRUE | S51: =OR(AND(T51<>0,U51<>0,U51<>$AD$27),AND(T51=0,U51=0,V51=0,W51=0,X51=0,Y51=0)) -> TRUE | T51: Lorry 2 | U51: Vesoul factory | Z51: =IF(AND(T51<>"",U51<>"",U51<>$AD$27),0,1000000000000000) -> 0 | AA51: =ROW(Y51) -> 51
C52: =OR(AND(D52<>0,E52<>0,E52<>$AD$27),AND(D52=0,E52=0,F52=0,G52=0,H52=0,I52=0)) -> TRUE | D52: Lorry 2 | E52: Vesoul factory | G52: 47 | K52: =OR(AND(L52<>0,M52<>0,M52<>$AD$27),AND(L52=0,M52=0,N52=0,O52=0,P52=0,Q52=0)) -> TRUE | S52: =OR(AND(T52<>0,U52<>0,U52<>$AD$27),AND(T52=0,U52=0,V52=0,W52=0,X52=0,Y52=0)) -> TRUE | T52: Lorry 3 | U52: Paris | Z52: =IF(AND(T52<>"",U52<>"",U52<>$AD$27),0,1000000000000000) -> 0 | AA52: =ROW(Y52) -> 52
E55: Production in Europe
E57: Arnhem factory | M57: Vesoul factory
C59: 2 | E59: Nectar packaging | I59: 7 | J59: x 30 pallets | M59: Cordial packaging | Q59: 7 | R59: x 20 pallets
C60: 3 | E60: Nectar production | I60: 7 | J60: x 1 vat | M60: Cordial production | Q60: 7 | R60: x 1 vat
C61: 4 | E61: Hiring | I61: 0 | J61: x 1 person | M61: Hiring | Q61: 0 | R61: x 1 person
C62: 4 | E62: Laying-off | I62: 0 | J62: x 1 person | M62: Laying-off | Q62: 0 | R62: x 1 person
C63: 4 | E63: Pack Purchasing | I63: 10 | J63: x 1 batch | M63: Bottle Purchasing | Q63: 10 | R63: x 1 batch
C64: 4 | E64: Puree Purchasing | I64: 0 | J64: x 1 bin | M64: Sugar Purchasing | Q64: 10 | R64: x 1 tonne
C65: 4 | E65: Concentrate Purchasing for Arnhem | I65: 0 | J65: x 1 bin | M65: Concentrate Purchasing for Vesoul | Q65: 0 | R65: x 1 bin
E68: Intercontinental transport
C70: 5 | E70: Puree transport to Arnhem | I70: 60 | J70: x 1 bin
C71: 5 | E71: Concentrate transport to Arnhem | I71: 5 | J71: x 1 bin
C72: 5 | E72: Concentrate transport to Vesoul | I72: 10 | J72: x 1 bin
E75: Production in New-Zealand
E77: Auckland factory
C79: 6 | E79: Purchasing and pression of kiwis | I79: 24 | J79: x (4 bins of puree + 1 bin of concentrate)
C80: 7 | E80: Hiring | I80: 0 | J80: x 1 person
C81: 7 | E81: Laying-off | I81: 0 | J81: x 1 person
C82: 7 | E82: Puree sale | I82: 0 | J82: x 1 bin
C83: 7 | E83: Concentrate sale | I83: 0 | J83: x 1 bin

Sheet Bilan
A1: Distribution errors : | B1: 3
A2: Production errors : | B2: 2
D5: End of period 0 | E5: End of period 1 | F5: End of period 2 | G5: End of period 3 | H5: End of period 4 | I5: End of period 5 | J5: End of period 6 | K5: End of period 7 | L5: End of period 8 | M5: End of period 9 | N5: End of period 10 | O5: End of period 11 | P5: End of period 12
A6: Account
A7: cumulative result | D7: x | E7: 11454.5 | F7: -55172
A8: cumulative CO2 | E8: 340808.32 | F8: 722862.96
A10: Auckland factory
A11: concentrate (bin) | D11: 15 | E11: 15 | F11: 24
A12: puree (bin) | D12: 60 | E12: 60 | F12: 96
A13: staff | D13: 5 | E13: 8 | F13: 8
A14: Time not used | E14: 0 | F14: 0
A15: Puree sale | E15: 0 | F15: 0
A16: Concentrate sale | E16: 0 | F16: 0
A17: production cost (wages excluded) | E17: 150000 | F17: 240000
A18: concentrate storage cost | E18: 0 | F18: 0
A19: puree storage cost | E19: 0 | F19: 0
A20: Hiring cost | E20: 6000 | F20: 0
A21: Laying-off cost | E21: 0 | F21: 0
A22: wages cost | E22: 15000 | F22: 24000
A23: CO2 production | E23: 150000 | F23: 240000
A25: Intercontinental transport
A26: Intercontinental transport cost | E26: 15000 | F26: 15000
A27: CO2 production | E27: 14250 | F27: 14250
A29: Purchasing
A30: Puree Purchasing cost | E30: 0 | F30: 0
A31: concentrate Purchasing cost | E31: 0 | F31: 0
A32: Pack Purchasing cost | E32: 20000 | F32: 10000
A33: bottles Purchasing cost | E33: 60000 | F33: 30000
A34: Sugar Purchasing cost | E34: 8000 | F34: 4000
A35: CO2 from puree purchasing | E35: 0 | F35: 0
A36: CO2 from concentrate purchasing | E36: 0 | F36: 0
A37: CO2 from pack purchasing | E37: 18000 | F37: 9000
A38: CO2 from bottle purchasing | E38: 80000 | F38: 40000
A39: CO2 from sugar purchasing | E39: 6000 | F39: 3000
A41: Arnhem factory
A42: nectar (pallet) | D42: 300 | E42: 472 | F42: 282
A43: nectar (vat) | D43: 10 | E43: 7 | F43: 7
A44: cordial (pallet) | D44: 0 | E44: 0 | F44: 0
A45: concentrate (bin) | D45: 10 | E45: 13 | F45: 11
A46: puree (bin) | D46: 50 | E46: 65 | F46: 90
A47: pack (batch) | D47: 10 | E47: 20 | F47: 23
A48: staff | D48: 6 | E48: 6 | F48: 6
A49: Time not used | E49: 0 | F49: 60
A50: production cost (wages excluded) | E50: 3100 | F50: 2800
A51: cost of nectar pallets storage | E51: 2064 | F51: 864
A52: cost of nectar vats storage | E52: 0 | F52: 0
A53: cost of cordial pallets storage | E53: 0 | F53: 0
A54: concentrate storage cost | E54: 192 | F54: 384
A55: puree storage cost | E55: 660 | F55: 1320
A56: pack storage cost | E56: 0 | F56: 260
A57: Hiring cost | E57: 0 | F57: 0
A58: Laying-off cost | E58: 0 | F58: 0
A59: wages cost | E59: 18000 | F59: 18000
A60: CO2 production | E60: 19000 | F60: 17500
A62: Vesoul factory
A63: cordial (pallet) | D63: 200 | E63: 304 | F63: 185
A64: cordial (vat) | D64: 10 | E64: 7 | F64: 7
A65: nectar (pallet) | D65: 0 | E65: 0 | F65: 0
A66: concentrate (bin) | D66: 40 | E66: 52 | F66: 34
A67: sugar (tonne) | D67: 10 | E67: 23 | F67: 26
A68: bottle (batch) | D68: 10 | E68: 20 | F68: 23
A69: staff | D69: 6 | E69: 6 | F69: 6
A70: Time not used | E70: 0 | F70: 60
A71: production cost (wages excluded) | E71: 3100 | F71: 2800
A72: cost of cordial vats storage | E72: 0 | F72: 0
A73: cost of cordial pallets storage | E73: 1976 | F73: 855
A74: cost of nectar pallets storage | E74: 0 | F74: 0
A75: concentrate storage cost | E75: 768 | F75: 1536
A76: sugar storage cost | E76: 24 | F76: 128
A77: bottles storage cost | E77: 0 | F77: 780
A78: Hiring cost | E78: 0 | F78: 0
A79: Laying-off cost | E79: 0 | F79: 0
A80: wages cost | E80: 18000 | F80: 18000
A81: CO2 production | E81: 19000 | F81: 17500
A83: Lorry 1
A84: nectar (pallet) | E84: 0 | F84: 0
A85: cordial (pallet) | E85: 0 | F85: 0
A86: volume (pallet) | E86: 0 | F86: 0
A87: weight (tonne) | E87: -3.5527137e-15 | F87: -3.5527137e-15
A88: distance (km) | E88: 21967 | F88: 22676
A89: Time not used | E89: 124.88333 | F89: 99.266667
A90: transport cost | E90: 54917.5 | F90: 56690
A91: CO2 production | E91: 20209.64 | F91: 20861.92
A93: Lorry 2
A94: nectar (pallet) | E94: 0 | F94: 0
A95: cordial (pallet) | E95: 2 | F95: 0
A96: volume (pallet) | E96: 2 | F96: 0
A97: weight (tonne) | E97: 1 | F97: 0
A98: distance (km) | E98: 9539 | F98: 13476
A99: Time not used | E99: 88.076667 | F99: 11.78
A100: transport cost | E100: 19078 | F100: 26952
A101: CO2 production | E101: 8775.88 | F101: 12397.92
A103: Lorry 3
A104: nectar (pallet) | E104: 0 | F104: 0
A105: cordial (pallet) | E105: 0 | F105: 0
A106: volume (pallet) | E106: 0 | F106: 0
A107: weight (tonne) | E107: 0 | F107: 0
A108: distance (km) | E108: 6966 | F108: 9431
A109: Time not used | E109: 49.045714 | F109: 9.5114286
A110: transport cost | E110: 10449 | F110: 14146.5
...

Sheet Execution_Transports
A1: =LEFT(A2,A3-1) -> X:\MLT\Kiwis_2024\Profs\Equipe 03\
A2: =CELL("nomfichier",A3) -> X:\MLT\Kiwis_2024\Profs\Equipe 03\[decision2.xlsx]Execution_Transports
A3: =SEARCH("[",A2,1) -> 35
A4: D:\
A23: 1 | B23: 2 | C23: 3 | D23: 4 | E23: 5 | F23: 6 | G23: 7 | H23: 8 | I23: 9 | J23: 10 | K23: 11 | L23: 12 | M23: 13 | N23: 14 | O23: 15 | P23: 16 | Q23: 17 | R23: 18 | S23: 19 | T23: 20 | U23: 21 | V23: 22 | W23: 23 | X23: 24 | Y23: 25 | Z23: 26 | AA23: 27 | AB23: 28 | AC23: 29 | AD23: 30
E26: Départ | F26: Lorry | G26: distance (km) | H26: Arrivée | I26: Loading | K26: Unloading | N26: Départ | O26: Lorry | P26: distance (km) | Q26: Arrivée | R26: Loading | T26: Unloading | W26: Départ | X26: Lorry | Y26: distance (km) | Z26: Arrivée | AA26: Loading | AC26: Unloading
I27: A | J27: B | K27: A | L27: B | R27: A | S27: B | T27: A | U27: B | AA27: A | AB27: B | AC27: A | AD27: B
E28: Arnhem factory | F28: =Order!D28 -> Lorry 1 | G28: =IF(OR(E28=0,H28=0),0,INDEX(Distances!$E$15:$P$26,MATCH(E28,Distances!$C$15:$C$26,0),MATCH(H28,Distances!$E$13:$P$13,0))) -> 0 | H28: =Order!E28 -> Arnhem factory | I28: =Order!F28 -> 66 | J28: =Order!G28 -> 0 | K28: =Order!H28 -> 0 | L28: =Order!I28 -> 0 | N28: Vesoul factory | O28: =Order!L28 -> Lorry 2 | P28: =IF(OR(N28=0,Q28=0),0,INDEX(Distances!$E$15:$P$26,MATCH(N28,Distances!$C$15:$C$26,0),MATCH(Q28,Distances!$E$13:$P$13,0))) -> 360 | Q28: =Order!M28 -> Paris | R28: =Order!N28 -> 0 | S28: =Order!O28 -> 0 | T28: =Order!P28 -> 0 | U28: =Order!Q28 -> 20 | W28: Paris | X28: =Order!T28 -> Lorry 3 | Y28: =IF(OR(W28=0,Z28=0),0,INDEX(Distances!$E$15:$P$26,MATCH(W28,Distances!$C$15:$C$26,0),MATCH(Z28,Distances!$E$13:$P$13,0))) -> 0 | Z28: =Order!U28 -> Paris | AA28: =Order!V28 -> 24 | AB28: =Order!W28 -> 0 | AC28: =Order!X28 -> 0 | AD28: =Order!Y28 -> 0
E29: Vesoul factory | F29: =Order!D29 -> Lorry 2 | G29: =IF(OR(E29=0,H29=0),0,INDEX(Distances!$E$15:$P$26,MATCH(E29,Distances!$C$15:$C$26,0),MATCH(H29,Distances!$E$13:$P$13,0))) -> 0 | H29: =Order!E29 -> Vesoul factory | I29: =Order!F29 -> 0 | J29: =Order!G29 -> 48 | K29: =Order!H29 -> 0 | L29: =Order!I29 -> 0 | N29: Paris | O29: =Order!L29 -> Lorry 2 | P29: =IF(OR(N29=0,Q29=0),0,INDEX(Distances!$E$15:$P$26,MATCH(N29,Distances!$C$15:$C$26,0),MATCH(Q29,Distances!$E$13:$P$13,0))) -> 1408 | Q29: =Order!M29 -> Berlin | R29: =Order!N29 -> 0 | S29: =Order!O29 -> 0 | T29: =Order!P29 -> 0 | U29: =Order!Q29 -> 30 | W29: Paris | X29: =Order!T29 -> Lorry 3 | Y29: =IF(OR(W29=0,Z29=0),0,INDEX(Distances!$E$15:$P$26,MATCH(W29,Distances!$C$15:$C$26,0),MATCH(Z29,Distances!$E$13:$P$13,0))) -> 1274 | Z29: =Order!U29 -> Madrid | AA29: =Order!V29 -> 0 | AB29: =Order!W29 -> 0 | AC29: =Order!X29 -> 24 | AD29: =Order!Y29 -> 0
E30: Paris | F30: =Order!D30 -> Lorry 3 | G30: =IF(OR(E30=0,H30=0),0,INDEX(Distances!$E$15:$P$26,MATCH(E30,Distances!$C$15:$C$26,0),MATCH(H30,Distances!$E$13:$P$13,0))) -> 0 | H30: =Order!E30 -> Paris | I30: =Order!F30 -> 0 | J30: =Order!G30 -> 0 | K30: =Order!H30 -> 0 | L30: =Order!I30 -> 0 | N30: Berlin | O30: =Order!L30 -> Lorry 2 | P30: =IF(OR(N30=0,Q30=0),0,INDEX(Distances!$E$15:$P$26,MATCH(N30,Distances!$C$15:$C$26,0),MATCH(Q30,Distances!$E$13:$P$13,0))) -> 967 | Q30: =Order!M30 -> Vesoul factory | R30: =Order!N30 -> 0 | S30: =Order!O30 -> 15 | T30: =Order!P30 -> 0 | U30: =Order!Q30 -> 0 | W30: Madrid | X30: =Order!T30 -> Lorry 3 | Y30: =IF(OR(W30=0,Z30=0),0,INDEX(Distances!$E$15:$P$26,MATCH(W30,Distances!$C$15:$C$26,0),MATCH(Z30,Distances!$E$13:$P$13,0))) -> 1274 | Z30: =Order!U30 -> Paris | AA30: =Order!V30 -> 3 | AB30: =Order!W30 -> 0 | AC30: =Order!X30 -> 0 | AD30: =Order!Y30 -> 0
E31: Arnhem factory | F31: =Order!D31 -> Lorry 1 | G31: =IF(OR(E31=0,H31=0),0,INDEX(Distances!$E$15:$P$26,MATCH(E31,Distances!$C$15:$C$26,0),MATCH(H31,Distances!$E$13:$P$13,0))) -> 509 | H31: =Order!E31 -> Paris | I31: =Order!F31 -> 0 | J31: =Order!G31 -> 0 | K31: =Order!H31 -> 66 | L31: =Order!I31 -> 0 | N31: Arnhem factory | O31: =Order!L31 -> Lorry 1 | P31: =IF(OR(N31=0,Q31=0),0,INDEX(Distances!$E$15:$P$26,MATCH(N31,Distances!$C$15:$C$26,0),MATCH(Q31,Distances!$E$13:$P$13,0))) -> 1134 | Q31: =Order!M31 -> Warsaw | R31: =Order!N31 -> 0 | S31: =Order!O31 -> 0 | T31: =Order!P31 -> 19 | U31: =Order!Q31 -> 0 | W31: Paris | X31: =Order!T31 -> Lorry 3 | Y31: =IF(OR(W31=0,Z31=0),0,INDEX(Distances!$E$15:$P$26,MATCH(W31,Distances!$C$15:$C$26,0),MATCH(Z31,Distances!$E$13:$P$13,0))) -> 360 | Z31: =Order!U31 -> Vesoul factory | AA31: =Order!V31 -> 0 | AB31: =Order!W31 -> 21 | AC31: =Order!X31 -> 0 | AD31: =Order!Y31 -> 0
E32: Paris | F32: =Order!D32 -> Lorry 1 | G32: =IF(OR(E32=0,H32=0),0,INDEX(Distances!$E$15:$P$26,MATCH(E32,Distances!$C$15:$C$26,0),MATCH(H32,Distances!$E$13:$P$13,0))) -> 360 | H32: =Order!E32 -> Vesoul factory | I32: =Order!F32 -> 0 | J32: =Order!G32 -> 50 | K32: =Order!H32 -> 0 | L32: =Order!I32 -> 0 | N32: Warsaw | O32: =Order!L32 -> Lorry 1 | P32: =IF(OR(N32=0,Q32=0),0,INDEX(Distances!$E$15:$P$26,MATCH(N32,Distances!$C$15:$C$26,0),MATCH(Q32,Distances!$E$13:$P$13,0))) -> 1952 | Q32: =Order!M32 -> Kemijarvi | R32: =Order!N32 -> 0 | S32: =Order!O32 -> 0 | T32: =Order!P32 -> 18 | U32: =Order!Q32 -> 0 | W32: Vesoul factory | X32: =Order!T32 -> Lorry 3 | Y32: =IF(OR(W32=0,Z32=0),0,INDEX(Distances!$E$15:$P$26,MATCH(W32,Distances!$C$15:$C$26,0),MATCH(Z32,Distances!$E$13:$P$13,0))) -> 1527 | Z32: =Order!U32 -> Madrid | AA32: =Order!V32 -> 0 | AB32: =Order!W32 -> 0 | AC32: =Order!X32 -> 3 | AD32: =Order!Y32 -> 21
E33: Vesoul factory | F33: =Order!D33 -> Lorry 1 | G33: =IF(OR(E33=0,H33=0),0,INDEX(Distances!$E$15:$P$26,MATCH(E33,Distances!$C$15:$C$26,0),MATCH(H33,Distances!$E$13:$P$13,0))) -> 967 | H33: =Order!E33 -> Berlin | I33: =Order!F33 -> 0 | J33: =Order!G33 -> 0 | K33: =Order!H33 -> 0 | L33: =Order!I33 -> 15 | N33: Kemijarvi | O33: =Order!L33 -> Lorry 1 | P33: =IF(OR(N33=0,Q33=0),0,INDEX(Distances!$E$15:$P$26,MATCH(N33,Distances!$C$15:$C$26,0),MATCH(Q33,Distances!$E$13:$P$13,0))) -> 832 | Q33: =Order!M33 -> Rauma | R33: =Order!N33 -> 0 | S33: =Order!O33 -> 0 | T33: =Order!P33 -> 24 | U33: =Order!Q33 -> 0 | W33: Madrid | X33: =Order!T33 -> Lorry 3 | Y33: =IF(OR(W33=0,Z33=0),0,INDEX(Distances!$E$15:$P$26,MATCH(W33,Distances!$C$15:$C$26,0),MATCH(Z33,Distances!$E$13:$P$13,0))) -> 1274 | Z33: =Order!U33 -> Paris | AA33: =Order!V33 -> 0 | AB33: =Order!W33 -> 0 | AC33: =Order!X33 -> 0 | AD33: =Order!Y33 -> 0
E34: Berlin | F34: =Order!D34 -> Lorry 1 | G34: =IF(OR(E34=0,H34=0),0,INDEX(Distances!$E$15:$P$26,MATCH(E34,Distances!$C$15:$C$26,0),MATCH(H34,Distances!$E$13:$P$13,0))) -> 1483 | H34: =Order!E34 -> Rauma | I34: =Order!F34 -> 0 | J34: =Order!G34 -> 0 | K34: =Order!H34 -> 0 | L34: =Order!I34 -> 17 | N34: Rauma | O34: =Order!L34 -> Lorry 1 | P34: =IF(OR(N34=0,Q34=0),0,INDEX(Distances!$E$15:$P$26,MATCH(N34,Distances!$C$15:$C$26,0),MATCH(Q34,Distances!$E$13:$P$13,0))) -> 1483 | Q34: =Order!M34 -> Berlin | R34: =Order!N34 -> 0 | S34: =Order!O34 -> 0 | T34: =Order!P34 -> 5 | U34: =Order!Q34 -> 0 | W34: 0 | X34: =Order!T34 -> 0 | Y34: =IF(OR(W34=0,Z34=0),0,INDEX(Distances!$E$15:$P$26,MATCH(W34,Distances!$C$15:$C$26,0),MATCH(Z34,Distances!$E$13:$P$13,0))) -> 0 | Z34: =Order!U34 -> 0 | AA34: =Order!V34 -> 0 | AB34: =Order!W34 -> 0 | AC34: =Order!X34 -> 0 | AD34: =Order!Y34 -> 0
E35: Rauma | F35: =Order!D35 -> Lorry 1 | G35: =IF(OR(E35=0,H35=0),0,INDEX(Distances!$E$15:$P$26,MATCH(E35,Distances!$C$15:$C$26,0),MATCH(H35,Distances!$E$13:$P$13,0))) -> 832 | H35: =Order!E35 -> Kemijarvi | I35: =Order!F35 -> 0 | J35: =Order!G35 -> 0 | K35: =Order!H35 -> 0 | L35: =Order!I35 -> 18 | N35: Berlin | O35: =Order!L35 -> Lorry 1 | P35: =IF(OR(N35=0,Q35=0),0,INDEX(Distances!$E$15:$P$26,MATCH(N35,Distances!$C$15:$C$26,0),MATCH(Q35,Distances!$E$13:$P$13,0))) -> 597 | Q35: =Order!M35 -> Arnhem factory | R35: =Order!N35 -> 66 | S35: =Order!O35 -> 0 | T35: =Order!P35 -> 0 | U35: =Order!Q35 -> 0 | W35: 0 | X35: =Order!T35 -> 0 | Y35: =IF(OR(W35=0,Z35=0),0,INDEX(Distances!$E$15:$P$26,MATCH(W35,Distances!$C$15:$C$26,0),MATCH(Z35,Distances!$E$13:$P$13,0))) -> 0 | Z35: =Order!U35 -> 0 | AA35: =Order!V35 -> 0 | AB35: =Order!W35 -> 0 | AC35: =Order!X35 -> 0 | AD35: =Order!Y35 -> 0
E36: Kemijarvi | F36: =Order!D36 -> Lorry 1 | G36: =IF(OR(E36=0,H36=0),0,INDEX(Distances!$E$15:$P$26,MATCH(E36,Distances!$C$15:$C$26,0),MATCH(H36,Distances!$E$13:$P$13,0))) -> 2597 | H36: =Order!E36 -> Arnhem factory | I36: =Order!F36 -> 66 | J36: =Order!G36 -> 0 | K36: =Order!H36 -> 0 | L36: =Order!I36 -> 0 | N36: Paris | O36: =Order!L36 -> Lorry 3 | P36: =IF(OR(N36=0,Q36=0),0,INDEX(Distances!$E$15:$P$26,MATCH(N36,Distances!$C$15:$C$26,0),MATCH(Q36,Distances!$E$13:$P$13,0))) -> 360 | Q36: =Order!M36 -> Vesoul factory | R36: =Order!N36 -> 0 | S36: =Order!O36 -> 4 | T36: =Order!P36 -> 0 | U36: =Order!Q36 -> 0 | W36: 0 | X36: =Order!T36 -> 0 | Y36: =IF(OR(W36=0,Z36=0),0,INDEX(Distances!$E$15:$P$26,MATCH(W36,Distances!$C$15:$C$26,0),MATCH(Z36,Distances!$E$13:$P$13,0))) -> 0 | Z36: =Order!U36 -> 0 | AA36: =Order!V36 -> 0 | AB36: =Order!W36 -> 0 | AC36: =Order!X36 -> 0 | AD36: =Order!Y36 -> 0
E37: 0 | F37: =Order!D37 -> 0 | G37: =IF(OR(E37=0,H37=0),0,INDEX(Distances!$E$15:$P$26,MATCH(E37,Distances!$C$15:$C$26,0),MATCH(H37,Distances!$E$13:$P$13,0))) -> 0 | H37: =Order!E37 -> 0 | I37: =Order!F37 -> 0 | J37: =Order!G37 -> 0 | K37: =Order!H37 -> 0 | L37: =Order!I37 -> 0 | N37: Vesoul factory | O37: =Order!L37 -> Lorry 3 | P37: =IF(OR(N37=0,Q37=0),0,INDEX(Distances!$E$15:$P$26,MATCH(N37,Distances!$C$15:$C$26,0),MATCH(Q37,Distances!$E$13:$P$13,0))) -> 637 | Q37: =Order!M37 -> Arnhem factory | R37: =Order!N37 -> 20 | S37: =Order!O37 -> 0 | T37: =Order!P37 -> 0 | U37: =Order!Q37 -> 0 | W37: 0 | X37: =Order!T37 -> 0 | Y37: =IF(OR(W37=0,Z37=0),0,INDEX(Distances!$E$15:$P$26,MATCH(W37,Distances!$C$15:$C$26,0),MATCH(Z37,Distances!$E$13:$P$13,0))) -> 0 | Z37: =Order!U37 -> 0 | AA37: =Order!V37 -> 0 | AB37: =Order!W37 -> 0 | AC37: =Order!X37 -> 0 | AD37: =Order!Y37 -> 0
E38: 0 | F38: =Order!D38 -> 0 | G38: =IF(OR(E38=0,H38=0),0,INDEX(Distances!$E$15:$P$26,MATCH(E38,Distances!$C$15:$C$26,0),MATCH(H38,Distances!$E$13:$P$13,0))) -> 0 | H38: =Order!E38 -> 0 | I38: =Order!F38 -> 0 | J38: =Order!G38 -> 0 | K38: =Order!H38 -> 0 | L38: =Order!I38 -> 0 | N38: Arnhem factory | O38: =Order!L38 -> Lorry 3 | P38: =IF(OR(N38=0,Q38=0),0,INDEX(Distances!$E$15:$P$26,MATCH(N38,Distances!$C$15:$C$26,0),MATCH(Q38,Distances!$E$13:$P$13,0))) -> 597 | Q38: =Order!M38 -> Berlin | R38: =Order!N38 -> 0 | S38: =Order!O38 -> 0 | T38: =Order!P38 -> 20 | U38: =Order!Q38 -> 4 | W38: 0 | X38: =Order!T38 -> 0 | Y38: =IF(OR(W38=0,Z38=0),0,INDEX(Distances!$E$15:$P$26,MATCH(W38,Distances!$C$15:$C$26,0),MATCH(Z38,Distances!$E$13:$P$13,0))) -> 0 | Z38: =Order!U38 -> 0 | AA38: =Order!V38 -> 0 | AB38: =Order!W38 -> 0 | AC38: =Order!X38 -> 0 | AD38: =Order!Y38 -> 0
E39: 0 | F39: =Order!D39 -> 0 | G39: =IF(OR(E39=0,H39=0),0,INDEX(Distances!$E$15:$P$26,MATCH(E39,Distances!$C$15:$C$26,0),MATCH(H39,Distances!$E$13:$P$13,0))) -> 0 | H39: =Order!E39 -> 0 | I39: =Order!F39 -> 0 | J39: =Order!G39 -> 0 | K39: =Order!H39 -> 0 | L39: =Order!I39 -> 0 | N39: Berlin | O39: =Order!L39 -> Lorry 3 | P39: =IF(OR(N39=0,Q39=0),0,INDEX(Distances!$E$15:$P$26,MATCH(N39,Distances!$C$15:$C$26,0),MATCH(Q39,Distances!$E$13:$P$13,0))) -> 1408 | Q39: =Order!M39 -> Paris | R39: =Order!N39 -> 0 | S39: =Order!O39 -> 0 | T39: =Order!P39 -> 0 | U39: =Order!Q39 -> 0 | W39: 0 | X39: =Order!T39 -> 0 | Y39: =IF(OR(W39=0,Z39=0),0,INDEX(Distances!$E$15:$P$26,MATCH(W39,Distances!$C$15:$C$26,0),MATCH(Z39,Distances!$E$13:$P$13,0))) -> 0 | Z39: =Order!U39 -> 0 | AA39: =Order!V39 -> 0 | AB39: =Order!W39 -> 0 | AC39: =Order!X39 -> 0 | AD39: =Order!Y39 -> 0
E40: 0 | F40: =Order!D40 -> 0 | G40: =IF(OR(E40=0,H40=0),0,INDEX(Distances!$E$15:$P$26,MATCH(E40,Distances!$C$15:$C$26,0),MATCH(H40,Distances!$E$13:$P$13,0))) -> 0 | H40: =Order!E40 -> 0 | I40: =Order!F40 -> 0 | J40: =Order!G40 -> 0 | K40: =Order!H40 -> 0 | L40: =Order!I40 -> 0 | N40: Arnhem factory | O40: =Order!L40 -> Lorry 1 | P40: =IF(OR(N40=0,Q40=0),0,INDEX(Distances!$E$15:$P$26,MATCH(N40,Distances!$C$15:$C$26,0),MATCH(Q40,Distances!$E$13:$P$13,0))) -> 1301 | Q40: =Order!M40 -> Budapest | R40: =Order!N40 -> 0 | S40: =Order!O40 -> 0 | T40: =Order!P40 -> 66 | U40: =Order!Q40 -> 0 | W40: 0 | X40: =Order!T40 -> 0 | Y40: =IF(OR(W40=0,Z40=0),0,INDEX(Distances!$E$15:$P$26,MATCH(W40,Distances!$C$15:$C$26,0),MATCH(Z40,Distances!$E$13:$P$13,0))) -> 0 | Z40: =Order!U40 -> 0 | AA40: =Order!V40 -> 0 | AB40: =Order!W40 -> 0 | AC40: =Order!X40 -> 0 | AD40: =Order!Y40 -> 0
E41: 0 | F41: =Order!D41 -> 0 | G41: =IF(OR(E41=0,H41=0),0,INDEX(Distances!$E$15:$P$26,MATCH(E41,Distances!$C$15:$C$26,0),MATCH(H41,Distances!$E$13:$P$13,0))) -> 0 | H41: =Order!E41 -> 0 | I41: =Order!F41 -> 0 | J41: =Order!G41 -> 0 | K41: =Order!H41 -> 0 | L41: =Order!I41 -> 0 | N41: Budapest | O41: =Order!L41 -> Lorry 1 | P41: =IF(OR(N41=0,Q41=0),0,INDEX(Distances!$E$15:$P$26,MATCH(N41,Distances!$C$15:$C$26,0),MATCH(Q41,Distances!$E$13:$P$13,0))) -> 1301 | Q41: =Order!M41 -> Arnhem factory | R41: =Order!N41 -> 66 | S41: =Order!O41 -> 0 | T41: =Order!P41 -> 0 | U41: =Order!Q41 -> 0 | W41: 0 | X41: =Order!T41 -> 0 | Y41: =IF(OR(W41=0,Z41=0),0,INDEX(Distances!$E$15:$P$26,MATCH(W41,Distances!$C$15:$C$26,0),MATCH(Z41,Distances!$E$13:$P$13,0))) -> 0 | Z41: =Order!U41 -> 0 | AA41: =Order!V41 -> 0 | AB41: =Order!W41 -> 0 | AC41: =Order!X41 -> 0 | AD41: =Order!Y41 -> 0
E42: Vesoul factory | F42: =Order!D42 -> Lorry 2 | G42: =IF(OR(E42=0,H42=0),0,INDEX(Distances!$E$15:$P$26,MATCH(E42,Distances!$C$15:$C$26,0),MATCH(H42,Distances!$E$13:$P$13,0))) -> 360 | H42: =Order!E42 -> Paris | I42: =Order!F42 -> 16 | J42: =Order!G42 -> 0 | K42: =Order!H42 -> 0 | L42: =Order!I42 -> 12 | N42: Arnhem factory | O42: =Order!L42 -> Lorry 1 | P42: =IF(OR(N42=0,Q42=0),0,INDEX(Distances!$E$15:$P$26,MATCH(N42,Distances!$C$15:$C$26,0),MATCH(Q42,Distances!$E$13:$P$13,0))) -> 1771 | Q42: =Order!M42 -> Rauma | R42: =Order!N42 -> 0 | S42: =Order!O42 -> 0 | T42: =Order!P42 -> 66 | U42: =Order!Q42 -> 0 | W42: 0 | X42: =Order!T42 -> 0 | Y42: =IF(OR(W42=0,Z42=0),0,INDEX(Distances!$E$15:$P$26,MATCH(W42,Distances!$C$15:$C$26,0),MATCH(Z42,Distances!$E$13:$P$13,0))) -> 0 | Z42: =Order!U42 -> 0 | AA42: =Order!V42 -> 0 | AB42: =Order!W42 -> 0 | AC42: =Order!X42 -> 0 | AD42: =Order!Y42 -> 0
E43: Paris | F43: =Order!D43 -> Lorry 2 | G43: =IF(OR(E43=0,H43=0),0,INDEX(Distances!$E$15:$P$26,MATCH(E43,Distances!$C$15:$C$26,0),MATCH(H43,Distances!$E$13:$P$13,0))) -> 2284 | H43: =Order!E43 -> Bucharest | I43: =Order!F43 -> 0 | J43: =Order!G43 -> 0 | K43: =Order!H43 -> 16 | L43: =Order!I43 -> 17 | N43: Vesoul factory | O43: =Order!L43 -> Lorry 2 | P43: =IF(OR(N43=0,Q43=0),0,INDEX(Distances!$E$15:$P$26,MATCH(N43,Distances!$C$15:$C$26,0),MATCH(Q43,Distances!$E$13:$P$13,0))) -> 637 | Q43: =Order!M43 -> Arnhem factory | R43: =Order!N43 -> 50 | S43: =Order!O43 -> 0 | T43: =Order!P43 -> 0 | U43: =Order!Q43 -> 0 | W43: 0 | X43: =Order!T43 -> 0 | Y43: =IF(OR(W43=0,Z43=0),0,INDEX(Distances!$E$15:$P$26,MATCH(W43,Distances!$C$15:$C$26,0),MATCH(Z43,Distances!$E$13:$P$13,0))) -> 0 | Z43: =Order!U43 -> 0 | AA43: =Order!V43 -> 0 | AB43: =Order!W43 -> 0 | AC43: =Order!X43 -> 0 | AD43: =Order!Y43 -> 0
E44: Bucharest | F44: =Order!D44 -> Lorry 2 | G44: =IF(OR(E44=0,H44=0),0,INDEX(Distances!$E$15:$P$26,MATCH(E44,Distances!$C$15:$C$26,0),MATCH(H44,Distances!$E$13:$P$13,0))) -> 796 | H44: =Order!E44 -> Budapest | I44: =Order!F44 -> 0 | J44: =Order!G44 -> 0 | K44: =Order!H44 -> 0 | L44: =Order!I44 -> 21 | N44: Arnhem factory | O44: =Order!L44 -> Lorry 2 | P44: =IF(OR(N44=0,Q44=0),0,INDEX(Distances!$E$15:$P$26,MATCH(N44,Distances!$C$15:$C$26,0),MATCH(Q44,Distances!$E$13:$P$13,0))) -> 1764 | Q44: =Order!M44 -> Madrid | R44: =Order!N44 -> 0 | S44: =Order!O44 -> 0 | T44: =Order!P44 -> 50 | U44: =Order!Q44 -> 15 | W44: 0 | X44: =Order!T44 -> 0 | Y44: =IF(OR(W44=0,Z44=0),0,INDEX(Distances!$E$15:$P$26,MATCH(W44,Distances!$C$15:$C$26,0),MATCH(Z44,Distances!$E$13:$P$13,0))) -> 0 | Z44: =Order!U44 -> 0 | AA44: =Order!V44 -> 0 | AB44: =Order!W44 -> 0 | AC44: =Order!X44 -> 0 | AD44: =Order!Y44 -> 0
E45: Budapest | F45: =Order!D45 -> Lorry 2 | G45: =IF(OR(E45=0,H45=0),0,INDEX(Distances!$E$15:$P$26,MATCH(E45,Distances!$C$15:$C$26,0),MATCH(H45,Distances!$E$13:$P$13,0))) -> 1224 | H45: =Order!E45 -> Vesoul factory | I45: =Order!F45 -> 0 | J45: =Order!G45 -> 50 | K45: =Order!H45 -> 0 | L45: =Order!I45 -> 0 | N45: Madrid | O45: =Order!L45 -> Lorry 2 | P45: =IF(OR(N45=0,Q45=0),0,INDEX(Distances!$E$15:$P$26,MATCH(N45,Distances!$C$15:$C$26,0),MATCH(Q45,Distances!$E$13:$P$13,0))) -> 1527 | Q45: =Order!M45 -> Vesoul factory | R45: =Order!N45 -> 0 | S45: =Order!O45 -> 0 | T45: =Order!P45 -> 0 | U45: =Order!Q45 -> 0 | W45: 0 | X45: =Order!T45 -> 0 | Y45: =IF(OR(W45=0,Z45=0),0,INDEX(Distances!$E$15:$P$26,MATCH(W45,Distances!$C$15:$C$26,0),MATCH(Z45,Distances!$E$13:$P$13,0))) -> 0 | Z45: =Order!U45 -> 0 | AA45: =Order!V45 -> 0 | AB45: =Order!W45 -> 0 | AC45: =Order!X45 -> 0 | AD45: =Order!Y45 -> 0
E46: Arnhem factory | F46: =Order!D46 -> Lorry 1 | G46: =IF(OR(E46=0,H46=0),0,INDEX(Distances!$E$15:$P$26,MATCH(E46,Distances!$C$15:$C$26,0),MATCH(H46,Distances!$E$13:$P$13,0))) -> 1577 | H46: =Order!E46 -> Rome | I46: =Order!F46 -> 0 | J46: =Order!G46 -> 0 | K46: =Order!H46 -> 31 | L46: =Order!I46 -> 0 | N46: Paris | O46: =Order!L46 -> Lorry 3 | P46: =IF(OR(N46=0,Q46=0),0,INDEX(Distances!$E$15:$P$26,MATCH(N46,Distances!$C$15:$C$26,0),MATCH(Q46,Distances!$E$13:$P$13,0))) -> 360 | Q46: =Order!M46 -> Vesoul factory | R46: =Order!N46 -> 0 | S46: =Order!O46 -> 24 | T46: =Order!P46 -> 0 | U46: =Order!Q46 -> 0 | W46: 0 | X46: =Order!T46 -> 0 | Y46: =IF(OR(W46=0,Z46=0),0,INDEX(Distances!$E$15:$P$26,MATCH(W46,Distances!$C$15:$C$26,0),MATCH(Z46,Distances!$E$13:$P$13,0))) -> 0 | Z46: =Order!U46 -> 0 | AA46: =Order!V46 -> 0 | AB46: =Order!W46 -> 0 | AC46: =Order!X46 -> 0 | AD46: =Order!Y46 -> 0
E47: Rome | F47: =Order!D47 -> Lorry 1 | G47: =IF(OR(E47=0,H47=0),0,INDEX(Distances!$E$15:$P$26,MATCH(E47,Distances!$C$15:$C$26,0),MATCH(H47,Distances!$E$13:$P$13,0))) -> 584 | H47: =Order!E47 -> Milan | I47: =Order!F47 -> 0 | J47: =Order!G47 -> 0 | K47: =Order!H47 -> 30 | L47: =Order!I47 -> 0 | N47: Vesoul factory | O47: =Order!L47 -> Lorry 3 | P47: =IF(OR(N47=0,Q47=0),0,INDEX(Distances!$E$15:$P$26,MATCH(N47,Distances!$C$15:$C$26,0),MATCH(Q47,Distances!$E$13:$P$13,0))) -> 360 | Q47: =Order!M47 -> Paris | R47: =Order!N47 -> 0 | S47: =Order!O47 -> 0 | T47: =Order!P47 -> 0 | U47: =Order!Q47 -> 24 | W47: 0 | X47: =Order!T47 -> 0 | Y47: =IF(OR(W47=0,Z47=0),0,INDEX(Distances!$E$15:$P$26,MATCH(W47,Distances!$C$15:$C$26,0),MATCH(Z47,Distances!$E$13:$P$13,0))) -> 0 | Z47: =Order!U47 -> 0 | AA47: =Order!V47 -> 0 | AB47: =Order!W47 -> 0 | AC47: =Order!X47 -> 0 | AD47: =Order!Y47 -> 0
E48: Milan | F48: =Order!D48 -> Lorry 1 | G48: =IF(OR(E48=0,H48=0),0,INDEX(Distances!$E$15:$P$26,MATCH(E48,Distances!$C$15:$C$26,0),MATCH(H48,Distances!$E$13:$P$13,0))) -> 1028 | H48: =Order!E48 -> Berlin | I48: =Order!F48 -> 0 | J48: =Order!G48 -> 0 | K48: =Order!H48 -> 5 | L48: =Order!I48 -> 0 | N48: 0 | O48: =Order!L48 -> 0 | P48: =IF(OR(N48=0,Q48=0),0,INDEX(Distances!$E$15:$P$26,MATCH(N48,Distances!$C$15:$C$26,0),MATCH(Q48,Distances!$E$13:$P$13,0))) -> 0 | Q48: =Order!M48 -> 0 | R48: =Order!N48 -> 0 | S48: =Order!O48 -> 0 | T48: =Order!P48 -> 0 | U48: =Order!Q48 -> 0 | W48: 0 | X48: =Order!T48 -> 0 | Y48: =IF(OR(W48=0,Z48=0),0,INDEX(Distances!$E$15:$P$26,MATCH(W48,Distances!$C$15:$C$26,0),MATCH(Z48,Distances!$E$13:$P$13,0))) -> 0 | Z48: =Order!U48 -> 0 | AA48: =Order!V48 -> 0 | AB48: =Order!W48 -> 0 | AC48: =Order!X48 -> 0 | AD48: =Order!Y48 -> 0
E49: Berlin | F49: =Order!D49 -> Lorry 1 | G49: =IF(OR(E49=0,H49=0),0,INDEX(Distances!$E$15:$P$26,MATCH(E49,Distances!$C$15:$C$26,0),MATCH(H49,Distances!$E$13:$P$13,0))) -> 597 | H49: =Order!E49 -> Arnhem factory | I49: =Order!F49 -> 66 | J49: =Order!G49 -> 0 | K49: =Order!H49 -> 0 | L49: =Order!I49 -> 0 | N49: 0 | O49: =Order!L49 -> 0 | P49: =IF(OR(N49=0,Q49=0),0,INDEX(Distances!$E$15:$P$26,MATCH(N49,Distances!$C$15:$C$26,0),MATCH(Q49,Distances!$E$13:$P$13,0))) -> 0 | Q49: =Order!M49 -> 0 | R49: =Order!N49 -> 0 | S49: =Order!O49 -> 0 | T49: =Order!P49 -> 0 | U49: =Order!Q49 -> 0 | W49: 0 | X49: =Order!T49 -> 0 | Y49: =IF(OR(W49=0,Z49=0),0,INDEX(Distances!$E$15:$P$26,MATCH(W49,Distances!$C$15:$C$26,0),MATCH(Z49,Distances!$E$13:$P$13,0))) -> 0 | Z49: =Order!U49 -> 0 | AA49: =Order!V49 -> 0 | AB49: =Order!W49 -> 0 | AC49: =Order!X49 -> 0 | AD49: =Order!Y49 -> 0
E50: Vesoul factory | F50: =Order!D50 -> Lorry 2 | G50: =IF(OR(E50=0,H50=0),0,INDEX(Distances!$E$15:$P$26,MATCH(E50,Distances!$C$15:$C$26,0),MATCH(H50,Distances!$E$13:$P$13,0))) -> 1081 | H50: =Order!E50 -> Rome | I50: =Order!F50 -> 0 | J50: =Order!G50 -> 0 | K50: =Order!H50 -> 0 | L50: =Order!I50 -> 25 | N50: 0 | O50: =Order!L50 -> 0 | P50: =IF(OR(N50=0,Q50=0),0,INDEX(Distances!$E$15:$P$26,MATCH(N50,Distances!$C$15:$C$26,0),MATCH(Q50,Distances!$E$13:$P$13,0))) -> 0 | Q50: =Order!M50 -> 0 | R50: =Order!N50 -> 0 | S50: =Order!O50 -> 0 | T50: =Order!P50 -> 0 | U50: =Order!Q50 -> 0 | W50: Rauma | X50: =Order!T50 -> Lorry 1 | Y50: =IF(OR(W50=0,Z50=0),0,INDEX(Distances!$E$15:$P$26,MATCH(W50,Distances!$C$15:$C$26,0),MATCH(Z50,Distances!$E$13:$P$13,0))) -> 1771 | Z50: =Order!U50 -> Arnhem factory | AA50: =Order!V50 -> 0 | AB50: =Order!W50 -> 0 | AC50: =Order!X50 -> 0 | AD50: =Order!Y50 -> 0
E51: Rome | F51: =Order!D51 -> Lorry 2 | G51: =IF(OR(E51=0,H51=0),0,INDEX(Distances!$E$15:$P$26,MATCH(E51,Distances!$C$15:$C$26,0),MATCH(H51,Distances!$E$13:$P$13,0))) -> 584 | H51: =Order!E51 -> Milan | I51: =Order!F51 -> 0 | J51: =Order!G51 -> 0 | K51: =Order!H51 -> 0 | L51: =Order!I51 -> 22 | N51: 0 | O51: =Order!L51 -> 0 | P51: =IF(OR(N51=0,Q51=0),0,INDEX(Distances!$E$15:$P$26,MATCH(N51,Distances!$C$15:$C$26,0),MATCH(Q51,Distances!$E$13:$P$13,0))) -> 0 | Q51: =Order!M51 -> 0 | R51: =Order!N51 -> 0 | S51: =Order!O51 -> 0 | T51: =Order!P51 -> 0 | U51: =Order!Q51 -> 0 | W51: Vesoul factory | X51: =Order!T51 -> Lorry 2 | Y51: =IF(OR(W51=0,Z51=0),0,INDEX(Distances!$E$15:$P$26,MATCH(W51,Distances!$C$15:$C$26,0),MATCH(Z51,Distances!$E$13:$P$13,0))) -> 0 | Z51: =Order!U51 -> Vesoul factory | AA51: =Order!V51 -> 0 | AB51: =Order!W51 -> 0 | AC51: =Order!X51 -> 0 | AD51: =Order!Y51 -> 0
E52: Milan | F52: =Order!D52 -> Lorry 2 | G52: =IF(OR(E52=0,H52=0),0,INDEX(Distances!$E$15:$P$26,MATCH(E52,Distances!$C$15:$C$26,0),MATCH(H52,Distances!$E$13:$P$13,0))) -> 484 | H52: =Order!E52 -> Vesoul factory | I52: =Order!F52 -> 0 | J52: =Order!G52 -> 47 | K52: =Order!H52 -> 0 | L52: =Order!I52 -> 0 | N52: 0 | O52: =Order!L52 -> 0 | P52: =IF(OR(N52=0,Q52=0),0,INDEX(Distances!$E$15:$P$26,MATCH(N52,Distances!$C$15:$C$26,0),MATCH(Q52,Distances!$E$13:$P$13,0))) -> 0 | Q52: =Order!M52 -> 0 | R52: =Order!N52 -> 0 | S52: =Order!O52 -> 0 | T52: =Order!P52 -> 0 | U52: =Order!Q52 -> 0 | W52: Paris | X52: =Order!T52 -> Lorry 3 | Y52: =IF(OR(W52=0,Z52=0),0,INDEX(Distances!$E$15:$P$26,MATCH(W52,Distances!$C$15:$C$26,0),MATCH(Z52,Distances!$E$13:$P$13,0))) -> 0 | Z52: =Order!U52 -> Paris | AA52: =Order!V52 -> 0 | AB52: =Order!W52 -> 0 | AC52: =Order!X52 -> 0 | AD52: =Order!Y52 -> 0
G54: =SUM(G28:G52)/60 -> 289.11667 | I54: =SUM(I28:I52) -> 214 | P54: =SUM(P28:P52)/60 -> 345.93333 | Y54: =SUM(Y28:Y52)/60 -> 124.66667

Sheet Graphiques_Produits
A1: Ville | B1: Produit | C1: Position x | D1: Position y | E1: Largeur | F1: Hauteur | G1: Profondeur | H1: N produits par côté | I1: N produits par hauteur | J1: Quantité début | K1: Quantité fin | L1: Nom détaillé | M1: Dernière colonne bilan : | N1: =COUNTA(Bilan!7:7)+3 -> 7 | O1: Numéro ligne bilan
A2: Kemijarvi | B2: panneau8 | C2: 1534 | D2: 400 | E2: 207 | F2: 131 | G2: 0 | H2: 1 | I2: 1 | L2: panneau_Kemijarvi
A3: Kemijarvi | B3: sirop8 | C3: 1639 | D3: 401 | E3: 12 | F3: 12 | G3: 4 | H3: 5 | I3: 30 | J3: =M3 -> 0 | K3: =J3 -> 0 | L3: cordial (pallet)_Kemijarvi | M3: =INDEX(Bilan!$1:$300,O3,$N$1) -> 0 | O3: 199
A4: Kemijarvi | B4: nectar8 | C4: 1559 | D4: 401 | E4: 12 | F4: 12 | G4: 4 | H4: 5 | I4: 30 | J4: =M4 -> 0 | K4: =J4 -> 0 | L4: nectar (pallet)_Kemijarvi | M4: =INDEX(Bilan!$1:$300,O4,$N$1) -> 0 | O4: 198
A5: Warsaw | B5: panneau9 | C5: 1385 | D5: 843 | E5: 207 | F5: 131 | G5: 0 | H5: 1 | I5: 1 | L5: panneau_Warsaw
A6: Warsaw | B6: sirop9 | C6: 1490 | D6: 844 | E6: 12 | F6: 12 | G6: 4 | H6: 5 | I6: 30 | J6: =M6 -> 0 | K6: =J6 -> 0 | L6: cordial (pallet)_Warsaw | M6: =INDEX(Bilan!$1:$300,O6,$N$1) -> 0 | O6: 211
A7: Warsaw | B7: nectar9 | C7: 1390 | D7: 844 | E7: 12 | F7: 12 | G7: 4 | H7: 5 | I7: 30 | J7: =M7 -> 0 | K7: =J7 -> 0 | L7: nectar (pallet)_Warsaw | M7: =INDEX(Bilan!$1:$300,O7,$N$1) -> 0 | O7: 210
A8: Berlin | B8: panneau10 | C8: 945 | D8: 850 | E8: 207 | F8: 131 | G8: 0 | H8: 1 | I8: 1 | L8: panneau_Berlin | M8: =INDEX(Bilan!$1:$300,O8,$N$1) -> 0
A9: Berlin | B9: sirop10 | C9: 1050 | D9: 851 | E9: 12 | F9: 12 | G9: 4 | H9: 5 | I9: 30 | J9: =M9 -> 0 | K9: =J9 -> 0 | L9: cordial (pallet)_Berlin | M9: =INDEX(Bilan!$1:$300,O9,$N$1) -> 0 | O9: 223
A10: Berlin | B10: nectar10 | C10: 950 | D10: 851 | E10: 12 | F10: 12 | G10: 4 | H10: 5 | I10: 30 | J10: =M10 -> 0 | K10: =J10 -> 0 | L10: nectar (pallet)_Berlin | M10: =INDEX(Bilan!$1:$300,O10,$N$1) -> 0 | O10: 222
A11: Arnhem factory | B11: panneau11 | C11: 625 | D11: 865 | E11: 207 | F11: 131 | G11: 0 | H11: 1 | I11: 1 | L11: panneau_Arnhem factory
A12: Arnhem factory | B12: sirop11 | C12: 730 | D12: 866 | E12: 12 | F12: 12 | G12: 4 | H12: 5 | I12: 30 | J12: =M12 -> 0 | K12: =J12 -> 0 | L12: cordial (pallet)_Arnhem factory | M12: =INDEX(Bilan!$1:$300,O12,$N$1) -> 0 | O12: 44
A13: Arnhem factory | B13: nectar11 | C13: 630 | D13: 866 | E13: 12 | F13: 12 | G13: 4 | H13: 5 | I13: 30 | J13: =M13 -> 0 | K13: =J13 -> 0 | L13: nectar (pallet)_Arnhem factory | M13: =INDEX(Bilan!$1:$300,O13,$N$1) -> 0 | O13: 42
A14: Arnhem factory | B14: cuve_nectar | C14: 500 | D14: 866 | E14: 22 | F14: 31 | G14: 8 | H14: 4 | I14: 10 | J14: =M14 -> 0 | K14: =J14 -> 0 | L14: nectar (vat)_Arnhem factory | M14: =INDEX(Bilan!$1:$300,O14,$N$1) -> 0 | O14: 43
A15: Arnhem factory | B15: pack_nectar | C15: 425 | D15: 866 | E15: 19 | F15: 23 | G15: 8 | H15: 3 | I15: 10 | J15: =M15 -> 0 | K15: =J15 -> 0 | L15: pack (batch)_Arnhem factory | M15: =INDEX(Bilan!$1:$300,O15,$N$1) -> 0 | O15: 47
A16: Arnhem factory | B16: bin_puree_Arnhem | C16: 335 | D16: 866 | E16: 24 | F16: 24 | G16: 8 | H16: 3 | I16: 10 | J16: =M16 -> 0 | K16: =J16 -> 0 | L16: puree (bin)_Arnhem factory | M16: =INDEX(Bilan!$1:$300,O16,$N$1) -> 0 | O16: 46
A17: Arnhem factory | B17: bin_concentre_Arnhem | C17: 250 | D17: 866 | E17: 24 | F17: 24 | G17: 8 | H17: 3 | I17: 10 | J17: =M17 -> 0 | K17: =J17 -> 0 | L17: concentrate (bin)_Arnhem factory | M17: =INDEX(Bilan!$1:$300,O17,$N$1) -> 0 | O17: 45
A18: Arnhem factory | B18: personne_arnhem | C18: 250 | D18: 920 | E18: 40 | F18: 74 | G18: 0 | H18: 21 | I18: 1 | J18: =M18 -> 0 | K18: =J18 -> 0 | L18: staff_Arnhem factory | M18: =INDEX(Bilan!$1:$300,O18,$N$1) -> 0 | O18: 48
A19: Le Havre | B19: panneau_le_havre | C19: 150 | D19: 960 | E19: 207 | F19: 131 | G19: 0 | H19: 1 | I19: 1 | L19: panneau_Le Havre
A20: Paris | B20: panneau1 | C20: 440 | D20: 1061 | E20: 207 | F20: 131 | G20: 0 | H20: 1 | I20: 1 | L20: panneau_Paris
A21: Paris | B21: sirop1 | C21: 450 | D21: 1062 | E21: 12 | F21: 12 | G21: 4 | H21: 5 | I21: 30 | J21: =M21 -> 0 | K21: =J21 -> 0 | L21: cordial (pallet)_Paris | M21: =INDEX(Bilan!$1:$300,O21,$N$1) -> 0 | O21: 115
A22: Paris | B22: nectar1 | C22: 350 | D22: 1062 | E22: 12 | F22: 12 | G22: 4 | H22: 5 | I22: 30 | J22: =M22 -> 0 | K22: =J22 -> 0 | L22: nectar (pallet)_Paris | M22: =INDEX(Bilan!$1:$300,O22,$N$1) -> 0 | O22: 114
A23: Vesoul factory | B23: panneau12 | C23: 643 | D23: 1100 | E23: 207 | F23: 131 | G23: 0 | H23: 1 | I23: 1 | L23: panneau_Vesoul factory
A24: Vesoul factory | B24: sirop12 | C24: 748 | D24: 1101 | E24: 12 | F24: 12 | G24: 4 | H24: 5 | I24: 30 | J24: =M24 -> 0 | K24: =J24 -> 0 | L24: cordial (pallet)_Vesoul factory | M24: =INDEX(Bilan!$1:$300,O24,$N$1) -> 0 | O24: 63
A25: Vesoul factory | B25: nectar12 | C25: 648 | D25: 1101 | E25: 12 | F25: 12 | G25: 4 | H25: 5 | I25: 30 | J25: =M25 -> 0 | K25: =J25 -> 0 | L25: nectar (pallet)_Vesoul factory | M25: =INDEX(Bilan!$1:$300,O25,$N$1) -> 0 | O25: 65
A26: Budapest | B26: panneau7 | C26: 1408 | D26: 1146 | E26: 207 | F26: 131 | G26: 0 | H26: 1 | I26: 1 | L26: panneau_Budapest
A27: Budapest | B27: sirop7 | C27: 1513 | D27: 1147 | E27: 12 | F27: 12 | G27: 4 | H27: 5 | I27: 30 | J27: =M27 -> 0 | K27: =J27 -> 0 | L27: cordial (pallet)_Budapest | M27: =INDEX(Bilan!$1:$300,O27,$N$1) -> 0 | O27: 187
A28: Budapest | B28: nectar7 | C28: 1413 | D28: 1147 | E28: 12 | F28: 12 | G28: 4 | H28: 5 | I28: 30 | J28: =M28 -> 0 | K28: =J28 -> 0 | L28: nectar (pallet)_Budapest | M28: =INDEX(Bilan!$1:$300,O28,$N$1) -> 0 | O28: 186
A29: Vesoul factory | B29: cuve_sirop | C29: 750 | D29: 1200 | E29: 22 | F29: 31 | G29: 8 | H29: 4 | I29: 10 | J29: =M29 -> 0 | K29: =J29 -> 0 | L29: cordial (vat)_Vesoul factory | M29: =INDEX(Bilan!$1:$300,O29,$N$1) -> 0 | O29: 64
A30: Vesoul factory | B30: bouteille_sirop | C30: 675 | D30: 1200 | E30: 19 | F30: 23 | G30: 8 | H30: 3 | I30: 10 | J30: =M30 -> 0 | K30: =J30 -> 0 | L30: bottle (batch)_Vesoul factory | M30: =INDEX(Bilan!$1:$300,O30,$N$1) -> 0 | O30: 68
A31: Vesoul factory | B31: sucre | C31: 600 | D31: 1200 | E31: 19 | F31: 23 | G31: 8 | H31: 3 | I31: 10 | J31: =M31 -> 0 | K31: =J31 -> 0 | L31: sugar (tonne)_Vesoul factory | M31: =INDEX(Bilan!$1:$300,O31,$N$1) -> 0 | O31: 67
A32: Vesoul factory | B32: bin_concentre_Vesoul | C32: 510 | D32: 1200 | E32: 24 | F32: 24 | G32: 8 | H32: 3 | I32: 10 | J32: =M32 -> 0 | K32: =J32 -> 0 | L32: concentrate (bin)_Vesoul factory | M32: =INDEX(Bilan!$1:$300,O32,$N$1) -> 0 | O32: 66
A33: Vesoul factory | B33: personne_vesoul | C33: 450 | D33: 1240 | E33: 40 | F33: 74 | G33: 0 | H33: 21 | I33: 1 | J33: =M33 -> 0 | K33: =J33 -> 0 | L33: staff_Vesoul factory | M33: =INDEX(Bilan!$1:$300,O33,$N$1) -> 0 | O33: 69
A34: Rauma | B34: panneau2 | C34: 1385 | D34: 524 | E34: 207 | F34: 131 | G34: 0 | H34: 1 | I34: 1 | L34: panneau_Rauma
A35: Rauma | B35: sirop2 | C35: 1490 | D35: 525 | E35: 12 | F35: 12 | G35: 4 | H35: 5 | I35: 30 | J35: =M35 -> 0 | K35: =J35 -> 0 | L35: cordial (pallet)_Rauma | M35: =INDEX(Bilan!$1:$300,O35,$N$1) -> 0 | O35: 127
A36: Rauma | B36: nectar2 | C36: 1390 | D36: 525 | E36: 12 | F36: 12 | G36: 4 | H36: 5 | I36: 30 | J36: =M36 -> 0 | K36: =J36 -> 0 | L36: nectar (pallet)_Rauma | M36: =INDEX(Bilan!$1:$300,O36,$N$1) -> 0 | O36: 126
A37: Bucharest | B37: panneau6 | C37: 1760 | D37: 1302 | E37: 207 | F37: 131 | G37: 0 | H37: 1 | I37: 1 | L37: panneau_Bucharest
A38: Bucharest | B38: sirop6 | C38: 1865 | D38: 1303 | E38: 12 | F38: 12 | G38: 4 | H38: 5 | I38: 30 | J38: =M38 -> 0 | K38: =J38 -> 0 | L38: cordial (pallet)_Bucharest | M38: =INDEX(Bilan!$1:$300,O38,$N$1) -> 0 | O38: 175
A39: Bucharest | B39: nectar6 | C39: 1765 | D39: 1303 | E39: 12 | F39: 12 | G39: 4 | H39: 5 | I39: 30 | J39: =M39 -> 0 | K39: =J39 -> 0 | L39: nectar (pallet)_Bucharest | M39: =INDEX(Bilan!$1:$300,O39,$N$1) -> 0 | O39: 174
A40: Milan | B40: panneau4 | C40: 865 | D40: 1306 | E40: 207 | F40: 131 | G40: 0 | H40: 1 | I40: 1 | L40: panneau_Milan
A41: Milan | B41: sirop4 | C41: 970 | D41: 1307 | E41: 12 | F41: 12 | G41: 4 | H41: 5 | I41: 30 | J41: =M41 -> 0 | K41: =J41 -> 0 | L41: cordial (pallet)_Milan | M41: =INDEX(Bilan!$1:$300,O41,$N$1) -> 0 | O41: 151
A42: Milan | B42: nectar4 | C42: 870 | D42: 1307 | E42: 12 | F42: 12 | G42: 4 | H42: 5 | I42: 30 | J42: =M42 -> 0 | K42: =J42 -> 0 | L42: nectar (pallet)_Milan | M42: =INDEX(Bilan!$1:$300,O42,$N$1) -> 0 | O42: 150
A43: Atlantique | B43: panneau_atlantique | C43: 5 | D43: 1320 | E43: 207 | F43: 131 | G43: 0 | H43: 1 | I43: 1 | L43: panneau_Atlantique
A44: Rome | B44: panneau5 | C44: 1003 | D44: 1510 | E44: 207 | F44: 131 | G44: 0 | H44: 1 | I44: 1 | L44: panneau_Rome
A45: Rome | B45: sirop5 | C45: 1108 | D45: 1511 | E45: 12 | F45: 12 | G45: 4 | H45: 5 | I45: 30 | J45: =M45 -> 0 | K45: =J45 -> 0 | L45: cordial (pallet)_Rome | M45: =INDEX(Bilan!$1:$300,O45,$N$1) -> 0 | O45: 163
A46: Rome | B46: nectar5 | C46: 1008 | D46: 1511 | E46: 12 | F46: 12 | G46: 4 | H46: 5 | I46: 30 | J46: =M46 -> 0 | K46: =J46 -> 0 | L46: nectar (pallet)_Rome | M46: =INDEX(Bilan!$1:$300,O46,$N$1) -> 0 | O46: 162
A47: Madrid | B47: panneau3 | C47: 120 | D47: 1569 | E47: 207 | F47: 131 | G47: 0 | H47: 1 | I47: 1 | L47: panneau_Madrid
A48: Auckland | B48: panneau13 | C48: 2180 | D48: 1570 | E48: 207 | F48: 131 | G48: 0 | H48: 1 | I48: 1 | L48: panneau_Auckland
A49: Auckland | B49: bin_puree_Auckland | C49: 2100 | D49: 1570 | E49: 24 | F49: 24 | G49: 8 | H49: 3 | I49: 10 | J49: =M49 -> 0 | K49: =J49 -> 0 | L49: puree (bin)_Auckland factory | M49: =INDEX(Bilan!$1:$300,O49,$N$1) -> 0 | O49: 12
A50: Auckland | B50: bin_concentre_Auckland | C50: 2015 | D50: 1570 | E50: 24 | F50: 24 | G50: 8 | H50: 3 | I50: 10 | J50: =M50 -> 0 | K50: =J50 -> 0 | L50: concentrate (bin)_Auckland factory | M50: =INDEX(Bilan!$1:$300,O50,$N$1) -> 0 | O50: 11
A51: Madrid | B51: sirop3 | C51: 225 | D51: 1570 | E51: 12 | F51: 12 | G51: 4 | H51: 5 | I51: 30 | J51: =M51 -> 0 | K51: =J51 -> 0 | L51: cordial (pallet)_Madrid | M51: =INDEX(Bilan!$1:$300,O51,$N$1) -> 0 | O51: 139
A52: Madrid | B52: nectar3 | C52: 125 | D52: 1570 | E52: 12 | F52: 12 | G52: 4 | H52: 5 | I52: 30 | J52: =M52 -> 0 | K52: =J52 -> 0 | L52: nectar (pallet)_Madrid | M52: =INDEX(Bilan!$1:$300,O52,$N$1) -> 0 | O52: 138
A53: Auckland | B53: personne_auckland | C53: 1900 | D53: 1640 | E53: 40 | F53: 74 | G53: 0 | H53: 21 | I53: 1 | J53: =M53 -> 0 | K53: =J53 -> 0 | L53: staff_Auckland factory | M53: =INDEX(Bilan!$1:$300,O53,$N$1) -> 0 | O53: 13
A54: Pacifique | B54: panneau_pacifique | C54: 1400 | D54: 1820 | E54: 207 | F54: 131 | G54: 0 | H54: 1 | I54: 1 | L54: panneau_Pacifique
